Workbook

Sheet UPSTREAM
A1: ZONA | B1: 45992 | C1: =+B1+1 -> 45993 | D1: =+C1+1 -> 45994 | E1: =+D1+1 -> 45995 | F1: =+E1+1 -> 45996 | G1: =+F1+1 -> 45997 | H1: =+G1+1 -> 45998 | I1: =+H1+1 -> 45999 | J1: ACUMULADO S1 | K1: =+I1+1 -> 46000 | L1: =+K1+1 -> 46001 | M1: =+L1+1 -> 46002 | N1: =+M1+1 -> 46003 | O1: =+N1+1 -> 46004 | P1: =+O1+1 -> 46005 | Q1: ACUMULADO S2 | R1: =+P1+1 -> 46006 | S1: =+R1+1 -> 46007 | T1: =+S1+1 -> 46008 | U1: =+T1+1 -> 46009 | V1: =+U1+1 -> 46010 | W1: =+V1+1 -> 46011 | X1: =+W1+1 -> 46012 | Y1: ACUMULADO S3 | Z1: =+X1+1 -> 46013 | AA1: =+Z1+1 -> 46014 | AB1: =+AA1+1 -> 46015 | AC1: =+AB1+1 -> 46016 | AD1: =+AC1+1 -> 46017 | AE1: =+AD1+1 -> 46018 | AF1: =+AE1+1 -> 46019 | AG1: ACUMULADO S4 | AH1: =+AF1+1 -> 46020 | AI1: =+AH1+1 -> 46021 | AJ1: =+AI1+1 -> 46022 | AK1: ACUMULADO DIC 25
A2: Codazzi Proyección | B2: =+HLOOKUP(B$1,'[1]RFF Resumen'!$C$16:$AG$153,3,0)+HLOOKUP(B$1,'[1]RFF Resumen'!$C$16:$AG$153,6,0) -> 525 | C2: =+HLOOKUP(C$1,'[1]RFF Resumen'!$C$16:$AG$153,3,0)+HLOOKUP(C$1,'[1]RFF Resumen'!$C$16:$AG$153,6,0) -> 597 | D2: =+HLOOKUP(D$1,'[1]RFF Resumen'!$C$16:$AG$153,3,0)+HLOOKUP(D$1,'[1]RFF Resumen'!$C$16:$AG$153,6,0) -> 659 | E2: =+HLOOKUP(E$1,'[1]RFF Resumen'!$C$16:$AG$153,3,0)+HLOOKUP(E$1,'[1]RFF Resumen'!$C$16:$AG$153,6,0) -> 675 | F2: =+HLOOKUP(F$1,'[1]RFF Resumen'!$C$16:$AG$153,3,0)+HLOOKUP(F$1,'[1]RFF Resumen'!$C$16:$AG$153,6,0) -> 743 | G2: =+HLOOKUP(G$1,'[1]RFF Resumen'!$C$16:$AG$153,3,0)+HLOOKUP(G$1,'[1]RFF Resumen'!$C$16:$AG$153,6,0) -> 789 | H2: =+HLOOKUP(H$1,'[1]RFF Resumen'!$C$16:$AG$153,3,0)+HLOOKUP(H$1,'[1]RFF Resumen'!$C$16:$AG$153,6,0) -> 300 | I2: =+HLOOKUP(I$1,'[1]RFF Resumen'!$C$16:$AG$153,3,0)+HLOOKUP(I$1,'[1]RFF Resumen'!$C$16:$AG$153,6,0) -> 50 | J2: =+SUM(B2:I2) -> 4338 | K2: =+HLOOKUP(K$1,'[1]RFF Resumen'!$C$16:$AG$153,3,0)+HLOOKUP(K$1,'[1]RFF Resumen'!$C$16:$AG$153,6,0) -> 560 | L2: =+HLOOKUP(L$1,'[1]RFF Resumen'!$C$16:$AG$153,3,0)+HLOOKUP(L$1,'[1]RFF Resumen'!$C$16:$AG$153,6,0) -> 669 | M2: =+HLOOKUP(M$1,'[1]RFF Resumen'!$C$16:$AG$153,3,0)+HLOOKUP(M$1,'[1]RFF Resumen'!$C$16:$AG$153,6,0) -> 655 | N2: =+HLOOKUP(N$1,'[1]RFF Resumen'!$C$16:$AG$153,3,0)+HLOOKUP(N$1,'[1]RFF Resumen'!$C$16:$AG$153,6,0) -> 729 | O2: =+HLOOKUP(O$1,'[1]RFF Resumen'!$C$16:$AG$153,3,0)+HLOOKUP(O$1,'[1]RFF Resumen'!$C$16:$AG$153,6,0) -> 740 | P2: =+HLOOKUP(P$1,'[1]RFF Resumen'!$C$16:$AG$153,3,0)+HLOOKUP(P$1,'[1]RFF Resumen'!$C$16:$AG$153,6,0) -> 510 | Q2: =+J2+SUM(K2:P2) -> 8201 | R2: =+HLOOKUP(R$1,'[1]RFF Resumen'!$C$16:$AG$153,3,0)+HLOOKUP(R$1,'[1]RFF Resumen'!$C$16:$AG$153,6,0) -> 715 | S2: =+HLOOKUP(S$1,'[1]RFF Resumen'!$C$16:$AG$153,3,0)+HLOOKUP(S$1,'[1]RFF Resumen'!$C$16:$AG$153,6,0) -> 629 | T2: =+HLOOKUP(T$1,'[1]RFF Resumen'!$C$16:$AG$153,3,0)+HLOOKUP(T$1,'[1]RFF Resumen'!$C$16:$AG$153,6,0) -> 638 | U2: =+HLOOKUP(U$1,'[1]RFF Resumen'!$C$16:$AG$153,3,0)+HLOOKUP(U$1,'[1]RFF Resumen'!$C$16:$AG$153,6,0) -> 654 | V2: =+HLOOKUP(V$1,'[1]RFF Resumen'!$C$16:$AG$153,3,0)+HLOOKUP(V$1,'[1]RFF Resumen'!$C$16:$AG$153,6,0) -> 729 | W2: =+HLOOKUP(W$1,'[1]RFF Resumen'!$C$16:$AG$153,3,0)+HLOOKUP(W$1,'[1]RFF Resumen'!$C$16:$AG$153,6,0) -> 710 | X2: =+HLOOKUP(X$1,'[1]RFF Resumen'!$C$16:$AG$153,3,0)+HLOOKUP(X$1,'[1]RFF Resumen'!$C$16:$AG$153,6,0) -> 384 | Y2: =+Q2+SUM(R2:X2) -> 12660 | Z2: =+HLOOKUP(Z$1,'[1]RFF Resumen'!$C$16:$AG$153,3,0)+HLOOKUP(Z$1,'[1]RFF Resumen'!$C$16:$AG$153,6,0) -> 700 | AA2: =+HLOOKUP(AA$1,'[1]RFF Resumen'!$C$16:$AG$153,3,0)+HLOOKUP(AA$1,'[1]RFF Resumen'!$C$16:$AG$153,6,0) -> 840 | AB2: =+HLOOKUP(AB$1,'[1]RFF Resumen'!$C$16:$AG$153,3,0)+HLOOKUP(AB$1,'[1]RFF Resumen'!$C$16:$AG$153,6,0) -> 219 | AC2: =+HLOOKUP(AC$1,'[1]RFF Resumen'!$C$16:$AG$153,3,0)+HLOOKUP(AC$1,'[1]RFF Resumen'!$C$16:$AG$153,6,0) -> 0 | AD2: =+HLOOKUP(AD$1,'[1]RFF Resumen'!$C$16:$AG$153,3,0)+HLOOKUP(AD$1,'[1]RFF Resumen'!$C$16:$AG$153,6,0) -> 590 | AE2: =+HLOOKUP(AE$1,'[1]RFF Resumen'!$C$16:$AG$153,3,0)+HLOOKUP(AE$1,'[1]RFF Resumen'!$C$16:$AG$153,6,0) -> 690 | AF2: =+HLOOKUP(AF$1,'[1]RFF Resumen'!$C$16:$AG$153,3,0)+HLOOKUP(AF$1,'[1]RFF Resumen'!$C$16:$AG$153,6,0) -> 569 | AG2: =+Y2+SUM(Z2:AF2) -> 16268 | AH2: =+HLOOKUP(AH$1,'[1]RFF Resumen'!$C$16:$AG$153,3,0)+HLOOKUP(AH$1,'[1]RFF Resumen'!$C$16:$AG$153,6,0) -> 740 | AI2: =+HLOOKUP(AI$1,'[1]RFF Resumen'!$C$16:$AG$153,3,0)+HLOOKUP(AI$1,'[1]RFF Resumen'!$C$16:$AG$153,6,0) -> 922 | AJ2: =+HLOOKUP(AJ$1,'[1]RFF Resumen'!$C$16:$AG$153,3,0)+HLOOKUP(AJ$1,'[1]RFF Resumen'!$C$16:$AG$153,6,0) -> 70 | AK2: =+AG2+SUM(AH2:AJ2) -> 18000
A3: Codazzi Real | B3: =(IFERROR(VLOOKUP(B$1,[2]Hoja1!$A$2:$E$32,2,0)/1000,0)) -> 359.35 | C3: =(IFERROR(VLOOKUP(C$1,[2]Hoja1!$A$2:$E$32,2,0)/1000,0)) -> 412.66 | D3: =(IFERROR(VLOOKUP(D$1,[2]Hoja1!$A$2:$E$32,2,0)/1000,0)) -> 832.23 | E3: =(IFERROR(VLOOKUP(E$1,[2]Hoja1!$A$2:$E$32,2,0)/1000,0)) -> 757.85 | F3: =(IFERROR(VLOOKUP(F$1,[2]Hoja1!$A$2:$E$32,2,0)/1000,0)) -> 824.73 | G3: =(IFERROR(VLOOKUP(G$1,[2]Hoja1!$A$2:$E$32,2,0)/1000,0)) -> 511.17 | H3: =(IFERROR(VLOOKUP(H$1,[2]Hoja1!$A$2:$E$32,2,0)/1000,0)) -> 694.46 | I3: =(IFERROR(VLOOKUP(I$1,[2]Hoja1!$A$2:$E$32,2,0)/1000,0)) -> 192.89 | J3: =+SUM(B3:I3) -> 4585.34 | K3: =(IFERROR(VLOOKUP(K$1,[2]Hoja1!$A$2:$E$32,2,0)/1000,0)) -> 367.07 | L3: =(IFERROR(VLOOKUP(L$1,[2]Hoja1!$A$2:$E$32,2,0)/1000,0)) -> 588.51 | M3: =(IFERROR(VLOOKUP(M$1,[2]Hoja1!$A$2:$E$32,2,0)/1000,0)) -> 750.68 | N3: =(IFERROR(VLOOKUP(N$1,[2]Hoja1!$A$2:$E$32,2,0)/1000,0)) -> 0 | O3: =(IFERROR(VLOOKUP(O$1,[2]Hoja1!$A$2:$E$32,2,0)/1000,0)) -> 0 | P3: =(IFERROR(VLOOKUP(P$1,[2]Hoja1!$A$2:$E$32,2,0)/1000,0)) -> 0 | Q3: =+J3+SUM(K3:P3) -> 6291.6 | R3: =(IFERROR(VLOOKUP(R$1,[2]Hoja1!$A$2:$E$32,2,0)/1000,0)) -> 0 | S3: =(IFERROR(VLOOKUP(S$1,[2]Hoja1!$A$2:$E$32,2,0)/1000,0)) -> 0 | T3: =(IFERROR(VLOOKUP(T$1,[2]Hoja1!$A$2:$E$32,2,0)/1000,0)) -> 0 | U3: =IFERROR(VLOOKUP(U$1,[2]Hoja1!$A$2:$E$32,2,0)/1000,0) -> 0 | V3: =IFERROR(VLOOKUP(V$1,[2]Hoja1!$A$2:$E$32,2,0)/1000,0) -> 0 | W3: =IFERROR(VLOOKUP(W$1,[2]Hoja1!$A$2:$E$32,2,0)/1000,0) -> 0 | X3: =IFERROR(VLOOKUP(X$1,[2]Hoja1!$A$2:$E$32,2,0)/1000,0) -> 0 | Y3: =+Q3+SUM(R3:X3) -> 6291.6 | Z3: =IFERROR(VLOOKUP(Z$1,[2]Hoja1!$A$2:$E$32,2,0)/1000,0) -> 0 | AA3: =IFERROR(VLOOKUP(AA$1,[2]Hoja1!$A$2:$E$32,2,0)/1000,0) -> 0 | AB3: =(IFERROR(VLOOKUP(AB$1,[2]Hoja1!$A$2:$E$32,2,0)/1000,0)) -> 0 | AC3: =(IFERROR(VLOOKUP(AC$1,[2]Hoja1!$A$2:$E$32,2,0)/1000,0)) -> 0 | AD3: =(IFERROR(VLOOKUP(AD$1,[2]Hoja1!$A$2:$E$32,2,0)/1000,0)) -> 0 | AE3: =(IFERROR(VLOOKUP(AE$1,[2]Hoja1!$A$2:$E$32,2,0)/1000,0)) -> 0 | AF3: =(IFERROR(VLOOKUP(AF$1,[2]Hoja1!$A$2:$E$32,2,0)/1000,0)) -> 0 | AG3: =+Y3+SUM(Z3:AF3) -> 6291.6 | AH3: =(IFERROR(VLOOKUP(AH$1,[2]Hoja1!$A$2:$E$32,2,0)/1000,0)) -> 0 | AI3: =(IFERROR(VLOOKUP(AI$1,[2]Hoja1!$A$2:$E$32,2,0)/1000,0)) -> 0 | AJ3: =(IFERROR(VLOOKUP(AJ$1,[2]Hoja1!$A$2:$E$32,2,0)/1000,0)) -> 0 | AK3: =+AG3+SUM(AH3:AJ3) -> 6291.6
A4: % Cumplimiento | B4: =IFERROR(+B3/B2,0) -> 0.68447619 | C4: =IFERROR(+C3/C2,0) -> 0.69122278 | D4: =IFERROR(+D3/D2,0) -> 1.262868 | E4: =IFERROR(+E3/E2,0) -> 1.1227407 | F4: =IFERROR(+F3/F2,0) -> 1.11 | G4: =IFERROR(+G3/G2,0) -> 0.64787072 | H4: =IFERROR(+H3/H2,0) -> 2.3148667 | I4: =IFERROR(+I3/I2,0) -> 3.8578 | ... AK4: =IFERROR(+AK3/AK2,0) -> 0.34953333
A5: Ext Codazzi Proy | B5: =+HLOOKUP(B$1,[3]Resumen!$B$1:$AH$27,2,0) -> 600 | C5: =+HLOOKUP(C$1,[3]Resumen!$B$1:$AH$27,2,0) -> 600 | D5: =+HLOOKUP(D$1,[3]Resumen!$B$1:$AH$27,2,0) -> 650 | E5: =+HLOOKUP(E$1,[3]Resumen!$B$1:$AH$27,2,0) -> 700 | F5: =+HLOOKUP(F$1,[3]Resumen!$B$1:$AH$27,2,0) -> 700 | G5: =+HLOOKUP(G$1,[3]Resumen!$B$1:$AH$27,2,0) -> 800 | H5: =+HLOOKUP(H$1,[3]Resumen!$B$1:$AH$27,2,0) -> 300 | I5: =+HLOOKUP(I$1,[3]Resumen!$B$1:$AH$27,2,0) -> 0 | J5: =+SUM(B5:I5) -> 4350 | K5: =+HLOOKUP(K$1,[3]Resumen!$B$1:$AH$27,2,0) -> 400 | L5: =+HLOOKUP(L$1,[3]Resumen!$B$1:$AH$27,2,0) -> 750 | M5: =+HLOOKUP(M$1,[3]Resumen!$B$1:$AH$27,2,0) -> 750 | N5: =+HLOOKUP(N$1,[3]Resumen!$B$1:$AH$27,2,0) -> 750 | O5: =+HLOOKUP(O$1,[3]Resumen!$B$1:$AH$27,2,0) -> 750 | P5: =+HLOOKUP(P$1,[3]Resumen!$B$1:$AH$27,2,0) -> 400 | Q5: =+J5+SUM(K5:P5) -> 8150 | R5: =+HLOOKUP(R$1,[3]Resumen!$B$1:$AH$27,2,0) -> 400 | S5: =+HLOOKUP(S$1,[3]Resumen!$B$1:$AH$27,2,0) -> 750 | T5: =+HLOOKUP(T$1,[3]Resumen!$B$1:$AH$27,2,0) -> 750 | U5: =+HLOOKUP(U$1,[3]Resumen!$B$1:$AH$27,2,0) -> 750 | V5: =+HLOOKUP(V$1,[3]Resumen!$B$1:$AH$27,2,0) -> 750 | W5: =+HLOOKUP(W$1,[3]Resumen!$B$1:$AH$27,2,0) -> 750 | X5: =+HLOOKUP(X$1,[3]Resumen!$B$1:$AH$27,2,0) -> 400 | Y5: =+Q5+SUM(R5:X5) -> 12700 | Z5: =+HLOOKUP(Z$1,[3]Resumen!$B$1:$AH$27,2,0) -> 400 | AA5: =+HLOOKUP(AA$1,[3]Resumen!$B$1:$AH$27,2,0) -> 750 | AB5: =+HLOOKUP(AB$1,[3]Resumen!$B$1:$AH$27,2,0) -> 400 | AC5: =+HLOOKUP(AC$1,[3]Resumen!$B$1:$AH$27,2,0) -> 0 | AD5: =+HLOOKUP(AD$1,[3]Resumen!$B$1:$AH$27,2,0) -> 750 | AE5: =+HLOOKUP(AE$1,[3]Resumen!$B$1:$AH$27,2,0) -> 750 | AF5: =+HLOOKUP(AF$1,[3]Resumen!$B$1:$AH$27,2,0) -> 400 | AG5: =+Y5+SUM(Z5:AF5) -> 16150 | AH5: =+HLOOKUP(AH$1,[3]Resumen!$B$1:$AH$27,2,0) -> 750 | AI5: =+HLOOKUP(AI$1,[3]Resumen!$B$1:$AH$27,2,0) -> 750 | AJ5: =+HLOOKUP(AJ$1,[3]Resumen!$B$1:$AH$27,2,0) -> 600 | AK5: =+AG5+SUM(AH5:AJ5) -> 18250
A6: Ext Codazzi Real | B6: =+IFERROR(VLOOKUP(B$1,'[4]Base de Datos'!$A$5:$EI$35,36,0)/1000,0) -> 701.25 | C6: =+IFERROR(VLOOKUP(C$1,'[4]Base de Datos'!$A$5:$EI$35,36,0)/1000,0) -> 319 | D6: =+IFERROR(VLOOKUP(D$1,'[4]Base de Datos'!$A$5:$EI$35,36,0)/1000,0) -> 726 | E6: =+IFERROR(VLOOKUP(E$1,'[4]Base de Datos'!$A$5:$EI$35,36,0)/1000,0) -> 792 | F6: =+IFERROR(VLOOKUP(F$1,'[4]Base de Datos'!$A$5:$EI$35,36,0)/1000,0) -> 759 | G6: =+IFERROR(VLOOKUP(G$1,'[4]Base de Datos'!$A$5:$EI$35,36,0)/1000,0) -> 555.5 | H6: =+IFERROR(VLOOKUP(H$1,'[4]Base de Datos'!$A$5:$EI$35,36,0)/1000,0) -> 830.5 | I6: =+IFERROR(VLOOKUP(I$1,'[4]Base de Datos'!$A$5:$EI$35,36,0)/1000,0) -> 527.609 | J6: =+SUM(B6:I6) -> 5210.859 | K6: =+IFERROR(VLOOKUP(K$1,'[4]Base de Datos'!$A$5:$EI$35,36,0)/1000,0) -> 187 | L6: =+IFERROR(VLOOKUP(L$1,'[4]Base de Datos'!$A$5:$EI$35,36,0)/1000,0) -> 613.25 | M6: =+IFERROR(VLOOKUP(M$1,'[4]Base de Datos'!$A$5:$EI$35,36,0)/1000,0) -> 728.75 | N6: =+IFERROR(VLOOKUP(N$1,'[4]Base de Datos'!$A$5:$EI$35,36,0)/1000,0) -> 0 | O6: =+IFERROR(VLOOKUP(O$1,'[4]Base de Datos'!$A$5:$EI$35,36,0)/1000,0) -> 0 | P6: =+IFERROR(VLOOKUP(P$1,'[4]Base de Datos'!$A$5:$EI$35,36,0)/1000,0) -> 0 | Q6: =+J6+SUM(K6:P6) -> 6739.859 | R6: =+IFERROR(VLOOKUP(R$1,'[4]Base de Datos'!$A$5:$EI$35,36,0)/1000,0) -> 0 | S6: =+IFERROR(VLOOKUP(S$1,'[4]Base de Datos'!$A$5:$EI$35,36,0)/1000,0) -> 0 | T6: =+IFERROR(VLOOKUP(T$1,'[4]Base de Datos'!$A$5:$EI$35,36,0)/1000,0) -> 0 | U6: =+IFERROR(VLOOKUP(U$1,'[4]Base de Datos'!$A$5:$EI$35,36,0)/1000,0) -> 0 | V6: =+IFERROR(VLOOKUP(V$1,'[4]Base de Datos'!$A$5:$EI$35,36,0)/1000,0) -> 0 | W6: =+IFERROR(VLOOKUP(W$1,'[4]Base de Datos'!$A$5:$EI$35,36,0)/1000,0) -> 0 | X6: =+IFERROR(VLOOKUP(X$1,'[4]Base de Datos'!$A$5:$EI$35,36,0)/1000,0) -> 0 | Y6: =+Q6+SUM(R6:X6) -> 6739.859 | Z6: =+IFERROR(VLOOKUP(Z$1,'[4]Base de Datos'!$A$5:$EI$35,36,0)/1000,0) -> 0 | AA6: =+IFERROR(VLOOKUP(AA$1,'[4]Base de Datos'!$A$5:$EI$35,36,0)/1000,0) -> 0 | AB6: =+IFERROR(VLOOKUP(AB$1,'[4]Base de Datos'!$A$5:$EI$35,36,0)/1000,0) -> 0 | AC6: =+IFERROR(VLOOKUP(AC$1,'[4]Base de Datos'!$A$5:$EI$35,36,0)/1000,0) -> 0 | AD6: =+IFERROR(VLOOKUP(AD$1,'[4]Base de Datos'!$A$5:$EI$35,36,0)/1000,0) -> 0 | AE6: =+IFERROR(VLOOKUP(AE$1,'[4]Base de Datos'!$A$5:$EI$35,36,0)/1000,0) -> 0 | AF6: =+IFERROR(VLOOKUP(AF$1,'[4]Base de Datos'!$A$5:$EI$35,36,0)/1000,0) -> 0 | AG6: =+Y6+SUM(Z6:AF6) -> 6739.859 | AH6: =+IFERROR(VLOOKUP(AH$1,'[4]Base de Datos'!$A$5:$EI$35,36,0)/1000,0) -> 0 | AI6: =+IFERROR(VLOOKUP(AI$1,'[4]Base de Datos'!$A$5:$EI$35,36,0)/1000,0) -> 0 | AJ6: =+IFERROR(VLOOKUP(AJ$1,'[4]Base de Datos'!$A$5:$EI$35,36,0)/1000,0) -> 0 | AK6: =+AG6+SUM(AH6:AJ6) -> 6739.859 | AL6: =+AG6/AG5 -> 0.41732873 | AM6: =1-15% -> 0.85
A7: CPO | B7: =IFERROR(VLOOKUP(B$1,'[4]Base de Datos'!$A$5:$EI$35,34,0)/1000,0) -> 162.948 | C7: =IFERROR(VLOOKUP(C$1,'[4]Base de Datos'!$A$5:$EI$35,34,0)/1000,0) -> 64.56 | D7: =IFERROR(VLOOKUP(D$1,'[4]Base de Datos'!$A$5:$EI$35,34,0)/1000,0) -> 155.836 | E7: =IFERROR(VLOOKUP(E$1,'[4]Base de Datos'!$A$5:$EI$35,34,0)/1000,0) -> 158.532 | F7: =IFERROR(VLOOKUP(F$1,'[4]Base de Datos'!$A$5:$EI$35,34,0)/1000,0) -> 159.892 | G7: =IFERROR(VLOOKUP(G$1,'[4]Base de Datos'!$A$5:$EI$35,34,0)/1000,0) -> 115.172 | H7: =IFERROR(VLOOKUP(H$1,'[4]Base de Datos'!$A$5:$EI$35,34,0)/1000,0) -> 170.816 | I7: =IFERROR(VLOOKUP(I$1,'[4]Base de Datos'!$A$5:$EI$35,34,0)/1000,0) -> 122.624 | J7: =+SUM(B7:I7) -> 1110.38 | K7: =IFERROR(VLOOKUP(K$1,'[4]Base de Datos'!$A$5:$EI$35,34,0)/1000,0) -> 36.28 | L7: =IFERROR(VLOOKUP(L$1,'[4]Base de Datos'!$A$5:$EI$35,34,0)/1000,0) -> 134.408 | M7: =IFERROR(VLOOKUP(M$1,'[4]Base de Datos'!$A$5:$EI$35,34,0)/1000,0) -> 162.652 | N7: =IFERROR(VLOOKUP(N$1,'[4]Base de Datos'!$A$5:$EI$35,34,0)/1000,0) -> 0 | O7: =IFERROR(VLOOKUP(O$1,'[4]Base de Datos'!$A$5:$EI$35,34,0)/1000,0) -> 0 | P7: =IFERROR(VLOOKUP(P$1,'[4]Base de Datos'!$A$5:$EI$35,34,0)/1000,0) -> 0 | Q7: =+J7+SUM(K7:P7) -> 1443.72 | R7: =IFERROR(VLOOKUP(R$1,'[4]Base de Datos'!$A$5:$EI$35,34,0)/1000,0) -> 0 | S7: =IFERROR(VLOOKUP(S$1,'[4]Base de Datos'!$A$5:$EI$35,34,0)/1000,0) -> 0 | T7: =IFERROR(VLOOKUP(T$1,'[4]Base de Datos'!$A$5:$EI$35,34,0)/1000,0) -> 0 | U7: =IFERROR(VLOOKUP(U$1,'[4]Base de Datos'!$A$5:$EI$35,34,0)/1000,0) -> 0 | V7: =IFERROR(VLOOKUP(V$1,'[4]Base de Datos'!$A$5:$EI$35,34,0)/1000,0) -> 0 | W7: =IFERROR(VLOOKUP(W$1,'[4]Base de Datos'!$A$5:$EI$35,34,0)/1000,0) -> 0 | X7: =IFERROR(VLOOKUP(X$1,'[4]Base de Datos'!$A$5:$EI$35,34,0)/1000,0) -> 0 | Y7: =+Q7+SUM(R7:X7) -> 1443.72 | Z7: =IFERROR(VLOOKUP(Z$1,'[4]Base de Datos'!$A$5:$EI$35,34,0)/1000,0) -> 0 | AA7: =IFERROR(VLOOKUP(AA$1,'[4]Base de Datos'!$A$5:$EI$35,34,0)/1000,0) -> 0 | AB7: =IFERROR(VLOOKUP(AB$1,'[4]Base de Datos'!$A$5:$EI$35,34,0)/1000,0) -> 0 | AC7: =IFERROR(VLOOKUP(AC$1,'[4]Base de Datos'!$A$5:$EI$35,34,0)/1000,0) -> 0 | AD7: =IFERROR(VLOOKUP(AD$1,'[4]Base de Datos'!$A$5:$EI$35,34,0)/1000,0) -> 0 | AE7: =IFERROR(VLOOKUP(AE$1,'[4]Base de Datos'!$A$5:$EI$35,34,0)/1000,0) -> 0 | AF7: =IFERROR(VLOOKUP(AF$1,'[4]Base de Datos'!$A$5:$EI$35,34,0)/1000,0) -> 0 | AG7: =+Y7+SUM(Z7:AF7) -> 1443.72 | AH7: =IFERROR(VLOOKUP(AH$1,'[4]Base de Datos'!$A$5:$EI$35,34,0)/1000,0) -> 0 | AI7: =IFERROR(VLOOKUP(AI$1,'[4]Base de Datos'!$A$5:$EI$35,34,0)/1000,0) -> 12.417 | AJ7: =IFERROR(VLOOKUP(AJ$1,'[4]Base de Datos'!$A$5:$EI$35,34,0)/1000,0) -> 11.059 | AK7: =+AG7+SUM(AH7:AJ7) -> 1467.196
A8: =+_xlfn.CONCAT("TEA% ", B44,"%") -> TEA% 21.6% | B8: =IFERROR(+B7/B6,0) -> 0.23236791 | C8: =IFERROR(+C7/C6,0) -> 0.20238245 | D8: =IFERROR(+D7/D6,0) -> 0.21465014 | E8: =IFERROR(+E7/E6,0) -> 0.20016667 | F8: =IFERROR(+F7/F6,0) -> 0.2106614 | G8: =IFERROR(+G7/G6,0) -> 0.20733033 | H8: =IFERROR(+H7/H6,0) -> 0.20567851 | I8: =IFERROR(+I7/I6,0) -> 0.23241453 | ... Y8: =IFERROR(+Y7/Y6,0) -> 0.21420626 | Z8: 0.216 | AA8: 0.216 | AB8: =IFERROR(+AB7/AB6,0) -> 0 | AC8: =IFERROR(+AC7/AC6,0) -> 0 | AD8: =IFERROR(+AD7/AD6,0) -> 0 | AE8: =IFERROR(+AE7/AE6,0) -> 0 | AF8: =IFERROR(+AF7/AF6,0) -> 0 | AG8: =IFERROR(+AG7/AG6,0) -> 0.21420626 | AH8: =IFERROR(+AH7/AH6,0) -> 0 | AI8: =IFERROR(+AI7/AI6,0) -> 0 | ... AK8: =IFERROR(+AK7/AK6,0) -> 0.21768942
A9: MLB Proyección | B9: =+HLOOKUP(B$1,'[1]RFF Resumen'!$C$16:$AG$153,42,0) -> 74.194438 | C9: =+HLOOKUP(C$1,'[1]RFF Resumen'!$C$16:$AG$153,42,0) -> 131.18888 | D9: =+HLOOKUP(D$1,'[1]RFF Resumen'!$C$16:$AG$153,42,0) -> 188.1444 | E9: =+HLOOKUP(E$1,'[1]RFF Resumen'!$C$16:$AG$153,42,0) -> 185.84812 | F9: =+HLOOKUP(F$1,'[1]RFF Resumen'!$C$16:$AG$153,42,0) -> 176.54624 | G9: =+HLOOKUP(G$1,'[1]RFF Resumen'!$C$16:$AG$153,42,0) -> 187.05464 | H9: =+HLOOKUP(H$1,'[1]RFF Resumen'!$C$16:$AG$153,42,0) -> 38.67605 | I9: =+HLOOKUP(I$1,'[1]RFF Resumen'!$C$16:$AG$153,42,0) -> 14.911501 | J9: =+SUM(B9:I9) -> 996.56427 | K9: =+HLOOKUP(K$1,'[1]RFF Resumen'!$C$16:$AG$153,42,0) -> 109.66612 | L9: =+HLOOKUP(L$1,'[1]RFF Resumen'!$C$16:$AG$153,42,0) -> 213.94057 | M9: =+HLOOKUP(M$1,'[1]RFF Resumen'!$C$16:$AG$153,42,0) -> 261.61757 | N9: =+HLOOKUP(N$1,'[1]RFF Resumen'!$C$16:$AG$153,42,0) -> 334.97398 | O9: =+HLOOKUP(O$1,'[1]RFF Resumen'!$C$16:$AG$153,42,0) -> 299.2532 | P9: =+HLOOKUP(P$1,'[1]RFF Resumen'!$C$16:$AG$153,42,0) -> 100.55884 | Q9: =+J9+SUM(K9:P9) -> 2316.5746 | R9: =+HLOOKUP(R$1,'[1]RFF Resumen'!$C$16:$AG$153,42,0) -> 134.96412 | S9: =+HLOOKUP(S$1,'[1]RFF Resumen'!$C$16:$AG$153,42,0) -> 242.35995 | T9: =+HLOOKUP(T$1,'[1]RFF Resumen'!$C$16:$AG$153,42,0) -> 281.29552 | U9: =+HLOOKUP(U$1,'[1]RFF Resumen'!$C$16:$AG$153,42,0) -> 281.98829 | V9: =+HLOOKUP(V$1,'[1]RFF Resumen'!$C$16:$AG$153,42,0) -> 239.20743 | W9: =+HLOOKUP(W$1,'[1]RFF Resumen'!$C$16:$AG$153,42,0) -> 296.26415 | X9: =+HLOOKUP(X$1,'[1]RFF Resumen'!$C$16:$AG$153,42,0) -> 98.729603 | Y9: =+Q9+SUM(R9:X9) -> 3891.3836 | Z9: =+HLOOKUP(Z$1,'[1]RFF Resumen'!$C$16:$AG$153,42,0) -> 208.34388 | AA9: =+HLOOKUP(AA$1,'[1]RFF Resumen'!$C$16:$AG$153,42,0) -> 312.6806 | AB9: =+HLOOKUP(AB$1,'[1]RFF Resumen'!$C$16:$AG$153,42,0) -> 245.19333 | AC9: =+HLOOKUP(AC$1,'[1]RFF Resumen'!$C$16:$AG$153,42,0) -> 45.915169 | AD9: =+HLOOKUP(AD$1,'[1]RFF Resumen'!$C$16:$AG$153,42,0) -> 238.5925 | AE9: =+HLOOKUP(AE$1,'[1]RFF Resumen'!$C$16:$AG$153,42,0) -> 313.96496 | AF9: =+HLOOKUP(AF$1,'[1]RFF Resumen'!$C$16:$AG$153,42,0) -> 92.033268 | AG9: =+Y9+SUM(Z9:AF9) -> 5348.1073 | AH9: =+HLOOKUP(AH$1,'[1]RFF Resumen'!$C$16:$AG$153,42,0) -> 188.96172 | AI9: =+HLOOKUP(AI$1,'[1]RFF Resumen'!$C$16:$AG$153,42,0) -> 254.48742 | AJ9: =+HLOOKUP(AJ$1,'[1]RFF Resumen'!$C$16:$AG$153,42,0) -> 368.44352 | AK9: =+AG9+SUM(AH9:AJ9) -> 6160
A10: MLB Real | B10: =IFERROR(VLOOKUP(B$1,[2]Hoja1!$A$2:$E$32,4,0)/1000,0) -> 113.144 | C10: =IFERROR(VLOOKUP(C$1,[2]Hoja1!$A$2:$E$32,4,0)/1000,0) -> 191.936 | D10: =IFERROR(VLOOKUP(D$1,[2]Hoja1!$A$2:$E$32,4,0)/1000,0) -> 214.317 | E10: =IFERROR(VLOOKUP(E$1,[2]Hoja1!$A$2:$E$32,4,0)/1000,0) -> 187.637 | F10: =IFERROR(VLOOKUP(F$1,[2]Hoja1!$A$2:$E$32,4,0)/1000,0) -> 227.728 | G10: =IFERROR(VLOOKUP(G$1,[2]Hoja1!$A$2:$E$32,4,0)/1000,0) -> 275.93 | H10: =IFERROR(VLOOKUP(H$1,[2]Hoja1!$A$2:$E$32,4,0)/1000,0) -> 96.93 | I10: =IFERROR(VLOOKUP(I$1,[2]Hoja1!$A$2:$E$32,4,0)/1000,0) -> 29.045 | J10: =+SUM(B10:I10) -> 1336.667 | K10: =IFERROR(VLOOKUP(K$1,[2]Hoja1!$A$2:$E$32,4,0)/1000,0) -> 117.54 | L10: =IFERROR(VLOOKUP(L$1,[2]Hoja1!$A$2:$E$32,4,0)/1000,0) -> 226.516 | M10: =IFERROR(VLOOKUP(M$1,[2]Hoja1!$A$2:$E$32,4,0)/1000,0) -> 289.03 | N10: =IFERROR(VLOOKUP(N$1,[2]Hoja1!$A$2:$E$32,4,0)/1000,0) -> 0 | O10: =IFERROR(VLOOKUP(O$1,[2]Hoja1!$A$2:$E$32,4,0)/1000,0) -> 0 | P10: =IFERROR(VLOOKUP(P$1,[2]Hoja1!$A$2:$E$32,4,0)/1000,0) -> 0 | Q10: =+J10+SUM(K10:P10) -> 1969.753 | R10: =IFERROR(VLOOKUP(R$1,[2]Hoja1!$A$2:$E$32,4,0)/1000,0) -> 0 | S10: =IFERROR(VLOOKUP(S$1,[2]Hoja1!$A$2:$E$32,4,0)/1000,0) -> 0 | T10: =IFERROR(VLOOKUP(T$1,[2]Hoja1!$A$2:$E$32,4,0)/1000,0) -> 0 | U10: =IFERROR(VLOOKUP(U$1,[2]Hoja1!$A$2:$E$32,4,0)/1000,0) -> 0 | V10: =IFERROR(VLOOKUP(V$1,[2]Hoja1!$A$2:$E$32,4,0)/1000,0) -> 0 | W10: =IFERROR(VLOOKUP(W$1,[2]Hoja1!$A$2:$E$32,4,0)/1000,0) -> 0 | X10: =IFERROR(VLOOKUP(X$1,[2]Hoja1!$A$2:$E$32,4,0)/1000,0) -> 0 | Y10: =+Q10+SUM(R10:X10) -> 1969.753 | Z10: =IFERROR(VLOOKUP(Z$1,[2]Hoja1!$A$2:$E$32,4,0)/1000,0) -> 0 | AA10: =IFERROR(VLOOKUP(AA$1,[2]Hoja1!$A$2:$E$32,4,0)/1000,0) -> 0 | AB10: =IFERROR(VLOOKUP(AB$1,[2]Hoja1!$A$2:$E$32,4,0)/1000,0) -> 0 | AC10: =IFERROR(VLOOKUP(AC$1,[2]Hoja1!$A$2:$E$32,4,0)/1000,0) -> 0 | AD10: =IFERROR(VLOOKUP(AD$1,[2]Hoja1!$A$2:$E$32,4,0)/1000,0) -> 0 | AE10: =IFERROR(VLOOKUP(AE$1,[2]Hoja1!$A$2:$E$32,4,0)/1000,0) -> 0 | AF10: =IFERROR(VLOOKUP(AF$1,[2]Hoja1!$A$2:$E$32,4,0)/1000,0) -> 0 | AG10: =+Y10+SUM(Z10:AF10) -> 1969.753 | AH10: =IFERROR(VLOOKUP(AH$1,[2]Hoja1!$A$2:$E$32,4,0)/1000,0) -> 0 | AI10: =IFERROR(VLOOKUP(AI$1,[2]Hoja1!$A$2:$E$32,4,0)/1000,0) -> 0 | AJ10: =IFERROR(VLOOKUP(AJ$1,[2]Hoja1!$A$2:$E$32,4,0)/1000,0) -> 0 | AK10: =+AG10+SUM(AH10:AJ10) -> 1969.753
A11: % Cumplimiento | B11: =IFERROR(+B10/B9,0) -> 1.5249661 | C11: =IFERROR(+C10/C9,0) -> 1.4630508 | D11: =IFERROR(+D10/D9,0) -> 1.1391091 | E11: =IFERROR(+E10/E9,0) -> 1.0096255 | F11: =IFERROR(+F10/F9,0) -> 1.2899057 | G11: =IFERROR(+G10/G9,0) -> 1.4751305 | H11: =IFERROR(+H10/H9,0) -> 2.5062022 | I11: =IFERROR(+I10/I9,0) -> 1.9478254 | ... AK11: =IFERROR(+AK10/AK9,0) -> 0.3197651
A12: Ext MLB Proy | B12: =+HLOOKUP(B$1,[3]Resumen!$B$1:$AH$27,4,0) -> 150 | C12: =+HLOOKUP(C$1,[3]Resumen!$B$1:$AH$27,4,0) -> 150 | D12: =+HLOOKUP(D$1,[3]Resumen!$B$1:$AH$27,4,0) -> 200 | E12: =+HLOOKUP(E$1,[3]Resumen!$B$1:$AH$27,4,0) -> 200 | F12: =+HLOOKUP(F$1,[3]Resumen!$B$1:$AH$27,4,0) -> 200 | G12: =+HLOOKUP(G$1,[3]Resumen!$B$1:$AH$27,4,0) -> 200 | H12: =+HLOOKUP(H$1,[3]Resumen!$B$1:$AH$27,4,0) -> 0 | I12: =+HLOOKUP(I$1,[3]Resumen!$B$1:$AH$27,4,0) -> 0 | J12: =+SUM(B12:I12) -> 1100 | K12: =+HLOOKUP(K$1,[3]Resumen!$B$1:$AH$27,4,0) -> 100 | L12: =+HLOOKUP(L$1,[3]Resumen!$B$1:$AH$27,4,0) -> 350 | M12: =+HLOOKUP(M$1,[3]Resumen!$B$1:$AH$27,4,0) -> 350 | N12: =+HLOOKUP(N$1,[3]Resumen!$B$1:$AH$27,4,0) -> 350 | O12: =+HLOOKUP(O$1,[3]Resumen!$B$1:$AH$27,4,0) -> 350 | P12: =+HLOOKUP(P$1,[3]Resumen!$B$1:$AH$27,4,0) -> 300 | Q12: =+J12+SUM(K12:P12) -> 2900 | R12: =+HLOOKUP(R$1,[3]Resumen!$B$1:$AH$27,4,0) -> 100 | S12: =+HLOOKUP(S$1,[3]Resumen!$B$1:$AH$27,4,0) -> 250 | T12: =+HLOOKUP(T$1,[3]Resumen!$B$1:$AH$27,4,0) -> 250 | U12: =+HLOOKUP(U$1,[3]Resumen!$B$1:$AH$27,4,0) -> 300 | V12: =+HLOOKUP(V$1,[3]Resumen!$B$1:$AH$27,4,0) -> 300 | W12: =+HLOOKUP(W$1,[3]Resumen!$B$1:$AH$27,4,0) -> 300 | X12: =+HLOOKUP(X$1,[3]Resumen!$B$1:$AH$27,4,0) -> 0 | Y12: =+Q12+SUM(R12:X12) -> 4400 | Z12: =+HLOOKUP(Z$1,[3]Resumen!$B$1:$AH$27,4,0) -> 350 | AA12: =+HLOOKUP(AA$1,[3]Resumen!$B$1:$AH$27,4,0) -> 350 | AB12: =+HLOOKUP(AB$1,[3]Resumen!$B$1:$AH$27,4,0) -> 280 | AC12: =+HLOOKUP(AC$1,[3]Resumen!$B$1:$AH$27,4,0) -> 0 | AD12: =+HLOOKUP(AD$1,[3]Resumen!$B$1:$AH$27,4,0) -> 300 | AE12: =+HLOOKUP(AE$1,[3]Resumen!$B$1:$AH$27,4,0) -> 300 | AF12: =+HLOOKUP(AF$1,[3]Resumen!$B$1:$AH$27,4,0) -> 150 | AG12: =+Y12+SUM(Z12:AF12) -> 6130 | AH12: =+HLOOKUP(AH$1,[3]Resumen!$B$1:$AH$27,4,0) -> 100 | AI12: =+HLOOKUP(AI$1,[3]Resumen!$B$1:$AH$27,4,0) -> 370 | AJ12: =+HLOOKUP(AJ$1,[3]Resumen!$B$1:$AH$27,4,0) -> 400 | AK12: =+AG12+SUM(AH12:AJ12) -> 7000
A13: Ext MLB Real | B13: =+IFERROR(VLOOKUP(B$1,'[4]Base de Datos'!$A$5:$EI$35,7,0)/1000,0) -> 0 | C13: =+IFERROR(VLOOKUP(C$1,'[4]Base de Datos'!$A$5:$EI$35,7,0)/1000,0) -> 331.5 | D13: =+IFERROR(VLOOKUP(D$1,'[4]Base de Datos'!$A$5:$EI$35,7,0)/1000,0) -> 316.2 | E13: =+IFERROR(VLOOKUP(E$1,'[4]Base de Datos'!$A$5:$EI$35,7,0)/1000,0) -> 323.31 | F13: =+IFERROR(VLOOKUP(F$1,'[4]Base de Datos'!$A$5:$EI$35,7,0)/1000,0) -> 163.2 | G13: =+IFERROR(VLOOKUP(G$1,'[4]Base de Datos'!$A$5:$EI$35,7,0)/1000,0) -> 285.6 | H13: =+IFERROR(VLOOKUP(H$1,'[4]Base de Datos'!$A$5:$EI$35,7,0)/1000,0) -> 0 | I13: =+IFERROR(VLOOKUP(I$1,'[4]Base de Datos'!$A$5:$EI$35,7,0)/1000,0) -> 0 | J13: =+SUM(B13:I13) -> 1419.81 | K13: =+IFERROR(VLOOKUP(K$1,'[4]Base de Datos'!$A$5:$EI$35,7,0)/1000,0) -> 142.8 | L13: =+IFERROR(VLOOKUP(L$1,'[4]Base de Datos'!$A$5:$EI$35,7,0)/1000,0) -> 357 | M13: =+IFERROR(VLOOKUP(M$1,'[4]Base de Datos'!$A$5:$EI$35,7,0)/1000,0) -> 351.9 | N13: =+IFERROR(VLOOKUP(N$1,'[4]Base de Datos'!$A$5:$EI$35,7,0)/1000,0) -> 0 | O13: =+IFERROR(VLOOKUP(O$1,'[4]Base de Datos'!$A$5:$EI$35,7,0)/1000,0) -> 0 | P13: =+IFERROR(VLOOKUP(P$1,'[4]Base de Datos'!$A$5:$EI$35,7,0)/1000,0) -> 0 | Q13: =+J13+SUM(K13:P13) -> 2271.51 | R13: =+IFERROR(VLOOKUP(R$1,'[4]Base de Datos'!$A$5:$EI$35,7,0)/1000,0) -> 0 | S13: =+IFERROR(VLOOKUP(S$1,'[4]Base de Datos'!$A$5:$EI$35,7,0)/1000,0) -> 0 | T13: =+IFERROR(VLOOKUP(T$1,'[4]Base de Datos'!$A$5:$EI$35,7,0)/1000,0) -> 0 | U13: =+IFERROR(VLOOKUP(U$1,'[4]Base de Datos'!$A$5:$EI$35,7,0)/1000,0) -> 0 | V13: =+IFERROR(VLOOKUP(V$1,'[4]Base de Datos'!$A$5:$EI$35,7,0)/1000,0) -> 0 | W13: =+IFERROR(VLOOKUP(W$1,'[4]Base de Datos'!$A$5:$EI$35,7,0)/1000,0) -> 0 | X13: =+IFERROR(VLOOKUP(X$1,'[4]Base de Datos'!$A$5:$EI$35,7,0)/1000,0) -> 0 | Y13: =+Q13+SUM(R13:X13) -> 2271.51 | Z13: =+IFERROR(VLOOKUP(Z$1,'[4]Base de Datos'!$A$5:$EI$35,7,0)/1000,0) -> 0 | AA13: =+IFERROR(VLOOKUP(AA$1,'[4]Base de Datos'!$A$5:$EI$35,7,0)/1000,0) -> 0 | AB13: =+IFERROR(VLOOKUP(AB$1,'[4]Base de Datos'!$A$5:$EI$35,7,0)/1000,0) -> 0 | AC13: =+IFERROR(VLOOKUP(AC$1,'[4]Base de Datos'!$A$5:$EI$35,7,0)/1000,0) -> 0 | AD13: =+IFERROR(VLOOKUP(AD$1,'[4]Base de Datos'!$A$5:$EI$35,7,0)/1000,0) -> 0 | AE13: =+IFERROR(VLOOKUP(AE$1,'[4]Base de Datos'!$A$5:$EI$35,7,0)/1000,0) -> 0 | AF13: =+IFERROR(VLOOKUP(AF$1,'[4]Base de Datos'!$A$5:$EI$35,7,0)/1000,0) -> 0 | AG13: =+Y13+SUM(Z13:AF13) -> 2271.51 | AH13: =+IFERROR(VLOOKUP(AH$1,'[4]Base de Datos'!$A$5:$EI$35,7,0)/1000,0) -> 0 | AI13: =+IFERROR(VLOOKUP(AI$1,'[4]Base de Datos'!$A$5:$EI$35,7,0)/1000,0) -> 0 | AJ13: =+IFERROR(VLOOKUP(AJ$1,'[4]Base de Datos'!$A$5:$EI$35,7,0)/1000,0) -> 0 | AK13: =+AG13+SUM(AH13:AJ13) -> 2271.51 | AL13: =+AG13/AG12 -> 0.37055628
A14: CPO | B14: =+IFERROR(VLOOKUP(B$1,'[4]Base de Datos'!$A$5:$EI$35,5,0)/1000,0) -> 0 | C14: =+IFERROR(VLOOKUP(C$1,'[4]Base de Datos'!$A$5:$EI$35,5,0)/1000,0) -> 64.044 | D14: =+IFERROR(VLOOKUP(D$1,'[4]Base de Datos'!$A$5:$EI$35,5,0)/1000,0) -> 59.259 | E14: =+IFERROR(VLOOKUP(E$1,'[4]Base de Datos'!$A$5:$EI$35,5,0)/1000,0) -> 57.21 | F14: =+IFERROR(VLOOKUP(F$1,'[4]Base de Datos'!$A$5:$EI$35,5,0)/1000,0) -> 27.769 | G14: =+IFERROR(VLOOKUP(G$1,'[4]Base de Datos'!$A$5:$EI$35,5,0)/1000,0) -> 53.479 | H14: =+IFERROR(VLOOKUP(H$1,'[4]Base de Datos'!$A$5:$EI$35,5,0)/1000,0) -> 0 | I14: =+IFERROR(VLOOKUP(I$1,'[4]Base de Datos'!$A$5:$EI$35,5,0)/1000,0) -> 0 | J14: =+SUM(B14:I14) -> 261.761 | K14: =+IFERROR(VLOOKUP(K$1,'[4]Base de Datos'!$A$5:$EI$35,5,0)/1000,0) -> 26.384 | L14: =+IFERROR(VLOOKUP(L$1,'[4]Base de Datos'!$A$5:$EI$35,5,0)/1000,0) -> 68.814 | M14: =+IFERROR(VLOOKUP(M$1,'[4]Base de Datos'!$A$5:$EI$35,5,0)/1000,0) -> 67.739 | N14: =+IFERROR(VLOOKUP(N$1,'[4]Base de Datos'!$A$5:$EI$35,5,0)/1000,0) -> 0 | O14: =+IFERROR(VLOOKUP(O$1,'[4]Base de Datos'!$A$5:$EI$35,5,0)/1000,0) -> 0 | P14: =+IFERROR(VLOOKUP(P$1,'[4]Base de Datos'!$A$5:$EI$35,5,0)/1000,0) -> 0 | Q14: =+J14+SUM(K14:P14) -> 424.698 | R14: =+IFERROR(VLOOKUP(R$1,'[4]Base de Datos'!$A$5:$EI$35,5,0)/1000,0) -> 0 | S14: =+IFERROR(VLOOKUP(S$1,'[4]Base de Datos'!$A$5:$EI$35,5,0)/1000,0) -> 0 | T14: =+IFERROR(VLOOKUP(T$1,'[4]Base de Datos'!$A$5:$EI$35,5,0)/1000,0) -> 0 | U14: =+IFERROR(VLOOKUP(U$1,'[4]Base de Datos'!$A$5:$EI$35,5,0)/1000,0) -> 0 | V14: =+IFERROR(VLOOKUP(V$1,'[4]Base de Datos'!$A$5:$EI$35,5,0)/1000,0) -> 0 | W14: =+IFERROR(VLOOKUP(W$1,'[4]Base de Datos'!$A$5:$EI$35,5,0)/1000,0) -> 0 | X14: =+IFERROR(VLOOKUP(X$1,'[4]Base de Datos'!$A$5:$EI$35,5,0)/1000,0) -> 0 | Y14: =+Q14+SUM(R14:X14) -> 424.698 | Z14: =+IFERROR(VLOOKUP(Z$1,'[4]Base de Datos'!$A$5:$EI$35,5,0)/1000,0) -> 0 | AA14: =+IFERROR(VLOOKUP(AA$1,'[4]Base de Datos'!$A$5:$EI$35,5,0)/1000,0) -> 0 | AB14: =+IFERROR(VLOOKUP(AB$1,'[4]Base de Datos'!$A$5:$EI$35,5,0)/1000,0) -> 0 | AC14: =+IFERROR(VLOOKUP(AC$1,'[4]Base de Datos'!$A$5:$EI$35,5,0)/1000,0) -> 0 | AD14: =+IFERROR(VLOOKUP(AD$1,'[4]Base de Datos'!$A$5:$EI$35,5,0)/1000,0) -> 0 | AE14: =+IFERROR(VLOOKUP(AE$1,'[4]Base de Datos'!$A$5:$EI$35,5,0)/1000,0) -> 0 | AF14: =+IFERROR(VLOOKUP(AF$1,'[4]Base de Datos'!$A$5:$EI$35,5,0)/1000,0) -> 0 | AG14: =+Y14+SUM(Z14:AF14) -> 424.698 | AH14: =+IFERROR(VLOOKUP(AH$1,'[4]Base de Datos'!$A$5:$EI$35,5,0)/1000,0) -> 0 | AI14: =+IFERROR(VLOOKUP(AI$1,'[4]Base de Datos'!$A$5:$EI$35,5,0)/1000,0) -> 0 | AJ14: =+IFERROR(VLOOKUP(AJ$1,'[4]Base de Datos'!$A$5:$EI$35,5,0)/1000,0) -> 0 | AK14: =+AG14+SUM(AH14:AJ14) -> 424.698
A15: =+_xlfn.CONCAT("TEA% ", B45,"%") -> TEA% 18.6% | B15: =IFERROR(+B14/B13,0) -> 0 | C15: =IFERROR(+C14/C13,0) -> 0.19319457 | D15: =IFERROR(+D14/D13,0) -> 0.18740987 | E15: =IFERROR(+E14/E13,0) -> 0.17695091 | F15: =IFERROR(+F14/F13,0) -> 0.17015319 | G15: =IFERROR(+G14/G13,0) -> 0.1872514 | H15: =IFERROR(+H14/H13,0) -> 0 | I15: =IFERROR(+I14/I13,0) -> 0 | ... M15: =IFERROR(+M14/M13,0) -> 0.19249503 | N15: 0.1964 | O15: =IFERROR(+O14/O13,0) -> 0 | P15: =IFERROR(+P14/P13,0) -> 0 | Q15: =IFERROR(+Q14/Q13,0) -> 0.18696726 | R15: =IFERROR(+R14/R13,0) -> 0 | S15: =IFERROR(+S14/S13,0) -> 0 | T15: =IFERROR(+T14/T13,0) -> 0 | U15: =IFERROR(+U14/U13,0) -> 0 | V15: =IFERROR(+V14/V13,0) -> 0 | ... AK15: =IFERROR(+AK14/AK13,0) -> 0.18696726
A16: Córdoba Proyección | B16: =+HLOOKUP(B$1,'[1]RFF Resumen'!$C$16:$AG$153,106,0) -> 60 | C16: =+HLOOKUP(C$1,'[1]RFF Resumen'!$C$16:$AG$153,106,0) -> 130 | D16: =+HLOOKUP(D$1,'[1]RFF Resumen'!$C$16:$AG$153,106,0) -> 230 | E16: =+HLOOKUP(E$1,'[1]RFF Resumen'!$C$16:$AG$153,106,0) -> 270 | F16: =+HLOOKUP(F$1,'[1]RFF Resumen'!$C$16:$AG$153,106,0) -> 280 | G16: =+HLOOKUP(G$1,'[1]RFF Resumen'!$C$16:$AG$153,106,0) -> 290 | H16: =+HLOOKUP(H$1,'[1]RFF Resumen'!$C$16:$AG$153,106,0) -> 30 | I16: =+HLOOKUP(I$1,'[1]RFF Resumen'!$C$16:$AG$153,106,0) -> 20 | J16: =+SUM(B16:I16) -> 1310 | K16: =+HLOOKUP(K$1,'[1]RFF Resumen'!$C$16:$AG$153,106,0) -> 180 | L16: =+HLOOKUP(L$1,'[1]RFF Resumen'!$C$16:$AG$153,106,0) -> 230 | M16: =+HLOOKUP(M$1,'[1]RFF Resumen'!$C$16:$AG$153,106,0) -> 260 | N16: =+HLOOKUP(N$1,'[1]RFF Resumen'!$C$16:$AG$153,106,0) -> 280 | O16: 97.724 | P16: =+HLOOKUP(P$1,'[1]RFF Resumen'!$C$16:$AG$153,106,0) -> 50 | Q16: =+J16+SUM(K16:P16) -> 2407.724 | R16: =+HLOOKUP(R$1,'[1]RFF Resumen'!$C$16:$AG$153,106,0) -> 100 | S16: =+HLOOKUP(S$1,'[1]RFF Resumen'!$C$16:$AG$153,106,0) -> 230 | T16: =+HLOOKUP(T$1,'[1]RFF Resumen'!$C$16:$AG$153,106,0) -> 270 | U16: =+HLOOKUP(U$1,'[1]RFF Resumen'!$C$16:$AG$153,106,0) -> 280 | V16: =+HLOOKUP(V$1,'[1]RFF Resumen'!$C$16:$AG$153,106,0) -> 290 | W16: =+HLOOKUP(W$1,'[1]RFF Resumen'!$C$16:$AG$153,106,0) -> 300 | X16: =+HLOOKUP(X$1,'[1]RFF Resumen'!$C$16:$AG$153,106,0) -> 40 | Y16: =+Q16+SUM(R16:X16) -> 3917.724 | Z16: =+HLOOKUP(Z$1,'[1]RFF Resumen'!$C$16:$AG$153,106,0) -> 120 | AA16: =+HLOOKUP(AA$1,'[1]RFF Resumen'!$C$16:$AG$153,106,0) -> 230 | AB16: =+HLOOKUP(AB$1,'[1]RFF Resumen'!$C$16:$AG$153,106,0) -> 260 | AC16: =+HLOOKUP(AC$1,'[1]RFF Resumen'!$C$16:$AG$153,106,0) -> 20 | AD16: =+HLOOKUP(AD$1,'[1]RFF Resumen'!$C$16:$AG$153,106,0) -> 240 | AE16: =+HLOOKUP(AE$1,'[1]RFF Resumen'!$C$16:$AG$153,106,0) -> 270 | AF16: =+HLOOKUP(AF$1,'[1]RFF Resumen'!$C$16:$AG$153,106,0) -> 50 | AG16: =+Y16+SUM(Z16:AF16) -> 5107.724 | AH16: =+HLOOKUP(AH$1,'[1]RFF Resumen'!$C$16:$AG$153,106,0) -> 160 | AI16: =+HLOOKUP(AI$1,'[1]RFF Resumen'!$C$16:$AG$153,106,0) -> 270 | AJ16: =+HLOOKUP(AJ$1,'[1]RFF Resumen'!$C$16:$AG$153,106,0) -> 70 | AK16: =+AG16+SUM(AH16:AJ16) -> 5607.724
A17: Córdoba Real | B17: =IFERROR(VLOOKUP(B$1,[2]Hoja1!$A$2:$E$32,5,0)/1000,0) -> 70.1 | C17: =IFERROR(VLOOKUP(C$1,[2]Hoja1!$A$2:$E$32,5,0)/1000,0) -> 231.41 | D17: =IFERROR(VLOOKUP(D$1,[2]Hoja1!$A$2:$E$32,5,0)/1000,0) -> 284.59 | E17: =IFERROR(VLOOKUP(E$1,[2]Hoja1!$A$2:$E$32,5,0)/1000,0) -> 342.6 | F17: =IFERROR(VLOOKUP(F$1,[2]Hoja1!$A$2:$E$32,5,0)/1000,0) -> 380.72 | G17: =IFERROR(VLOOKUP(G$1,[2]Hoja1!$A$2:$E$32,5,0)/1000,0) -> 420.65 | H17: =IFERROR(VLOOKUP(H$1,[2]Hoja1!$A$2:$E$32,5,0)/1000,0) -> 0 | I17: =IFERROR(VLOOKUP(I$1,[2]Hoja1!$A$2:$E$32,5,0)/1000,0) -> 0 | J17: =+SUM(B17:I17) -> 1730.07 | K17: =IFERROR(VLOOKUP(K$1,[2]Hoja1!$A$2:$E$32,5,0)/1000,0) -> 37.81 | L17: =IFERROR(VLOOKUP(L$1,[2]Hoja1!$A$2:$E$32,5,0)/1000,0) -> 248.7 | M17: =IFERROR(VLOOKUP(M$1,[2]Hoja1!$A$2:$E$32,5,0)/1000,0) -> 361.91 | N17: =IFERROR(VLOOKUP(N$1,[2]Hoja1!$A$2:$E$32,5,0)/1000,0) -> 0 | O17: =IFERROR(VLOOKUP(O$1,[2]Hoja1!$A$2:$E$32,5,0)/1000,0) -> 0 | P17: =IFERROR(VLOOKUP(P$1,[2]Hoja1!$A$2:$E$32,5,0)/1000,0) -> 0 | Q17: =+J17+SUM(K17:P17) -> 2378.49 | R17: =IFERROR(VLOOKUP(R$1,[2]Hoja1!$A$2:$E$32,5,0)/1000,0) -> 0 | S17: =IFERROR(VLOOKUP(S$1,[2]Hoja1!$A$2:$E$32,5,0)/1000,0) -> 0 | T17: =IFERROR(VLOOKUP(T$1,[2]Hoja1!$A$2:$E$32,5,0)/1000,0) -> 0 | U17: =IFERROR(VLOOKUP(U$1,[2]Hoja1!$A$2:$E$32,5,0)/1000,0) -> 0 | V17: =IFERROR(VLOOKUP(V$1,[2]Hoja1!$A$2:$E$32,5,0)/1000,0) -> 0 | W17: =IFERROR(VLOOKUP(W$1,[2]Hoja1!$A$2:$E$32,5,0)/1000,0) -> 0 | X17: =IFERROR(VLOOKUP(X$1,[2]Hoja1!$A$2:$E$32,5,0)/1000,0) -> 0 | Y17: =+Q17+SUM(R17:X17) -> 2378.49 | Z17: =IFERROR(VLOOKUP(Z$1,[2]Hoja1!$A$2:$E$32,5,0)/1000,0) -> 0 | AA17: =IFERROR(VLOOKUP(AA$1,[2]Hoja1!$A$2:$E$32,5,0)/1000,0) -> 0 | AB17: =IFERROR(VLOOKUP(AB$1,[2]Hoja1!$A$2:$E$32,5,0)/1000,0) -> 0 | AC17: =IFERROR(VLOOKUP(AC$1,[2]Hoja1!$A$2:$E$32,5,0)/1000,0) -> 0 | AD17: =IFERROR(VLOOKUP(AD$1,[2]Hoja1!$A$2:$E$32,5,0)/1000,0) -> 0 | AE17: =IFERROR(VLOOKUP(AE$1,[2]Hoja1!$A$2:$E$32,5,0)/1000,0) -> 0 | AF17: =IFERROR(VLOOKUP(AF$1,[2]Hoja1!$A$2:$E$32,5,0)/1000,0) -> 0 | AG17: =+Y17+SUM(Z17:AF17) -> 2378.49 | AH17: =IFERROR(VLOOKUP(AH$1,[2]Hoja1!$A$2:$E$32,5,0)/1000,0) -> 0 | AI17: =IFERROR(VLOOKUP(AI$1,[2]Hoja1!$A$2:$E$32,5,0)/1000,0) -> 0 | AJ17: =IFERROR(VLOOKUP(AJ$1,[2]Hoja1!$A$2:$E$32,5,0)/1000,0) -> 0 | AK17: =+AG17+SUM(AH17:AJ17) -> 2378.49
A18: % Cumplimiento | B18: =IFERROR(+B17/B16,0) -> 1.1683333 | C18: =IFERROR(+C17/C16,0) -> 1.7800769 | D18: =IFERROR(+D17/D16,0) -> 1.2373478 | E18: =IFERROR(+E17/E16,0) -> 1.2688889 | F18: =IFERROR(+F17/F16,0) -> 1.3597143 | G18: =IFERROR(+G17/G16,0) -> 1.4505172 | H18: =IFERROR(+H17/H16,0) -> 0 | I18: =IFERROR(+I17/I16,0) -> 0 | ... K18: =IFERROR(+K17/K16,0) -> 0.21005556 | L18: 0.51 | M18: =IFERROR(+M17/M16,0) -> 1.3919615 | N18: =IFERROR(+N17/N16,0) -> 0 | O18: =IFERROR(+O17/O16,0) -> 0 | P18: =IFERROR(+P17/P16,0) -> 0 | Q18: =IFERROR(+Q17/Q16,0) -> 0.98785824 | R18: =IFERROR(+R17/R16,0) -> 0 | S18: =IFERROR(+S17/S16,0) -> 0 | T18: =IFERROR(+T17/T16,0) -> 0 | ... AK18: =IFERROR(+AK17/AK16,0) -> 0.42414534
A19: Ext SINÚ Proy | B19: =+HLOOKUP(B$1,[3]Resumen!$B$1:$AH$27,6,0) -> 100 | C19: =+HLOOKUP(C$1,[3]Resumen!$B$1:$AH$27,6,0) -> 200 | D19: =+HLOOKUP(D$1,[3]Resumen!$B$1:$AH$27,6,0) -> 200 | E19: =+HLOOKUP(E$1,[3]Resumen!$B$1:$AH$27,6,0) -> 250 | F19: =+HLOOKUP(F$1,[3]Resumen!$B$1:$AH$27,6,0) -> 250 | G19: =+HLOOKUP(G$1,[3]Resumen!$B$1:$AH$27,6,0) -> 300 | H19: =+HLOOKUP(H$1,[3]Resumen!$B$1:$AH$27,6,0) -> 0 | I19: =+HLOOKUP(I$1,[3]Resumen!$B$1:$AH$27,6,0) -> 0 | J19: =+SUM(B19:I19) -> 1300 | K19: =+HLOOKUP(K$1,[3]Resumen!$B$1:$AH$27,6,0) -> 0 | L19: =+HLOOKUP(L$1,[3]Resumen!$B$1:$AH$27,6,0) -> 0 | M19: =+HLOOKUP(M$1,[3]Resumen!$B$1:$AH$27,6,0) -> 150 | N19: =+HLOOKUP(N$1,[3]Resumen!$B$1:$AH$27,6,0) -> 320 | O19: =+HLOOKUP(O$1,[3]Resumen!$B$1:$AH$27,6,0) -> 320 | P19: =+HLOOKUP(P$1,[3]Resumen!$B$1:$AH$27,6,0) -> 0 | Q19: =+J19+SUM(K19:P19) -> 2090 | R19: =+HLOOKUP(R$1,[3]Resumen!$B$1:$AH$27,6,0) -> 250 | S19: =+HLOOKUP(S$1,[3]Resumen!$B$1:$AH$27,6,0) -> 200 | T19: =+HLOOKUP(T$1,[3]Resumen!$B$1:$AH$27,6,0) -> 250 | U19: =+HLOOKUP(U$1,[3]Resumen!$B$1:$AH$27,6,0) -> 250 | V19: =+HLOOKUP(V$1,[3]Resumen!$B$1:$AH$27,6,0) -> 250 | W19: =+HLOOKUP(W$1,[3]Resumen!$B$1:$AH$27,6,0) -> 250 | X19: =+HLOOKUP(X$1,[3]Resumen!$B$1:$AH$27,6,0) -> 0 | Y19: =+Q19+SUM(R19:X19) -> 3540 | Z19: =+HLOOKUP(Z$1,[3]Resumen!$B$1:$AH$27,6,0) -> 100 | AA19: =+HLOOKUP(AA$1,[3]Resumen!$B$1:$AH$27,6,0) -> 250 | AB19: =+HLOOKUP(AB$1,[3]Resumen!$B$1:$AH$27,6,0) -> 250 | AC19: =+HLOOKUP(AC$1,[3]Resumen!$B$1:$AH$27,6,0) -> 0 | AD19: =+HLOOKUP(AD$1,[3]Resumen!$B$1:$AH$27,6,0) -> 270 | AE19: =+HLOOKUP(AE$1,[3]Resumen!$B$1:$AH$27,6,0) -> 270 | AF19: =+HLOOKUP(AF$1,[3]Resumen!$B$1:$AH$27,6,0) -> 0 | AG19: =+Y19+SUM(Z19:AF19) -> 4680 | AH19: =+HLOOKUP(AH$1,[3]Resumen!$B$1:$AH$27,6,0) -> 100 | AI19: =+HLOOKUP(AI$1,[3]Resumen!$B$1:$AH$27,6,0) -> 250 | AJ19: =+HLOOKUP(AJ$1,[3]Resumen!$B$1:$AH$27,6,0) -> 100 | AK19: =+AG19+SUM(AH19:AJ19) -> 5130
A20: Ext SINÚ Real | B20: =+IFERROR(VLOOKUP(B$1,'[4]BD Sinu'!$A$5:$EI$35,7,0)/1000,0) -> 0 | C20: =+IFERROR(VLOOKUP(C$1,'[4]BD Sinu'!$A$5:$EI$35,7,0)/1000,0) -> 324 | D20: =+IFERROR(VLOOKUP(D$1,'[4]BD Sinu'!$A$5:$EI$35,7,0)/1000,0) -> 148.5 | E20: =+IFERROR(VLOOKUP(E$1,'[4]BD Sinu'!$A$5:$EI$35,7,0)/1000,0) -> 391.5 | F20: =+IFERROR(VLOOKUP(F$1,'[4]BD Sinu'!$A$5:$EI$35,7,0)/1000,0) -> 351 | G20: =+IFERROR(VLOOKUP(G$1,'[4]BD Sinu'!$A$5:$EI$35,7,0)/1000,0) -> 351 | H20: =+IFERROR(VLOOKUP(H$1,'[4]BD Sinu'!$A$5:$EI$35,7,0)/1000,0) -> 0 | I20: =+IFERROR(VLOOKUP(I$1,'[4]BD Sinu'!$A$5:$EI$35,7,0)/1000,0) -> 0 | J20: =+SUM(B20:I20) -> 1566 | K20: =+IFERROR(VLOOKUP(K$1,'[4]BD Sinu'!$A$5:$EI$35,7,0)/1000,0) -> 0 | L20: =+IFERROR(VLOOKUP(L$1,'[4]BD Sinu'!$A$5:$EI$35,7,0)/1000,0) -> 0 | M20: =+IFERROR(VLOOKUP(M$1,'[4]BD Sinu'!$A$5:$EI$35,7,0)/1000,0) -> 108 | N20: =+IFERROR(VLOOKUP(N$1,'[4]BD Sinu'!$A$5:$EI$35,7,0)/1000,0) -> 0 | O20: =+IFERROR(VLOOKUP(O$1,'[4]BD Sinu'!$A$5:$EI$35,7,0)/1000,0) -> 0 | P20: =+IFERROR(VLOOKUP(P$1,'[4]BD Sinu'!$A$5:$EI$35,7,0)/1000,0) -> 0 | Q20: =+J20+SUM(K20:P20) -> 1674 | R20: =+IFERROR(VLOOKUP(R$1,'[4]BD Sinu'!$A$5:$EI$35,7,0)/1000,0) -> 0 | S20: =+IFERROR(VLOOKUP(S$1,'[4]BD Sinu'!$A$5:$EI$35,7,0)/1000,0) -> 0 | T20: =+IFERROR(VLOOKUP(T$1,'[4]BD Sinu'!$A$5:$EI$35,7,0)/1000,0) -> 0 | U20: =+IFERROR(VLOOKUP(U$1,'[4]BD Sinu'!$A$5:$EI$35,7,0)/1000,0) -> 0 | V20: =+IFERROR(VLOOKUP(V$1,'[4]BD Sinu'!$A$5:$EI$35,7,0)/1000,0) -> 0 | W20: =+IFERROR(VLOOKUP(W$1,'[4]BD Sinu'!$A$5:$EI$35,7,0)/1000,0) -> 0 | X20: =+IFERROR(VLOOKUP(X$1,'[4]BD Sinu'!$A$5:$EI$35,7,0)/1000,0) -> 0 | Y20: =+Q20+SUM(R20:X20) -> 1674 | Z20: =+IFERROR(VLOOKUP(Z$1,'[4]BD Sinu'!$A$5:$EI$35,7,0)/1000,0) -> 0 | AA20: =+IFERROR(VLOOKUP(AA$1,'[4]BD Sinu'!$A$5:$EI$35,7,0)/1000,0) -> 0 | AB20: =+IFERROR(VLOOKUP(AB$1,'[4]BD Sinu'!$A$5:$EI$35,7,0)/1000,0) -> 0 | AC20: =+IFERROR(VLOOKUP(AC$1,'[4]BD Sinu'!$A$5:$EI$35,7,0)/1000,0) -> 0 | AD20: =+IFERROR(VLOOKUP(AD$1,'[4]BD Sinu'!$A$5:$EI$35,7,0)/1000,0) -> 0 | AE20: =+IFERROR(VLOOKUP(AE$1,'[4]BD Sinu'!$A$5:$EI$35,7,0)/1000,0) -> 0 | AF20: =+IFERROR(VLOOKUP(AF$1,'[4]BD Sinu'!$A$5:$EI$35,7,0)/1000,0) -> 0 | AG20: =+Y20+SUM(Z20:AF20) -> 1674 | AH20: =+IFERROR(VLOOKUP(AH$1,'[4]BD Sinu'!$A$5:$EI$35,7,0)/1000,0) -> 0 | AI20: =+IFERROR(VLOOKUP(AI$1,'[4]BD Sinu'!$A$5:$EI$35,7,0)/1000,0) -> 0 | AJ20: =+IFERROR(VLOOKUP(AJ$1,'[4]BD Sinu'!$A$5:$EI$35,7,0)/1000,0) -> 0 | AK20: =+AG20+SUM(AH20:AJ20) -> 1674 | AL20: =+AG20/AG19 -> 0.35769231
A21: CPO | B21: =+IFERROR(VLOOKUP(B$1,'[4]BD Sinu'!$A$5:$EI$35,5,0)/1000,0) -> 0 | C21: =+IFERROR(VLOOKUP(C$1,'[4]BD Sinu'!$A$5:$EI$35,5,0)/1000,0) -> 52.166 | D21: =+IFERROR(VLOOKUP(D$1,'[4]BD Sinu'!$A$5:$EI$35,5,0)/1000,0) -> 27.033 | E21: =+IFERROR(VLOOKUP(E$1,'[4]BD Sinu'!$A$5:$EI$35,5,0)/1000,0) -> 74.626 | F21: =+IFERROR(VLOOKUP(F$1,'[4]BD Sinu'!$A$5:$EI$35,5,0)/1000,0) -> 66.634 | G21: =+IFERROR(VLOOKUP(G$1,'[4]BD Sinu'!$A$5:$EI$35,5,0)/1000,0) -> 82.781 | H21: =+IFERROR(VLOOKUP(H$1,'[4]BD Sinu'!$A$5:$EI$35,5,0)/1000,0) -> 0 | I21: =+IFERROR(VLOOKUP(I$1,'[4]BD Sinu'!$A$5:$EI$35,5,0)/1000,0) -> 0 | J21: =+SUM(B21:I21) -> 303.24 | K21: =+IFERROR(VLOOKUP(K$1,'[4]BD Sinu'!$A$5:$EI$35,5,0)/1000,0) -> 0 | L21: =+IFERROR(VLOOKUP(L$1,'[4]BD Sinu'!$A$5:$EI$35,5,0)/1000,0) -> 0 | M21: =+IFERROR(VLOOKUP(M$1,'[4]BD Sinu'!$A$5:$EI$35,5,0)/1000,0) -> 7.396 | N21: =+IFERROR(VLOOKUP(N$1,'[4]BD Sinu'!$A$5:$EI$35,5,0)/1000,0) -> 0 | O21: =+IFERROR(VLOOKUP(O$1,'[4]BD Sinu'!$A$5:$EI$35,5,0)/1000,0) -> 0 | P21: =+IFERROR(VLOOKUP(P$1,'[4]BD Sinu'!$A$5:$EI$35,5,0)/1000,0) -> 0 | Q21: =+J21+SUM(K21:P21) -> 310.636 | R21: =+IFERROR(VLOOKUP(R$1,'[4]BD Sinu'!$A$5:$EI$35,5,0)/1000,0) -> 0 | S21: =+IFERROR(VLOOKUP(S$1,'[4]BD Sinu'!$A$5:$EI$35,5,0)/1000,0) -> 0 | T21: =+IFERROR(VLOOKUP(T$1,'[4]BD Sinu'!$A$5:$EI$35,5,0)/1000,0) -> 0 | U21: =+IFERROR(VLOOKUP(U$1,'[4]BD Sinu'!$A$5:$EI$35,5,0)/1000,0) -> 0 | V21: =+IFERROR(VLOOKUP(V$1,'[4]BD Sinu'!$A$5:$EI$35,5,0)/1000,0) -> 0 | W21: =+IFERROR(VLOOKUP(W$1,'[4]BD Sinu'!$A$5:$EI$35,5,0)/1000,0) -> 0 | X21: =+IFERROR(VLOOKUP(X$1,'[4]BD Sinu'!$A$5:$EI$35,5,0)/1000,0) -> 0 | Y21: =+Q21+SUM(R21:X21) -> 310.636 | Z21: =+IFERROR(VLOOKUP(Z$1,'[4]BD Sinu'!$A$5:$EI$35,5,0)/1000,0) -> 0 | AA21: =+IFERROR(VLOOKUP(AA$1,'[4]BD Sinu'!$A$5:$EI$35,5,0)/1000,0) -> 0 | AB21: =+IFERROR(VLOOKUP(AB$1,'[4]BD Sinu'!$A$5:$EI$35,5,0)/1000,0) -> 0 | AC21: =+IFERROR(VLOOKUP(AC$1,'[4]BD Sinu'!$A$5:$EI$35,5,0)/1000,0) -> 0 | AD21: =+IFERROR(VLOOKUP(AD$1,'[4]BD Sinu'!$A$5:$EI$35,5,0)/1000,0) -> 0 | AE21: =+IFERROR(VLOOKUP(AE$1,'[4]BD Sinu'!$A$5:$EI$35,5,0)/1000,0) -> 0 | AF21: =+IFERROR(VLOOKUP(AF$1,'[4]BD Sinu'!$A$5:$EI$35,5,0)/1000,0) -> 0 | AG21: =+Y21+SUM(Z21:AF21) -> 310.636 | AH21: =+IFERROR(VLOOKUP(AH$1,'[4]BD Sinu'!$A$5:$EI$35,5,0)/1000,0) -> 0 | AI21: =+IFERROR(VLOOKUP(AI$1,'[4]BD Sinu'!$A$5:$EI$35,5,0)/1000,0) -> 0 | AJ21: =+IFERROR(VLOOKUP(AJ$1,'[4]BD Sinu'!$A$5:$EI$35,5,0)/1000,0) -> 0 | AK21: =+AG21+SUM(AH21:AJ21) -> 310.636
A22: =+_xlfn.CONCAT("TEA% ", B47,"%") -> TEA% 22% | B22: =IFERROR(+B21/B20,0) -> 0 | C22: =IFERROR(+C21/C20,0) -> 0.16100617 | D22: =IFERROR(+D21/D20,0) -> 0.1820404 | E22: =IFERROR(+E21/E20,0) -> 0.19061558 | F22: =IFERROR(+F21/F20,0) -> 0.18984046 | G22: =IFERROR(+G21/G20,0) -> 0.2358433 | H22: =IFERROR(+H21/H20,0) -> 0 | I22: =IFERROR(+I21/I20,0) -> 0 | ... AK22: =IFERROR(+AK21/AK20,0) -> 0.18556511
A23: A&G Proyección | B23: =+HLOOKUP(B$1,'[1]RFF Resumen'!$C$16:$AG$153,77,0) -> 490.09901 | C23: =+HLOOKUP(C$1,'[1]RFF Resumen'!$C$16:$AG$153,77,0) -> 740.59406 | D23: =+HLOOKUP(D$1,'[1]RFF Resumen'!$C$16:$AG$153,77,0) -> 914.85149 | E23: =+HLOOKUP(E$1,'[1]RFF Resumen'!$C$16:$AG$153,77,0) -> 936.63366 | F23: =+HLOOKUP(F$1,'[1]RFF Resumen'!$C$16:$AG$153,77,0) -> 882.17822 | G23: =+HLOOKUP(G$1,'[1]RFF Resumen'!$C$16:$AG$153,77,0) -> 838.61386 | H23: =+HLOOKUP(H$1,'[1]RFF Resumen'!$C$16:$AG$153,77,0) -> 185.14851 | I23: =+HLOOKUP(I$1,'[1]RFF Resumen'!$C$16:$AG$153,77,0) -> 141.58416 | J23: =+SUM(B23:I23) -> 5129.703 | K23: =+HLOOKUP(K$1,'[1]RFF Resumen'!$C$16:$AG$153,77,0) -> 773.26733 | L23: =+HLOOKUP(L$1,'[1]RFF Resumen'!$C$16:$AG$153,77,0) -> 1034.6535 | M23: =+HLOOKUP(M$1,'[1]RFF Resumen'!$C$16:$AG$153,77,0) -> 1198.0198 | N23: =+HLOOKUP(N$1,'[1]RFF Resumen'!$C$16:$AG$153,77,0) -> 1143.5644 | O23: =+HLOOKUP(O$1,'[1]RFF Resumen'!$C$16:$AG$153,77,0) -> 991.08911 | P23: =+HLOOKUP(P$1,'[1]RFF Resumen'!$C$16:$AG$153,77,0) -> 152.47525 | Q23: =+J23+SUM(K23:P23) -> 10422.772 | R23: =+HLOOKUP(R$1,'[1]RFF Resumen'!$C$16:$AG$153,77,0) -> 490.09901 | S23: =+HLOOKUP(S$1,'[1]RFF Resumen'!$C$16:$AG$153,77,0) -> 805.94059 | T23: =+HLOOKUP(T$1,'[1]RFF Resumen'!$C$16:$AG$153,77,0) -> 1110.8911 | U23: =+HLOOKUP(U$1,'[1]RFF Resumen'!$C$16:$AG$153,77,0) -> 1089.1089 | V23: =+HLOOKUP(V$1,'[1]RFF Resumen'!$C$16:$AG$153,77,0) -> 1056.4356 | W23: =+HLOOKUP(W$1,'[1]RFF Resumen'!$C$16:$AG$153,77,0) -> 1001.9802 | X23: =+HLOOKUP(X$1,'[1]RFF Resumen'!$C$16:$AG$153,77,0) -> 185.14851 | Y23: =+Q23+SUM(R23:X23) -> 16162.376 | Z23: =+HLOOKUP(Z$1,'[1]RFF Resumen'!$C$16:$AG$153,77,0) -> 511.88119 | AA23: =+HLOOKUP(AA$1,'[1]RFF Resumen'!$C$16:$AG$153,77,0) -> 980.19802 | AB23: =+HLOOKUP(AB$1,'[1]RFF Resumen'!$C$16:$AG$153,77,0) -> 599.0099 | AC23: =+HLOOKUP(AC$1,'[1]RFF Resumen'!$C$16:$AG$153,77,0) -> 163.36634 | AD23: =+HLOOKUP(AD$1,'[1]RFF Resumen'!$C$16:$AG$153,77,0) -> 653.46535 | AE23: =+HLOOKUP(AE$1,'[1]RFF Resumen'!$C$16:$AG$153,77,0) -> 1034.6535 | AF23: =+HLOOKUP(AF$1,'[1]RFF Resumen'!$C$16:$AG$153,77,0) -> 163.36634 | AG23: =+Y23+SUM(Z23:AF23) -> 20268.317 | AH23: =+HLOOKUP(AH$1,'[1]RFF Resumen'!$C$16:$AG$153,77,0) -> 544.55446 | AI23: =+HLOOKUP(AI$1,'[1]RFF Resumen'!$C$16:$AG$153,77,0) -> 1001.9802 | AJ23: =+HLOOKUP(AJ$1,'[1]RFF Resumen'!$C$16:$AG$153,77,0) -> 185.14851 | AK23: =+AG23+SUM(AH23:AJ23) -> 22000
A24: A&G Real | B24: =IFERROR(VLOOKUP(B$1,[2]Hoja1!$A$2:$E$32,3,0)/1000,0) -> 455.3 | C24: =IFERROR(VLOOKUP(C$1,[2]Hoja1!$A$2:$E$32,3,0)/1000,0) -> 605.61 | D24: =IFERROR(VLOOKUP(D$1,[2]Hoja1!$A$2:$E$32,3,0)/1000,0) -> 799.38 | E24: =IFERROR(VLOOKUP(E$1,[2]Hoja1!$A$2:$E$32,3,0)/1000,0) -> 708.73 | F24: =IFERROR(VLOOKUP(F$1,[2]Hoja1!$A$2:$E$32,3,0)/1000,0) -> 742.49 | G24: =IFERROR(VLOOKUP(G$1,[2]Hoja1!$A$2:$E$32,3,0)/1000,0) -> 907.6 | H24: =IFERROR(VLOOKUP(H$1,[2]Hoja1!$A$2:$E$32,3,0)/1000,0) -> 306.72 | I24: =IFERROR(VLOOKUP(I$1,[2]Hoja1!$A$2:$E$32,3,0)/1000,0) -> 151.32 | J24: =+SUM(B24:I24) -> 4677.15 | K24: =IFERROR(VLOOKUP(K$1,[2]Hoja1!$A$2:$E$32,3,0)/1000,0) -> 754.27 | L24: =IFERROR(VLOOKUP(L$1,[2]Hoja1!$A$2:$E$32,3,0)/1000,0) -> 721.26 | M24: =IFERROR(VLOOKUP(M$1,[2]Hoja1!$A$2:$E$32,3,0)/1000,0) -> 610.6 | N24: =IFERROR(VLOOKUP(N$1,[2]Hoja1!$A$2:$E$32,3,0)/1000,0) -> 0 | O24: =IFERROR(VLOOKUP(O$1,[2]Hoja1!$A$2:$E$32,3,0)/1000,0) -> 0 | P24: =IFERROR(VLOOKUP(P$1,[2]Hoja1!$A$2:$E$32,3,0)/1000,0) -> 0 | Q24: =+J24+SUM(K24:P24) -> 6763.28 | R24: =IFERROR(VLOOKUP(R$1,[2]Hoja1!$A$2:$E$32,3,0)/1000,0) -> 0 | S24: =IFERROR(VLOOKUP(S$1,[2]Hoja1!$A$2:$E$32,3,0)/1000,0) -> 0 | T24: =IFERROR(VLOOKUP(T$1,[2]Hoja1!$A$2:$E$32,3,0)/1000,0) -> 0 | U24: =IFERROR(VLOOKUP(U$1,[2]Hoja1!$A$2:$E$32,3,0)/1000,0) -> 0 | V24: =IFERROR(VLOOKUP(V$1,[2]Hoja1!$A$2:$E$32,3,0)/1000,0) -> 0 | W24: =IFERROR(VLOOKUP(W$1,[2]Hoja1!$A$2:$E$32,3,0)/1000,0) -> 0 | X24: =IFERROR(VLOOKUP(X$1,[2]Hoja1!$A$2:$E$32,3,0)/1000,0) -> 0 | Y24: =+Q24+SUM(R24:X24) -> 6763.28 | Z24: =IFERROR(VLOOKUP(Z$1,[2]Hoja1!$A$2:$E$32,3,0)/1000,0) -> 0 | AA24: =IFERROR(VLOOKUP(AA$1,[2]Hoja1!$A$2:$E$32,3,0)/1000,0) -> 0 | AB24: =IFERROR(VLOOKUP(AB$1,[2]Hoja1!$A$2:$E$32,3,0)/1000,0) -> 0 | AC24: =IFERROR(VLOOKUP(AC$1,[2]Hoja1!$A$2:$E$32,3,0)/1000,0) -> 0 | AD24: =IFERROR(VLOOKUP(AD$1,[2]Hoja1!$A$2:$E$32,3,0)/1000,0) -> 0 | AE24: =IFERROR(VLOOKUP(AE$1,[2]Hoja1!$A$2:$E$32,3,0)/1000,0) -> 0 | AF24: =IFERROR(VLOOKUP(AF$1,[2]Hoja1!$A$2:$E$32,3,0)/1000,0) -> 0 | AG24: =+Y24+SUM(Z24:AF24) -> 6763.28 | AH24: =IFERROR(VLOOKUP(AH$1,[2]Hoja1!$A$2:$E$32,3,0)/1000,0) -> 0 | AI24: =IFERROR(VLOOKUP(AI$1,[2]Hoja1!$A$2:$E$32,3,0)/1000,0) -> 0 | AJ24: =IFERROR(VLOOKUP(AJ$1,[2]Hoja1!$A$2:$E$32,3,0)/1000,0) -> 0 | AK24: =+AG24+SUM(AH24:AJ24) -> 6763.28
A25: % Cumplimiento | B25: =IFERROR(+B24/B23,0) -> 0.92899596 | C25: =IFERROR(+C24/C23,0) -> 0.81773543 | D25: =IFERROR(+D24/D23,0) -> 0.87378117 | E25: =IFERROR(+E24/E23,0) -> 0.75667791 | F25: =IFERROR(+F24/F23,0) -> 0.84165533 | G25: =IFERROR(+G24/G23,0) -> 1.0822621 | H25: =IFERROR(+H24/H23,0) -> 1.656616 | I25: =IFERROR(+I24/I23,0) -> 1.0687636 | ... AK25: =IFERROR(+AK24/AK23,0) -> 0.30742182
A26: Ext A&GC Proy | B26: =+HLOOKUP(B$1,[3]Resumen!$B$1:$AH$27,8,0) -> 700 | C26: =+HLOOKUP(C$1,[3]Resumen!$B$1:$AH$27,8,0) -> 850 | D26: =+HLOOKUP(D$1,[3]Resumen!$B$1:$AH$27,8,0) -> 850 | E26: =+HLOOKUP(E$1,[3]Resumen!$B$1:$AH$27,8,0) -> 850 | F26: =+HLOOKUP(F$1,[3]Resumen!$B$1:$AH$27,8,0) -> 850 | G26: =+HLOOKUP(G$1,[3]Resumen!$B$1:$AH$27,8,0) -> 850 | H26: =+HLOOKUP(H$1,[3]Resumen!$B$1:$AH$27,8,0) -> 500 | I26: =+HLOOKUP(I$1,[3]Resumen!$B$1:$AH$27,8,0) -> 0 | J26: =+SUM(B26:I26) -> 5450 | K26: =+HLOOKUP(K$1,[3]Resumen!$B$1:$AH$27,8,0) -> 850 | L26: =+HLOOKUP(L$1,[3]Resumen!$B$1:$AH$27,8,0) -> 850 | M26: =+HLOOKUP(M$1,[3]Resumen!$B$1:$AH$27,8,0) -> 850 | N26: =+HLOOKUP(N$1,[3]Resumen!$B$1:$AH$27,8,0) -> 850 | O26: =+HLOOKUP(O$1,[3]Resumen!$B$1:$AH$27,8,0) -> 850 | P26: =+HLOOKUP(P$1,[3]Resumen!$B$1:$AH$27,8,0) -> 850 | Q26: =+J26+SUM(K26:P26) -> 10550 | R26: =+HLOOKUP(R$1,[3]Resumen!$B$1:$AH$27,8,0) -> 850 | S26: =+HLOOKUP(S$1,[3]Resumen!$B$1:$AH$27,8,0) -> 850 | T26: =+HLOOKUP(T$1,[3]Resumen!$B$1:$AH$27,8,0) -> 850 | U26: =+HLOOKUP(U$1,[3]Resumen!$B$1:$AH$27,8,0) -> 850 | V26: =+HLOOKUP(V$1,[3]Resumen!$B$1:$AH$27,8,0) -> 850 | W26: =+HLOOKUP(W$1,[3]Resumen!$B$1:$AH$27,8,0) -> 850 | X26: =+HLOOKUP(X$1,[3]Resumen!$B$1:$AH$27,8,0) -> 850 | Y26: =+Q26+SUM(R26:X26) -> 16500 | Z26: =+HLOOKUP(Z$1,[3]Resumen!$B$1:$AH$27,8,0) -> 400 | AA26: =+HLOOKUP(AA$1,[3]Resumen!$B$1:$AH$27,8,0) -> 850 | AB26: =+HLOOKUP(AB$1,[3]Resumen!$B$1:$AH$27,8,0) -> 850 | AC26: =+HLOOKUP(AC$1,[3]Resumen!$B$1:$AH$27,8,0) -> 0 | AD26: =+HLOOKUP(AD$1,[3]Resumen!$B$1:$AH$27,8,0) -> 850 | AE26: =+HLOOKUP(AE$1,[3]Resumen!$B$1:$AH$27,8,0) -> 850 | AF26: =+HLOOKUP(AF$1,[3]Resumen!$B$1:$AH$27,8,0) -> 500 | AG26: =+Y26+SUM(Z26:AF26) -> 20800 | AH26: =+HLOOKUP(AH$1,[3]Resumen!$B$1:$AH$27,8,0) -> 400 | AI26: =+HLOOKUP(AI$1,[3]Resumen!$B$1:$AH$27,8,0) -> 850 | AJ26: =+HLOOKUP(AJ$1,[3]Resumen!$B$1:$AH$27,8,0) -> 0 | AK26: =+AG26+SUM(AH26:AJ26) -> 22050
A27: Ext A&GC Real | B27: =+IFERROR(VLOOKUP(B$1,'[4]Base de Datos'!$A$5:$EI$35,21,0)/1000,0) -> 511.504 | C27: =+IFERROR(VLOOKUP(C$1,'[4]Base de Datos'!$A$5:$EI$35,21,0)/1000,0) -> 349.349 | D27: =+IFERROR(VLOOKUP(D$1,'[4]Base de Datos'!$A$5:$EI$35,21,0)/1000,0) -> 605.22 | E27: =+IFERROR(VLOOKUP(E$1,'[4]Base de Datos'!$A$5:$EI$35,21,0)/1000,0) -> 714.168 | F27: =+IFERROR(VLOOKUP(F$1,'[4]Base de Datos'!$A$5:$EI$35,21,0)/1000,0) -> 706.706 | G27: =+IFERROR(VLOOKUP(G$1,'[4]Base de Datos'!$A$5:$EI$35,21,0)/1000,0) -> 668.972 | H27: =+IFERROR(VLOOKUP(H$1,'[4]Base de Datos'!$A$5:$EI$35,21,0)/1000,0) -> 504.79 | I27: =+IFERROR(VLOOKUP(I$1,'[4]Base de Datos'!$A$5:$EI$35,21,0)/1000,0) -> 723.142 | J27: =+SUM(B27:I27) -> 4783.851 | K27: =+IFERROR(VLOOKUP(K$1,'[4]Base de Datos'!$A$5:$EI$35,21,0)/1000,0) -> 607.422 | L27: =+IFERROR(VLOOKUP(L$1,'[4]Base de Datos'!$A$5:$EI$35,21,0)/1000,0) -> 431.965 | M27: =+IFERROR(VLOOKUP(M$1,'[4]Base de Datos'!$A$5:$EI$35,21,0)/1000,0) -> 670.44 | N27: =+IFERROR(VLOOKUP(N$1,'[4]Base de Datos'!$A$5:$EI$35,21,0)/1000,0) -> 0 | O27: =+IFERROR(VLOOKUP(O$1,'[4]Base de Datos'!$A$5:$EI$35,21,0)/1000,0) -> 0 | P27: =+IFERROR(VLOOKUP(P$1,'[4]Base de Datos'!$A$5:$EI$35,21,0)/1000,0) -> 0 | Q27: =+J27+SUM(K27:P27) -> 6493.678 | R27: =+IFERROR(VLOOKUP(R$1,'[4]Base de Datos'!$A$5:$EI$35,21,0)/1000,0) -> 0 | S27: =+IFERROR(VLOOKUP(S$1,'[4]Base de Datos'!$A$5:$EI$35,21,0)/1000,0) -> 0 | T27: =+IFERROR(VLOOKUP(T$1,'[4]Base de Datos'!$A$5:$EI$35,21,0)/1000,0) -> 0 | U27: =+IFERROR(VLOOKUP(U$1,'[4]Base de Datos'!$A$5:$EI$35,21,0)/1000,0) -> 0 | V27: =+IFERROR(VLOOKUP(V$1,'[4]Base de Datos'!$A$5:$EI$35,21,0)/1000,0) -> 0 | W27: =+IFERROR(VLOOKUP(W$1,'[4]Base de Datos'!$A$5:$EI$35,21,0)/1000,0) -> 0 | X27: =+IFERROR(VLOOKUP(X$1,'[4]Base de Datos'!$A$5:$EI$35,21,0)/1000,0) -> 0 | Y27: =+Q27+SUM(R27:X27) -> 6493.678 | Z27: =+IFERROR(VLOOKUP(Z$1,'[4]Base de Datos'!$A$5:$EI$35,21,0)/1000,0) -> 0 | AA27: =+IFERROR(VLOOKUP(AA$1,'[4]Base de Datos'!$A$5:$EI$35,21,0)/1000,0) -> 0 | AB27: =+IFERROR(VLOOKUP(AB$1,'[4]Base de Datos'!$A$5:$EI$35,21,0)/1000,0) -> 0 | AC27: =+IFERROR(VLOOKUP(AC$1,'[4]Base de Datos'!$A$5:$EI$35,21,0)/1000,0) -> 0 | AD27: =+IFERROR(VLOOKUP(AD$1,'[4]Base de Datos'!$A$5:$EI$35,21,0)/1000,0) -> 0 | AE27: =+IFERROR(VLOOKUP(AE$1,'[4]Base de Datos'!$A$5:$EI$35,21,0)/1000,0) -> 0 | AF27: =+IFERROR(VLOOKUP(AF$1,'[4]Base de Datos'!$A$5:$EI$35,21,0)/1000,0) -> 0 | AG27: =+Y27+SUM(Z27:AF27) -> 6493.678 | AH27: =+IFERROR(VLOOKUP(AH$1,'[4]Base de Datos'!$A$5:$EI$35,21,0)/1000,0) -> 0 | AI27: =+IFERROR(VLOOKUP(AI$1,'[4]Base de Datos'!$A$5:$EI$35,21,0)/1000,0) -> 0 | AJ27: =+IFERROR(VLOOKUP(AJ$1,'[4]Base de Datos'!$A$5:$EI$35,21,0)/1000,0) -> 0 | AK27: =+AG27+SUM(AH27:AJ27) -> 6493.678 | AL27: =+AG27/AG26 -> 0.31219606
A28: CPO | B28: =+IFERROR(VLOOKUP(B$1,'[4]Base de Datos'!$A$5:$EI$35,19,0)/1000,0) -> 120.3 | C28: =+IFERROR(VLOOKUP(C$1,'[4]Base de Datos'!$A$5:$EI$35,19,0)/1000,0) -> 78.136 | D28: =+IFERROR(VLOOKUP(D$1,'[4]Base de Datos'!$A$5:$EI$35,19,0)/1000,0) -> 149.477 | E28: =+IFERROR(VLOOKUP(E$1,'[4]Base de Datos'!$A$5:$EI$35,19,0)/1000,0) -> 167.895 | F28: =+IFERROR(VLOOKUP(F$1,'[4]Base de Datos'!$A$5:$EI$35,19,0)/1000,0) -> 167.42 | G28: =+IFERROR(VLOOKUP(G$1,'[4]Base de Datos'!$A$5:$EI$35,19,0)/1000,0) -> 158.212 | H28: =+IFERROR(VLOOKUP(H$1,'[4]Base de Datos'!$A$5:$EI$35,19,0)/1000,0) -> 108.704 | I28: =+IFERROR(VLOOKUP(I$1,'[4]Base de Datos'!$A$5:$EI$35,19,0)/1000,0) -> 171.567 | J28: =+SUM(B28:I28) -> 1121.711 | K28: =+IFERROR(VLOOKUP(K$1,'[4]Base de Datos'!$A$5:$EI$35,19,0)/1000,0) -> 154.342 | L28: =+IFERROR(VLOOKUP(L$1,'[4]Base de Datos'!$A$5:$EI$35,19,0)/1000,0) -> 87.544 | M28: =+IFERROR(VLOOKUP(M$1,'[4]Base de Datos'!$A$5:$EI$35,19,0)/1000,0) -> 152.958 | N28: =+IFERROR(VLOOKUP(N$1,'[4]Base de Datos'!$A$5:$EI$35,19,0)/1000,0) -> 0 | O28: =+IFERROR(VLOOKUP(O$1,'[4]Base de Datos'!$A$5:$EI$35,19,0)/1000,0) -> 0 | P28: =+IFERROR(VLOOKUP(P$1,'[4]Base de Datos'!$A$5:$EI$35,19,0)/1000,0) -> 0 | Q28: =+J28+SUM(K28:P28) -> 1516.555 | R28: =+IFERROR(VLOOKUP(R$1,'[4]Base de Datos'!$A$5:$EI$35,19,0)/1000,0) -> 0 | S28: =+IFERROR(VLOOKUP(S$1,'[4]Base de Datos'!$A$5:$EI$35,19,0)/1000,0) -> 0 | T28: =+IFERROR(VLOOKUP(T$1,'[4]Base de Datos'!$A$5:$EI$35,19,0)/1000,0) -> 0 | U28: =+IFERROR(VLOOKUP(U$1,'[4]Base de Datos'!$A$5:$EI$35,19,0)/1000,0) -> 0 | V28: =+IFERROR(VLOOKUP(V$1,'[4]Base de Datos'!$A$5:$EI$35,19,0)/1000,0) -> 0 | W28: =+IFERROR(VLOOKUP(W$1,'[4]Base de Datos'!$A$5:$EI$35,19,0)/1000,0) -> 0 | X28: =+IFERROR(VLOOKUP(X$1,'[4]Base de Datos'!$A$5:$EI$35,19,0)/1000,0) -> 0 | Y28: =+Q28+SUM(R28:X28) -> 1516.555 | Z28: =+IFERROR(VLOOKUP(Z$1,'[4]Base de Datos'!$A$5:$EI$35,19,0)/1000,0) -> 0 | AA28: =+IFERROR(VLOOKUP(AA$1,'[4]Base de Datos'!$A$5:$EI$35,19,0)/1000,0) -> 0 | AB28: =+IFERROR(VLOOKUP(AB$1,'[4]Base de Datos'!$A$5:$EI$35,19,0)/1000,0) -> 0 | AC28: =+IFERROR(VLOOKUP(AC$1,'[4]Base de Datos'!$A$5:$EI$35,19,0)/1000,0) -> 0 | AD28: =+IFERROR(VLOOKUP(AD$1,'[4]Base de Datos'!$A$5:$EI$35,19,0)/1000,0) -> 0 | AE28: =+IFERROR(VLOOKUP(AE$1,'[4]Base de Datos'!$A$5:$EI$35,19,0)/1000,0) -> 0 | AF28: =+IFERROR(VLOOKUP(AF$1,'[4]Base de Datos'!$A$5:$EI$35,19,0)/1000,0) -> 0 | AG28: =+Y28+SUM(Z28:AF28) -> 1516.555 | AH28: =+IFERROR(VLOOKUP(AH$1,'[4]Base de Datos'!$A$5:$EI$35,19,0)/1000,0) -> 0 | AI28: =+IFERROR(VLOOKUP(AI$1,'[4]Base de Datos'!$A$5:$EI$35,19,0)/1000,0) -> 0 | AJ28: =+IFERROR(VLOOKUP(AJ$1,'[4]Base de Datos'!$A$5:$EI$35,19,0)/1000,0) -> 0 | AK28: =+AG28+SUM(AH28:AJ28) -> 1516.555
A29: =+_xlfn.CONCAT("TEA% ", B46,"%") -> TEA% 23.5% | B29: =IFERROR(+B28/B27,0) -> 0.23518878 | C29: =IFERROR(+C28/C27,0) -> 0.22366173 | D29: =IFERROR(+D28/D27,0) -> 0.24697961 | E29: =IFERROR(+E28/E27,0) -> 0.23509174 | F29: =IFERROR(+F28/F27,0) -> 0.23690191 | G29: =IFERROR(+G28/G27,0) -> 0.23650018 | H29: =IFERROR(+H28/H27,0) -> 0.21534499 | I29: =IFERROR(+I28/I27,0) -> 0.23725216 | ... Y29: =IFERROR(+Y28/Y27,0) -> 0.2335433 | Z29: =+Y29 -> 0.2335433 | AA29: =+Y29 -> 0.2335433 | AB29: =IFERROR(+AB28/AB27,0) -> 0 | AC29: =IFERROR(+AC28/AC27,0) -> 0 | AD29: =IFERROR(+AD28/AD27,0) -> 0 | AE29: =IFERROR(+AE28/AE27,0) -> 0 | AF29: =IFERROR(+AF28/AF27,0) -> 0 | AG29: =IFERROR(+AG28/AG27,0) -> 0.2335433 | AH29: =IFERROR(+AH28/AH27,0) -> 0 | AI29: =IFERROR(+AI28/AI27,0) -> 0 | ... AK29: =IFERROR(+AK28/AK27,0) -> 0.2335433
A30: TOTAL Proyección | B30: =B2+B9+B16+B23 -> 1149.2934 | C30: =C2+C9+C16+C23 -> 1598.7829 | D30: =D2+D9+D16+D23 -> 1991.9959 | E30: =E2+E9+E16+E23 -> 2067.4818 | F30: =F2+F9+F16+F23 -> 2081.7245 | G30: =G2+G9+G16+G23 -> 2104.6685 | H30: =H2+H9+H16+H23 -> 553.82456 | I30: =I2+I9+I16+I23 -> 226.49566 | J30: =+SUM(B30:I30) -> 11774.267 | K30: =K2+K9+K16+K23 -> 1622.9334 | L30: =L2+L9+L16+L23 -> 2147.594 | M30: =M2+M9+M16+M23 -> 2374.6374 | N30: =N2+N9+N16+N23 -> 2487.5383 | O30: =O2+O9+O16+O23 -> 2128.0663 | P30: =P2+P9+P16+P23 -> 813.03409 | Q30: =+J30+SUM(K30:P30) -> 23348.071 | R30: =R2+R9+R16+R23 -> 1440.0631 | S30: =S2+S9+S16+S23 -> 1907.3005 | T30: =T2+T9+T16+T23 -> 2300.1866 | U30: =U2+U9+U16+U23 -> 2305.0972 | V30: =V2+V9+V16+V23 -> 2314.6431 | W30: =W2+W9+W16+W23 -> 2308.2443 | X30: =X2+X9+X16+X23 -> 707.87812 | Y30: =+Q30+SUM(R30:X30) -> 36631.484 | Z30: =Z2+Z9+Z16+Z23 -> 1540.2251 | AA30: =AA2+AA9+AA16+AA23 -> 2362.8786 | AB30: =AB2+AB9+AB16+AB23 -> 1323.2032 | AC30: =AC2+AC9+AC16+AC23 -> 229.28151 | AD30: =AD2+AD9+AD16+AD23 -> 1722.0578 | AE30: =AE2+AE9+AE16+AE23 -> 2308.6184 | AF30: =AF2+AF9+AF16+AF23 -> 874.3996 | AG30: =+Y30+SUM(Z30:AF30) -> 46992.148 | AH30: =AH2+AH9+AH16+AH23 -> 1633.5162 | AI30: =AI2+AI9+AI16+AI23 -> 2448.4676 | AJ30: =AJ2+AJ9+AJ16+AJ23 -> 693.59204 | AK30: =+AG30+SUM(AH30:AJ30) -> 51767.724 | AL30: =+AK33-AK19 -> 47300 | AM30: Proyección inicio mes Fruta procesada sin Sinú
A31: TOTAL Real | B31: =B3+B10+B17+B24 -> 997.894 | C31: =C3+C10+C17+C24 -> 1441.616 | D31: =D3+D10+D17+D24 -> 2130.517 | E31: =E3+E10+E17+E24 -> 1996.817 | F31: =F3+F10+F17+F24 -> 2175.668 | G31: =G3+G10+G17+G24 -> 2115.35 | H31: =H3+H10+H17+H24 -> 1098.11 | I31: =I3+I10+I17+I24 -> 373.255 | J31: =+SUM(B31:I31) -> 12329.227 | K31: =K3+K10+K17+K24 -> 1276.69 | L31: =L3+L10+L17+L24 -> 1784.986 | M31: =M3+M10+M17+M24 -> 2012.22 | N31: =N3+N10+N17+N24 -> 0 | O31: =O3+O10+O17+O24 -> 0 | P31: =P3+P10+P17+P24 -> 0 | Q31: =+J31+SUM(K31:P31) -> 17403.123 | R31: =R3+R10+R17+R24 -> 0 | S31: =S3+S10+S17+S24 -> 0 | T31: =T3+T10+T17+T24 -> 0 | U31: =U3+U10+U17+U24 -> 0 | V31: =V3+V10+V17+V24 -> 0 | W31: =W3+W10+W17+W24 -> 0 | X31: =X3+X10+X17+X24 -> 0 | Y31: =+Q31+SUM(R31:X31) -> 17403.123 | Z31: =Z3+Z10+Z17+Z24 -> 0 | AA31: =AA3+AA10+AA17+AA24 -> 0 | AB31: =AB3+AB10+AB17+AB24 -> 0 | AC31: =AC3+AC10+AC17+AC24 -> 0 | AD31: =AD3+AD10+AD17+AD24 -> 0 | AE31: =AE3+AE10+AE17+AE24 -> 0 | AF31: =AF3+AF10+AF17+AF24 -> 0 | AG31: =+Y31+SUM(Z31:AF31) -> 17403.123 | AH31: =AH3+AH10+AH17+AH24 -> 0 | AI31: =AI3+AI10+AI17+AI24 -> 0 | AJ31: =AJ3+AJ10+AJ17+AJ24 -> 0 | AK31: =+AG31+SUM(AH31:AJ31) -> 17403.123 | AL31: =+AK34-AK20 -> 15505.047 | AM31: Cierre Fruta procesada sin Sinú
A32: % Cumplimiento | B32: =IFERROR(+B31/B30,0) -> 0.86826737 | C32: =IFERROR(+C31/C30,0) -> 0.90169589 | D32: =IFERROR(+D31/D30,0) -> 1.0695389 | E32: =IFERROR(+E31/E30,0) -> 0.96582084 | F32: =IFERROR(+F31/F30,0) -> 1.0451277 | G32: =IFERROR(+G31/G30,0) -> 1.0050751 | H32: =IFERROR(+H31/H30,0) -> 1.9827759 | I32: =IFERROR(+I31/I30,0) -> 1.6479565 | ... AK32: =IFERROR(+AK31/AK30,0) -> 0.33617709 | AL32: =+AL31-AL30 -> -31794.953 | AM32: Diferencia
A33: TOTAL Proyección | B33: =B5+B12+B19+B26 -> 1550 | C33: =C5+C12+C19+C26 -> 1800 | D33: =D5+D12+D19+D26 -> 1900 | E33: =E5+E12+E19+E26 -> 2000 | F33: =F5+F12+F19+F26 -> 2000 | G33: =G5+G12+G19+G26 -> 2150 | H33: =H5+H12+H19+H26 -> 800 | I33: =I5+I12+I19+I26 -> 0 | J33: =+SUM(B33:I33) -> 12200 | K33: =K5+K12+K19+K26 -> 1350 | L33: =L5+L12+L19+L26 -> 1950 | M33: =M5+M12+M19+M26 -> 2100 | N33: =N5+N12+N19+N26 -> 2270 | O33: =O5+O12+O19+O26 -> 2270 | P33: =P5+P12+P19+P26 -> 1550 | Q33: =+J33+SUM(K33:P33) -> 23690 | R33: =R5+R12+R19+R26 -> 1600 | S33: =S5+S12+S19+S26 -> 2050 | T33: =T5+T12+T19+T26 -> 2100 | U33: =U5+U12+U19+U26 -> 2150 | V33: =V5+V12+V19+V26 -> 2150 | W33: =W5+W12+W19+W26 -> 2150 | X33: =X5+X12+X19+X26 -> 1250 | Y33: =+Q33+SUM(R33:X33) -> 37140 | Z33: =Z5+Z12+Z19+Z26 -> 1250 | AA33: =AA5+AA12+AA19+AA26 -> 2200 | AB33: =AB5+AB12+AB19+AB26 -> 1780 | AC33: =AC5+AC12+AC19+AC26 -> 0 | AD33: =AD5+AD12+AD19+AD26 -> 2170 | AE33: =AE5+AE12+AE19+AE26 -> 2170 | AF33: =AF5+AF12+AF19+AF26 -> 1050 | AG33: =+Y33+SUM(Z33:AF33) -> 47760 | AH33: =AH5+AH12+AH19+AH26 -> 1350 | AI33: =AI5+AI12+AI19+AI26 -> 2220 | AJ33: =AJ5+AJ12+AJ19+AJ26 -> 1100 | AK33: =+AG33+SUM(AH33:AJ33) -> 52430 | AL33: =+AK5+AK12+AK19+AK26 -> 52430
A34: RFF Procesada | B34: =+B27+B13+B20+B6 -> 1212.754 | C34: =+C27+C13+C20+C6 -> 1323.849 | D34: =+D27+D13+D20+D6 -> 1795.92 | E34: =+E27+E13+E20+E6 -> 2220.978 | F34: =+F27+F13+F20+F6 -> 1979.906 | G34: =+G27+G13+G20+G6 -> 1861.072 | H34: =+H27+H13+H20+H6 -> 1335.29 | I34: =+I27+I13+I20+I6 -> 1250.751 | J34: =+SUM(B34:I34) -> 12980.52 | K34: =+K27+K13+K20+K6 -> 937.222 | L34: =+L27+L13+L20+L6 -> 1402.215 | M34: =+M27+M13+M20+M6 -> 1859.09 | N34: =+N27+N13+N20+N6 -> 0 | O34: =+O27+O13+O20+O6 -> 0 | P34: =+P27+P13+P20+P6 -> 0 | Q34: =+J34+SUM(K34:P34) -> 17179.047 | R34: =+R27+R13+R20+R6 -> 0 | S34: =+S27+S13+S20+S6 -> 0 | T34: =+T27+T13+T20+T6 -> 0 | U34: =+U27+U13+U20+U6 -> 0 | V34: =+V27+V13+V20+V6 -> 0 | W34: =+W27+W13+W20+W6 -> 0 | X34: =+X27+X13+X20+X6 -> 0 | Y34: =+Q34+SUM(R34:X34) -> 17179.047 | Z34: =+Z27+Z13+Z20+Z6 -> 0 | AA34: =+AA27+AA13+AA20+AA6 -> 0 | AB34: =+AB27+AB13+AB20+AB6 -> 0 | AC34: =+AC27+AC13+AC20+AC6 -> 0 | AD34: =+AD27+AD13+AD20+AD6 -> 0 | AE34: =+AE27+AE13+AE20+AE6 -> 0 | AF34: =+AF27+AF13+AF20+AF6 -> 0 | AG34: =+Y34+SUM(Z34:AF34) -> 17179.047 | AH34: =+AH27+AH13+AH20+AH6 -> 0 | AI34: =+AI27+AI13+AI20+AI6 -> 0 | AJ34: =+AJ27+AJ13+AJ20+AJ6 -> 0 | AK34: =+AG34+SUM(AH34:AJ34) -> 17179.047 | AL34: =+AK6+AK13+AK20+AK27 -> 17179.047
A35: CPO Real | B35: =B7+B14+B21+B28 -> 283.248 | C35: =C7+C14+C21+C28 -> 258.906 | D35: =D7+D14+D21+D28 -> 391.605 | E35: =E7+E14+E21+E28 -> 458.263 | F35: =F7+F14+F21+F28 -> 421.715 | G35: =G7+G14+G21+G28 -> 409.644 | H35: =H7+H14+H21+H28 -> 279.52 | I35: =I7+I14+I21+I28 -> 294.191 | J35: =+SUM(B35:I35) -> 2797.092 | K35: =K7+K14+K21+K28 -> 217.006 | L35: =L7+L14+L21+L28 -> 290.766 | M35: =M7+M14+M21+M28 -> 390.745 | N35: =N7+N14+N21+N28 -> 0 | O35: =O7+O14+O21+O28 -> 0 | P35: =P7+P14+P21+P28 -> 0 | Q35: =+J35+SUM(K35:P35) -> 3695.609 | R35: =R7+R14+R21+R28 -> 0 | S35: =S7+S14+S21+S28 -> 0 | T35: =T7+T14+T21+T28 -> 0 | U35: =U7+U14+U21+U28 -> 0 | V35: =V7+V14+V21+V28 -> 0 | W35: =W7+W14+W21+W28 -> 0 | X35: =X7+X14+X21+X28 -> 0 | Y35: =+Q35+SUM(R35:X35) -> 3695.609 | Z35: =Z7+Z14+Z21+Z28 -> 0 | AA35: =AA7+AA14+AA21+AA28 -> 0 | AB35: =AB7+AB14+AB21+AB28 -> 0 | AC35: =AC7+AC14+AC21+AC28 -> 0 | AD35: =AD7+AD14+AD21+AD28 -> 0 | AE35: =AE7+AE14+AE21+AE28 -> 0 | AF35: =AF7+AF14+AF21+AF28 -> 0 | AG35: =+Y35+SUM(Z35:AF35) -> 3695.609 | AH35: =AH7+AH14+AH21+AH28 -> 0 | AI35: =AI7+AI14+AI21+AI28 -> 12.417 | AJ35: =AJ7+AJ14+AJ21+AJ28 -> 11.059 | AK35: =+AG35+SUM(AH35:AJ35) -> 3719.085 | AL35: =+AK7+AK14+AK21+AK28 -> 3719.085
A36: TEA% 21,5% | B36: =IFERROR(+B35/B34,0) -> 0.23355767 | C36: =IFERROR(+C35/C34,0) -> 0.19557064 | D36: =IFERROR(+D35/D34,0) -> 0.21805259 | E36: =IFERROR(+E35/E34,0) -> 0.20633388 | F36: =IFERROR(+F35/F34,0) -> 0.21299749 | G36: =IFERROR(+G35/G34,0) -> 0.22011185 | H36: =IFERROR(+H35/H34,0) -> 0.2093328 | I36: =IFERROR(+I35/I34,0) -> 0.23521148 | ... AK36: =IFERROR(+AK35/AK34,0) -> 0.2164896
A37: Proyección CPO | B37: =+B26*$A$42+B12*$A$41+B19*$A$43+B5*$A$40 -> 344 | C37: =+C26*$A$42+C12*$A$41+C19*$A$43+C5*$A$40 -> 401.25 | D37: =+D26*$A$42+D12*$A$41+D19*$A$43+D5*$A$40 -> 421.35 | E37: =+E26*$A$42+E12*$A$41+E19*$A$43+E5*$A$40 -> 443.15 | F37: =+F26*$A$42+F12*$A$41+F19*$A$43+F5*$A$40 -> 443.15 | G37: =+G26*$A$42+G12*$A$41+G19*$A$43+G5*$A$40 -> 475.75 | H37: =+H26*$A$42+H12*$A$41+H19*$A$43+H5*$A$40 -> 182.3 | I37: =+I26*$A$42+I12*$A$41+I19*$A$43+I5*$A$40 -> 0 | ... AK37: =+AK26*$A$42+AK12*$A$41+AK19*$A$43+AK5*$A$40 -> 11554.35
H38: PLANTA | I38: CPO ME | J38: CPO REAL | K38: % CUMPL | L38: DIF TM | O38: PLANTA | P38: CPO ME | Q38: CPO REAL | R38: % CUMPL | S38: DIF TM | W38: PLANTA | X38: CPO ME | Y38: CPO REAL | Z38: % CUMPL | AA38: DIF TM | AE38: PLANTA | AF38: CPO ME | AG38: CPO REAL | AH38: % CUMPL | AI38: DIF TM | AM38: PLANTA | AN38: CPO ME | AO38: CPO REAL | AP38: % CUMPL | AQ38: DIF TM
A39: TEA ME | H39: Ext. Codazzi | I39: =+(SUM($J5))*$A$40 -> 939.6 | J39: =J7 -> 1110.38 | K39: =+J39/I39 -> 1.1817582 | L39: =+J39-I39 -> 170.78 | O39: Ext. Codazzi | P39: =(Q5)*$A$40 -> 1760.4 | Q39: =Q7 -> 1443.72 | R39: =+Q39/P39 -> 0.82010907 | S39: =+Q39-P39 -> -316.68 | W39: Ext. Codazzi | X39: =(Y5)*$A$40 -> 2743.2 | Y39: =Y7 -> 1443.72 | Z39: =+Y39/X39 -> 0.52629046 | AA39: =+Y39-X39 -> -1299.48 | AE39: Ext. Codazzi | AF39: =+AG5*$A$40 -> 3488.4 | AG39: =AG7 -> 1443.72 | AH39: =+AG39/AF39 -> 0.41386309 | AI39: =+AG39-AF39 -> -2044.68 | AM39: Ext. Codazzi | AN39: =+AK5*$A$40 -> 3942 | AO39: =AK7 -> 1467.196 | AP39: =+AO39/AN39 -> 0.37219584 | AQ39: =+AO39-AN39 -> -2474.804
A40: =+[3]Resumen!$B$3 -> 0.216 | B40: Ext. Codazzi | H40: Ext. MLB | I40: =+(SUM($J12))*$A$41 -> 204.6 | J40: =J14 -> 261.761 | K40: =+J40/I40 -> 1.2793793 | L40: =+J40-I40 -> 57.161 | O40: Ext. MLB | P40: =(Q12)*$A$41 -> 539.4 | Q40: =Q14 -> 424.698 | R40: =+Q40/P40 -> 0.78735261 | S40: =+Q40-P40 -> -114.702 | W40: Ext. MLB | X40: =+(Y12)*$A$41 -> 818.4 | Y40: =Y14 -> 424.698 | Z40: =+Y40/X40 -> 0.51893695 | AA40: =+Y40-X40 -> -393.702 | AE40: Ext. MLB | AF40: =+AG12*$A$41 -> 1140.18 | AG40: =AG14 -> 424.698 | AH40: =+AG40/AF40 -> 0.37248329 | AI40: =+AG40-AF40 -> -715.482 | AM40: Ext. MLB | AN40: =+AK12*$A$41 -> 1302 | AO40: =AK14 -> 424.698 | AP40: =+AO40/AN40 -> 0.32618894 | AQ40: =+AO40-AN40 -> -877.302
A41: =+[3]Resumen!$B$5 -> 0.186 | B41: Ext. MLB | H41: Ext. A&G | I41: =+(SUM($J26))*$A$42 -> 1280.75 | J41: =J28 -> 1121.711 | K41: =+J41/I41 -> 0.87582354 | L41: =+J41-I41 -> -159.039 | O41: Ext. A&G | P41: =(Q26)*$A$42 -> 2479.25 | Q41: =Q28 -> 1516.555 | R41: =IFERROR(+Q41/P41,0) -> 0.6116991 | S41: =+Q41-P41 -> -962.695 | W41: Ext. A&G | X41: =+(Y26)*$A$42 -> 3877.5 | Y41: =Y28 -> 1516.555 | Z41: =IFERROR(+Y41/X41,0) -> 0.3911167 | AA41: =+Y41-X41 -> -2360.945 | AE41: Ext. A&G | AF41: =+AG26*$A$42 -> 4888 | AG41: =AG28 -> 1516.555 | AH41: =IFERROR(+AG41/AF41,0) -> 0.31026084 | AI41: =+AG41-AF41 -> -3371.445 | AM41: Ext. A&G | AN41: =+AK26*$A$42 -> 5181.75 | AO41: =AK28 -> 1516.555 | AP41: =IFERROR(+AO41/AN41,0) -> 0.29267236 | AQ41: =+AO41-AN41 -> -3665.195
A42: =+[3]Resumen!$B$9 -> 0.235 | B42: Ext. A&G | H42: Ext. Sinú | I42: =+(SUM($J19))*$A$43 -> 286 | J42: =J21 -> 303.24 | K42: =IFERROR(+J42/I42,0) -> 1.0602797 | L42: =+J42-I42 -> 17.24 | O42: Ext. Sinú | P42: =+(Q19)*$A$43 -> 459.8 | Q42: =Q21 -> 310.636 | R42: =IFERROR(+Q42/P42,0) -> 0.67558939 | S42: =+Q42-P42 -> -149.164 | W42: Ext. Sinú | X42: =+(Y19)*$A$43 -> 778.8 | Y42: =Y21 -> 310.636 | Z42: =IFERROR(+Y42/X42,0) -> 0.39886492 | AA42: =+Y42-X42 -> -468.164 | AE42: Ext. Sinú | AF42: =+AG19*$A$43 -> 1029.6 | AG42: =AG21 -> 310.636 | AH42: =IFERROR(+AG42/AF42,0) -> 0.30170552 | AI42: =+AG42-AF42 -> -718.964 | AM42: Ext. Sinú | AN42: =+AK19*$A$43 -> 1128.6 | AO42: =AK21 -> 310.636 | AP42: =IFERROR(+AO42/AN42,0) -> 0.27524012 | AQ42: =+AO42-AN42 -> -817.964
A43: =+[3]Resumen!$B$7 -> 0.22 | B43: Ext. Sinú | H43: TOTAL | I43: =SUM(I39:I42) -> 2710.95 | J43: =SUM(J39:J42) -> 2797.092 | K43: =+J43/I43 -> 1.0317756 | L43: =+J43-I43 -> 86.142 | O43: TOTAL | P43: =SUM(P39:P42) -> 5238.85 | Q43: =SUM(Q39:Q42) -> 3695.609 | R43: =+Q43/P43 -> 0.70542371 | S43: =+Q43-P43 -> -1543.241 | W43: TOTAL | X43: =SUM(X39:X42) -> 8217.9 | Y43: =SUM(Y39:Y42) -> 3695.609 | Z43: =+Y43/X43 -> 0.44970236 | AA43: =+Y43-X43 -> -4522.291 | AE43: TOTAL | AF43: =SUM(AF39:AF42) -> 10546.18 | AG43: =SUM(AG39:AG42) -> 3695.609 | AH43: =+AG43/AF43 -> 0.35042157 | AI43: =+AG43-AF43 -> -6850.571 | AM43: TOTAL | AN43: =SUM(AN39:AN42) -> 11554.35 | AO43: =SUM(AO39:AO42) -> 3719.085 | AP43: =+AO43/AN43 -> 0.32187747 | AQ43: =+AO43-AN43 -> -7835.265
A44: =+AK37/AK33 -> 0.22037669 | B44: =+A40*100 -> 21.6
B45: =+A41*100 -> 18.6 | H45: CPO PROD | I45: =+I39+I40+I41 -> 2424.95 | J45: =+J39+J40+J41 -> 2493.852 | K45: =+J45/I45 -> 1.0284138 | L45: =+J45-I45 -> 68.902 | O45: CPO PROD | P45: =+P39+P40+P41 -> 4779.05 | Q45: =+Q39+Q40+Q41 -> 3384.973 | R45: =+Q45/P45 -> 0.70829412 | S45: =+Q45-P45 -> -1394.077 | W45: CPO PROD | X45: =+X39+X40+X41 -> 7439.1 | Y45: =+Y39+Y40+Y41 -> 3384.973 | Z45: =+Y45/X45 -> 0.45502453 | AA45: =+Y45-X45 -> -4054.127 | AE45: CPO PROD | AF45: =+AF39+AF40+AF41 -> 9516.58 | AG45: =+AG39+AG40+AG41 -> 3384.973 | AH45: =+AG45/AF45 -> 0.35569217 | AI45: =+AG45-AF45 -> -6131.607 | AM45: CPO PROD | AN45: =+AN39+AN40+AN41 -> 10425.75 | AO45: =+AO39+AO40+AO41 -> 3408.449 | AP45: =IFERROR(+AO45/AN45,0) -> 0.32692602 | AQ45: =+AO45-AN45 -> -7017.301
B46: =+A42*100 -> 23.5 | H46: CPO COMPRA SINÚ | I46: 0 | J46: 0 | K46: =+IFERROR(J46/I46,0) -> 0 | L46: =+J46-I46 -> 0 | O46: CPO COMPRA SINÚ | P46: 0 | Q46: 0 | R46: =IFERROR(+Q46/P46,0) -> 0 | S46: =+Q46-P46 -> 0 | W46: CPO COMPRA SINÚ | X46: 0 | Y46: 0 | Z46: =IFERROR(+Y46/X46,0) -> 0 | AA46: =+Y46-X46 -> 0 | AE46: CPO COMPRA SINÚ | AF46: 0 | AG46: 0 | AH46: =IFERROR(+AG46/AF46,0) -> 0 | AI46: =+AG46-AF46 -> 0 | AM46: CPO COMPRA SINÚ | AN46: 0
B47: =+A43*100 -> 22 | H47: TOTAL Oleoflores | I47: =+I46+I45 -> 2424.95 | J47: =+J46+J45 -> 2493.852 | K47: =+J47/I47 -> 1.0284138 | L47: =+J47-I47 -> 68.902 | O47: TOTAL Oleofl | P47: =+P46+P45 -> 4779.05 | Q47: =+Q46+Q45 -> 3384.973 | R47: =+Q47/P47 -> 0.70829412 | S47: =+Q47-P47 -> -1394.077 | W47: TOTAL Oleofl | X47: =+X46+X45 -> 7439.1 | Y47: =+Y46+Y45 -> 3384.973 | Z47: =+Y47/X47 -> 0.45502453 | AA47: =+Y47-X47 -> -4054.127 | AE47: TOTAL Oleofl | AF47: =+AF46+AF45 -> 9516.58 | AG47: =+AG46+AG45 -> 3384.973 | AH47: =+AG47/AF47 -> 0.35569217 | AI47: =+AG47-AF47 -> -6131.607 | AM47: TOTAL Oleofl | AN47: =+AN46+AN45 -> 10425.75 | AO47: =+AO46+AO45 -> 3408.449 | AP47: =+AO47/AN47 -> 0.32692602 | AQ47: =+AO47-AN47 -> -7017.301
H49: ALMENDRA | I49: =+J53 -> 720 | J49: =+J54 -> 803.014 | K49: =+J49/I49 -> 1.1152972 | L49: =+J49-I49 -> 83.014 | N49: ALMENDRA | O49: =+Q53 -> 1310 | P49: =+Q54 -> 1010.405 | Q49: =+P49/O49 -> 0.77130153 | R49: =+P49-O49 -> -299.595 | W49: ALMENDRA | X49: =+Y53 -> 2000 | Y49: =+Y54 -> 1010.405 | Z49: =+Y49/X49 -> 0.5052025 | AA49: =+Y49-X49 -> -989.595 | AE49: ALMENDRA | AF49: =+AG53 -> 2700 | AG49: =+AG54 -> 1010.405 | AH49: =+AG49/AF49 -> 0.37422407 | AI49: =+AG49-AF49 -> -1689.595 | AM49: ALMENDRA | AN49: =+AK53 -> 3000 | AO49: =+AK54 -> 1010.405 | AP49: =IFERROR(+AO49/AN49,0) -> 0.33680167 | AQ49: =+AO49-AN49 -> -1989.595
H50: KPO | I50: =+I49*0.41 -> 295.2 | J50: =+J55 -> 329.544 | K50: =+J50/I50 -> 1.1163415 | L50: =+J50-I50 -> 34.344 | N50: KPO | O50: =+O49*0.41 -> 537.1 | P50: =+Q55 -> 415.151 | Q50: =+P50/O50 -> 0.77294917 | R50: =+P50-O50 -> -121.949 | W50: KPO | X50: =+X49*0.41 -> 820 | Y50: =+Y55 -> 415.151 | Z50: =+Y50/X50 -> 0.50628171 | AA50: =+Y50-X50 -> -404.849 | AE50: KPO | AF50: =+AF49*0.41 -> 1107 | AG50: =+AG55 -> 415.151 | AH50: =+AG50/AF50 -> 0.37502349 | AI50: =+AG50-AF50 -> -691.849 | AM50: KPO | AN50: =+AN49*0.405 -> 1215 | AO50: =+AK55 -> 415.151
H51: EXTRACCIÓN | I51: =+I50/I49 -> 0.41 | J51: =IFERROR(+J50/J49,0) -> 0.41038388 | K51: =+J51/I51 -> 1.0009363 | L51: =+J51-I51 -> 0.00038387874 | N51: EXTRACCIÓN | O51: =+O50/O49 -> 0.41 | P51: =IFERROR(+P50/P49,0) -> 0.41087584 | Q51: =+P51/O51 -> 1.0021362 | R51: =+P51-O51 -> 0.00087583692 | W51: EXTRACCIÓN | X51: =+X50/X49 -> 0.41 | Y51: =IFERROR(+Y50/Y49,0) -> 0.41087584 | Z51: =+Y51/X51 -> 1.0021362 | AA51: =+Y51-X51 -> 0.00087583692 | AE51: EXTRACCIÓN | AF51: =+AF50/AF49 -> 0.41 | AG51: =IFERROR(+AG50/AG49,0) -> 0.41087584 | AH51: =+AG51/AF51 -> 1.0021362 | AI51: =+AG51-AF51 -> 0.00087583692 | AM51: EXTRACCIÓN | AN51: 0.41 | AO51: =IFERROR(+AO50/AO49,0) -> 0.41087584 | AP51: =+AO51/AN51 -> 1.0021362 | AQ51: =+AO51-AN51 -> 0.00087583692
A53: PK Proy | B53: =+HLOOKUP(B$1,[3]Resumen!$B$25:$AJ$29,2,0) -> 90 | C53: =+HLOOKUP(C$1,[3]Resumen!$B$25:$AJ$29,2,0) -> 90 | D53: =+HLOOKUP(D$1,[3]Resumen!$B$25:$AJ$29,2,0) -> 90 | E53: =+HLOOKUP(E$1,[3]Resumen!$B$25:$AJ$29,2,0) -> 90 | F53: =+HLOOKUP(F$1,[3]Resumen!$B$25:$AJ$29,2,0) -> 90 | G53: =+HLOOKUP(G$1,[3]Resumen!$B$25:$AJ$29,2,0) -> 90 | H53: =+HLOOKUP(H$1,[3]Resumen!$B$25:$AJ$29,2,0) -> 90 | I53: =+HLOOKUP(I$1,[3]Resumen!$B$25:$AJ$29,2,0) -> 90 | J53: =+SUM(B53:I53) -> 720 | K53: =+HLOOKUP(K$1,[3]Resumen!$B$25:$AJ$29,2,0) -> 90 | L53: =+HLOOKUP(L$1,[3]Resumen!$B$25:$AJ$29,2,0) -> 100 | M53: =+HLOOKUP(M$1,[3]Resumen!$B$25:$AJ$29,2,0) -> 100 | N53: =+HLOOKUP(N$1,[3]Resumen!$B$25:$AJ$29,2,0) -> 100 | O53: =+HLOOKUP(O$1,[3]Resumen!$B$25:$AJ$29,2,0) -> 100 | P53: =+HLOOKUP(P$1,[3]Resumen!$B$25:$AJ$29,2,0) -> 100 | Q53: =+J53+SUM(K53:P53) -> 1310 | R53: =+HLOOKUP(R$1,[3]Resumen!$B$25:$AJ$29,2,0) -> 100 | S53: =+HLOOKUP(S$1,[3]Resumen!$B$25:$AJ$29,2,0) -> 90 | T53: =+HLOOKUP(T$1,[3]Resumen!$B$25:$AJ$29,2,0) -> 100 | U53: =+HLOOKUP(U$1,[3]Resumen!$B$25:$AJ$29,2,0) -> 100 | V53: =+HLOOKUP(V$1,[3]Resumen!$B$25:$AJ$29,2,0) -> 100 | W53: =+HLOOKUP(W$1,[3]Resumen!$B$25:$AJ$29,2,0) -> 100 | X53: =+HLOOKUP(X$1,[3]Resumen!$B$25:$AJ$29,2,0) -> 100 | Y53: =+Q53+SUM(R53:X53) -> 2000 | Z53: =+HLOOKUP(Z$1,[3]Resumen!$B$25:$AJ$29,2,0) -> 100 | AA53: =+HLOOKUP(AA$1,[3]Resumen!$B$25:$AJ$29,2,0) -> 100 | AB53: =+HLOOKUP(AB$1,[3]Resumen!$B$25:$AJ$29,2,0) -> 100 | AC53: =+HLOOKUP(AC$1,[3]Resumen!$B$25:$AJ$29,2,0) -> 100 | AD53: =+HLOOKUP(AD$1,[3]Resumen!$B$25:$AJ$29,2,0) -> 100 | AE53: =+HLOOKUP(AE$1,[3]Resumen!$B$25:$AJ$29,2,0) -> 100 | AF53: =+HLOOKUP(AF$1,[3]Resumen!$B$25:$AJ$29,2,0) -> 100 | AG53: =+Y53+SUM(Z53:AF53) -> 2700 | AH53: =+HLOOKUP(AH$1,[3]Resumen!$B$25:$AJ$29,2,0) -> 100 | AI53: =+HLOOKUP(AI$1,[3]Resumen!$B$25:$AJ$29,2,0) -> 100 | AJ53: =+HLOOKUP(AJ$1,[3]Resumen!$B$25:$AJ$29,2,0) -> 100 | AK53: =+AG53+SUM(AH53:AJ53) -> 3000
A54: PK Real | B54: =+IFERROR(VLOOKUP(B$1,'[5]Base de Datos'!$A$4:$X$34,7,0)/1000,0) -> 97.973 | C54: =+IFERROR(VLOOKUP(C$1,'[5]Base de Datos'!$A$4:$X$34,7,0)/1000,0) -> 96.46 | D54: =+IFERROR(VLOOKUP(D$1,'[5]Base de Datos'!$A$4:$X$34,7,0)/1000,0) -> 102.188 | E54: =+IFERROR(VLOOKUP(E$1,'[5]Base de Datos'!$A$4:$X$34,7,0)/1000,0) -> 104.888 | F54: =+IFERROR(VLOOKUP(F$1,'[5]Base de Datos'!$A$4:$X$34,7,0)/1000,0) -> 100.107 | G54: =+IFERROR(VLOOKUP(G$1,'[5]Base de Datos'!$A$4:$X$34,7,0)/1000,0) -> 99.132 | H54: =+IFERROR(VLOOKUP(H$1,'[5]Base de Datos'!$A$4:$X$34,7,0)/1000,0) -> 102.846 | I54: =+IFERROR(VLOOKUP(I$1,'[5]Base de Datos'!$A$4:$X$34,7,0)/1000,0) -> 99.42 | J54: =+SUM(B54:I54) -> 803.014 | K54: =+IFERROR(VLOOKUP(K$1,'[5]Base de Datos'!$A$4:$X$34,7,0)/1000,0) -> 73.307 | L54: =+IFERROR(VLOOKUP(L$1,'[5]Base de Datos'!$A$4:$X$34,7,0)/1000,0) -> 66.722 | M54: =+IFERROR(VLOOKUP(M$1,'[5]Base de Datos'!$A$4:$X$34,7,0)/1000,0) -> 67.362 | N54: =+IFERROR(VLOOKUP(N$1,'[5]Base de Datos'!$A$4:$X$34,7,0)/1000,0) -> 0 | O54: =+IFERROR(VLOOKUP(O$1,'[5]Base de Datos'!$A$4:$X$34,7,0)/1000,0) -> 0 | P54: =+IFERROR(VLOOKUP(P$1,'[5]Base de Datos'!$A$4:$X$34,7,0)/1000,0) -> 0 | Q54: =+J54+SUM(K54:P54) -> 1010.405 | R54: =+IFERROR(VLOOKUP(R$1,'[5]Base de Datos'!$A$4:$X$34,7,0)/1000,0) -> 0 | S54: =+IFERROR(VLOOKUP(S$1,'[5]Base de Datos'!$A$4:$X$34,7,0)/1000,0) -> 0 | T54: =+IFERROR(VLOOKUP(T$1,'[5]Base de Datos'!$A$4:$X$34,7,0)/1000,0) -> 0 | U54: =+IFERROR(VLOOKUP(U$1,'[5]Base de Datos'!$A$4:$X$34,7,0)/1000,0) -> 0 | V54: =+IFERROR(VLOOKUP(V$1,'[5]Base de Datos'!$A$4:$X$34,7,0)/1000,0) -> 0 | W54: =+IFERROR(VLOOKUP(W$1,'[5]Base de Datos'!$A$4:$X$34,7,0)/1000,0) -> 0 | X54: =+IFERROR(VLOOKUP(X$1,'[5]Base de Datos'!$A$4:$X$34,7,0)/1000,0) -> 0 | Y54: =+Q54+SUM(R54:X54) -> 1010.405 | Z54: =+IFERROR(VLOOKUP(Z$1,'[5]Base de Datos'!$A$4:$X$34,7,0)/1000,0) -> 0 | AA54: =+IFERROR(VLOOKUP(AA$1,'[5]Base de Datos'!$A$4:$X$34,7,0)/1000,0) -> 0 | AB54: =+IFERROR(VLOOKUP(AB$1,'[5]Base de Datos'!$A$4:$X$34,7,0)/1000,0) -> 0 | AC54: =+IFERROR(VLOOKUP(AC$1,'[5]Base de Datos'!$A$4:$X$34,7,0)/1000,0) -> 0 | AD54: =+IFERROR(VLOOKUP(AD$1,'[5]Base de Datos'!$A$4:$X$34,7,0)/1000,0) -> 0 | AE54: =+IFERROR(VLOOKUP(AE$1,'[5]Base de Datos'!$A$4:$X$34,7,0)/1000,0) -> 0 | AF54: =+IFERROR(VLOOKUP(AF$1,'[5]Base de Datos'!$A$4:$X$34,7,0)/1000,0) -> 0 | AG54: =+Y54+SUM(Z54:AF54) -> 1010.405 | AH54: =+IFERROR(VLOOKUP(AH$1,'[5]Base de Datos'!$A$4:$X$34,7,0)/1000,0) -> 0 | AI54: =+IFERROR(VLOOKUP(AI$1,'[5]Base de Datos'!$A$4:$X$34,7,0)/1000,0) -> 0 | AJ54: =+IFERROR(VLOOKUP(AJ$1,'[5]Base de Datos'!$A$4:$X$34,7,0)/1000,0) -> 0 | AK54: =+AG54+SUM(AH54:AJ54) -> 1010.405
A55: KPO | B55: =+IFERROR(IF(VLOOKUP(B$1,'[5]Base de Datos'!$A$4:$X$34,5,0)/1000>0,VLOOKUP(B$1,'[5]Base de Datos'!$A$4:$X$34,5,0)/1000,0),0) -> 40.308 | C55: =+IFERROR(IF(VLOOKUP(C$1,'[5]Base de Datos'!$A$4:$X$34,5,0)/1000>0,VLOOKUP(C$1,'[5]Base de Datos'!$A$4:$X$34,5,0)/1000,0),0) -> 39.563 | D55: =+IFERROR(IF(VLOOKUP(D$1,'[5]Base de Datos'!$A$4:$X$34,5,0)/1000>0,VLOOKUP(D$1,'[5]Base de Datos'!$A$4:$X$34,5,0)/1000,0),0) -> 41.957 | E55: =+IFERROR(IF(VLOOKUP(E$1,'[5]Base de Datos'!$A$4:$X$34,5,0)/1000>0,VLOOKUP(E$1,'[5]Base de Datos'!$A$4:$X$34,5,0)/1000,0),0) -> 43.115 | F55: =+IFERROR(IF(VLOOKUP(F$1,'[5]Base de Datos'!$A$4:$X$34,5,0)/1000>0,VLOOKUP(F$1,'[5]Base de Datos'!$A$4:$X$34,5,0)/1000,0),0) -> 41.106 | G55: =+IFERROR(IF(VLOOKUP(G$1,'[5]Base de Datos'!$A$4:$X$34,5,0)/1000>0,VLOOKUP(G$1,'[5]Base de Datos'!$A$4:$X$34,5,0)/1000,0),0) -> 39.421 | H55: =+IFERROR(IF(VLOOKUP(H$1,'[5]Base de Datos'!$A$4:$X$34,5,0)/1000>0,VLOOKUP(H$1,'[5]Base de Datos'!$A$4:$X$34,5,0)/1000,0),0) -> 43.062 | I55: =+IFERROR(IF(VLOOKUP(I$1,'[5]Base de Datos'!$A$4:$X$34,5,0)/1000>0,VLOOKUP(I$1,'[5]Base de Datos'!$A$4:$X$34,5,0)/1000,0),0) -> 41.012 | J55: =+SUM(B55:I55) -> 329.544 | K55: =+IFERROR(IF(VLOOKUP(K$1,'[5]Base de Datos'!$A$4:$X$34,5,0)/1000>0,VLOOKUP(K$1,'[5]Base de Datos'!$A$4:$X$34,5,0)/1000,0),0) -> 30.167 | L55: =+IFERROR(IF(VLOOKUP(L$1,'[5]Base de Datos'!$A$4:$X$34,5,0)/1000>0,VLOOKUP(L$1,'[5]Base de Datos'!$A$4:$X$34,5,0)/1000,0),0) -> 27.71 | M55: =+IFERROR(IF(VLOOKUP(M$1,'[5]Base de Datos'!$A$4:$X$34,5,0)/1000>0,VLOOKUP(M$1,'[5]Base de Datos'!$A$4:$X$34,5,0)/1000,0),0) -> 27.73 | N55: =+IFERROR(IF(VLOOKUP(N$1,'[5]Base de Datos'!$A$4:$X$34,5,0)/1000>0,VLOOKUP(N$1,'[5]Base de Datos'!$A$4:$X$34,5,0)/1000,0),0) -> 0 | O55: =+IFERROR(IF(VLOOKUP(O$1,'[5]Base de Datos'!$A$4:$X$34,5,0)/1000>0,VLOOKUP(O$1,'[5]Base de Datos'!$A$4:$X$34,5,0)/1000,0),0) -> 0 | P55: =+IFERROR(IF(VLOOKUP(P$1,'[5]Base de Datos'!$A$4:$X$34,5,0)/1000>0,VLOOKUP(P$1,'[5]Base de Datos'!$A$4:$X$34,5,0)/1000,0),0) -> 0 | Q55: =+J55+SUM(K55:P55) -> 415.151 | R55: =+IFERROR(IF(VLOOKUP(R$1,'[5]Base de Datos'!$A$4:$X$34,5,0)/1000>0,VLOOKUP(R$1,'[5]Base de Datos'!$A$4:$X$34,5,0)/1000,0),0) -> 0 | S55: =+IFERROR(IF(VLOOKUP(S$1,'[5]Base de Datos'!$A$4:$X$34,5,0)/1000>0,VLOOKUP(S$1,'[5]Base de Datos'!$A$4:$X$34,5,0)/1000,0),0) -> 0 | T55: =+IFERROR(IF(VLOOKUP(T$1,'[5]Base de Datos'!$A$4:$X$34,5,0)/1000>0,VLOOKUP(T$1,'[5]Base de Datos'!$A$4:$X$34,5,0)/1000,0),0) -> 0 | U55: =+IFERROR(IF(VLOOKUP(U$1,'[5]Base de Datos'!$A$4:$X$34,5,0)/1000>0,VLOOKUP(U$1,'[5]Base de Datos'!$A$4:$X$34,5,0)/1000,0),0) -> 0 | V55: =+IFERROR(IF(VLOOKUP(V$1,'[5]Base de Datos'!$A$4:$X$34,5,0)/1000>0,VLOOKUP(V$1,'[5]Base de Datos'!$A$4:$X$34,5,0)/1000,0),0) -> 0 | W55: =+IFERROR(IF(VLOOKUP(W$1,'[5]Base de Datos'!$A$4:$X$34,5,0)/1000>0,VLOOKUP(W$1,'[5]Base de Datos'!$A$4:$X$34,5,0)/1000,0),0) -> 0 | X55: =+IFERROR(IF(VLOOKUP(X$1,'[5]Base de Datos'!$A$4:$X$34,5,0)/1000>0,VLOOKUP(X$1,'[5]Base de Datos'!$A$4:$X$34,5,0)/1000,0),0) -> 0 | Y55: =+Q55+SUM(R55:X55) -> 415.151 | Z55: =+IFERROR(IF(VLOOKUP(Z$1,'[5]Base de Datos'!$A$4:$X$34,5,0)/1000>0,VLOOKUP(Z$1,'[5]Base de Datos'!$A$4:$X$34,5,0)/1000,0),0) -> 0 | AA55: =+IFERROR(IF(VLOOKUP(AA$1,'[5]Base de Datos'!$A$4:$X$34,5,0)/1000>0,VLOOKUP(AA$1,'[5]Base de Datos'!$A$4:$X$34,5,0)/1000,0),0) -> 0 | AB55: =+IFERROR(IF(VLOOKUP(AB$1,'[5]Base de Datos'!$A$4:$X$34,5,0)/1000>0,VLOOKUP(AB$1,'[5]Base de Datos'!$A$4:$X$34,5,0)/1000,0),0) -> 0 | AC55: =+IFERROR(IF(VLOOKUP(AC$1,'[5]Base de Datos'!$A$4:$X$34,5,0)/1000>0,VLOOKUP(AC$1,'[5]Base de Datos'!$A$4:$X$34,5,0)/1000,0),0) -> 0 | AD55: =+IFERROR(IF(VLOOKUP(AD$1,'[5]Base de Datos'!$A$4:$X$34,5,0)/1000>0,VLOOKUP(AD$1,'[5]Base de Datos'!$A$4:$X$34,5,0)/1000,0),0) -> 0 | AE55: =+IFERROR(IF(VLOOKUP(AE$1,'[5]Base de Datos'!$A$4:$X$34,5,0)/1000>0,VLOOKUP(AE$1,'[5]Base de Datos'!$A$4:$X$34,5,0)/1000,0),0) -> 0 | AF55: =+IFERROR(IF(VLOOKUP(AF$1,'[5]Base de Datos'!$A$4:$X$34,5,0)/1000>0,VLOOKUP(AF$1,'[5]Base de Datos'!$A$4:$X$34,5,0)/1000,0),0) -> 0 | AG55: =+Y55+SUM(Z55:AF55) -> 415.151 | AH55: =+IFERROR(IF(VLOOKUP(AH$1,'[5]Base de Datos'!$A$4:$X$34,5,0)/1000>0,VLOOKUP(AH$1,'[5]Base de Datos'!$A$4:$X$34,5,0)/1000,0),0) -> 0 | AI55: =+IFERROR(IF(VLOOKUP(AI$1,'[5]Base de Datos'!$A$4:$X$34,5,0)/1000>0,VLOOKUP(AI$1,'[5]Base de Datos'!$A$4:$X$34,5,0)/1000,0),0) -> 0 | AJ55: =+IFERROR(IF(VLOOKUP(AJ$1,'[5]Base de Datos'!$A$4:$X$34,5,0)/1000>0,VLOOKUP(AJ$1,'[5]Base de Datos'!$A$4:$X$34,5,0)/1000,0),0) -> 0 | AK55: =+AG55+SUM(AH55:AJ55) -> 415.151
A56: TEA% 41% | B56: =IFERROR(+B55/B54,0) -> 0.41141947 | C56: =IFERROR(+C55/C54,0) -> 0.41014928 | D56: =IFERROR(+D55/D54,0) -> 0.41058637 | E56: =IFERROR(+E55/E54,0) -> 0.41105751 | F56: =IFERROR(+F55/F54,0) -> 0.41062064 | G56: =IFERROR(+G55/G54,0) -> 0.3976617 | H56: =IFERROR(+H55/H54,0) -> 0.41870369 | I56: =IFERROR(+I55/I54,0) -> 0.41251257 | ... AK56: =IFERROR(+AK55/AK54,0) -> 0.41087584
T65: =+SUM(E35:M35) -> 5558.942
T66: =+SUM(E36:M36) -> 1.9485558
T67: =+SUM(E37:M37) -> 5446.75
T70: =+T67-T65 -> -112.192

Sheet Resumen UPSTREAM
B3: RFF Procesada | D3: ACUMULADO S1 | J3: CPO | R3: TAE% | X3: ALMENDRA Y KPO
C4: 1
B5: PLANTA | C5: ME | D5: Real | E5: Dif | F5: % | J5: PLANTA | K5: CPO ME | L5: CPO REAL | M5: DIF TM | N5: % CUMPL | R5: PLANTA | S5: TEA ME | T5: TEA REAL | U5: DIF | Y5: ME | Z5: Real | AA5: Dif | AB5: % | AC5: =+DAY(TODAY()-1) -> 11
B6: Ext. Codazzi | C6: =+HLOOKUP($D$3,UPSTREAM!$A$1:$AK$37,5,0)*$C$4 -> 4350 | D6: =+HLOOKUP($D$3,UPSTREAM!$A$1:$AK$37,6,0) -> 5210.859 | E6: =+D6-C6 -> 860.859 | F6: =+D6/C6 -> 1.1978986 | J6: Ext. Codazzi | K6: =+HLOOKUP($D$3,UPSTREAM!$A$1:$AK$37,5,0)*UPSTREAM!$A$40*C4 -> 939.6 | L6: =+HLOOKUP($D$3,UPSTREAM!$A$1:$AK$37,7,0) -> 1110.38 | M6: =+L6-K6 -> 170.78 | N6: =+L6/K6 -> 1.1817582 | R6: Ext. Codazzi | S6: =+UPSTREAM!A40 -> 0.216 | T6: =+HLOOKUP($D$3,UPSTREAM!$A$1:$AK$37,8,0) -> 0.21308963 | U6: =+T6-S6 -> -0.0029103731 | X6: ALMENDRA | Y6: =+HLOOKUP($D$3,UPSTREAM!$A$1:$BD$60,53,0) -> 720 | Z6: =+HLOOKUP($D$3,UPSTREAM!$A$1:$BD$60,54,0) -> 803.014 | AA6: =+Z6-Y6 -> 83.014 | AB6: =+Z6/Y6 -> 1.1152972 | AC6: =+Z6/AC5 -> 73.001273 | AD6: Promedio díario
B7: Ext. MLB | C7: =+HLOOKUP($D$3,UPSTREAM!$A$1:$AK$37,12,0)*C4 -> 1100 | D7: =+HLOOKUP($D$3,UPSTREAM!$A$1:$AK$37,13,0) -> 1419.81 | E7: =+D7-C7 -> 319.81 | F7: =+D7/C7 -> 1.2907364 | J7: Ext. MLB | K7: =+HLOOKUP($D$3,UPSTREAM!$A$1:$AK$37,12,0)*UPSTREAM!$A$41*C4 -> 204.6 | L7: =+HLOOKUP($D$3,UPSTREAM!$A$1:$AK$37,14,0) -> 261.761 | M7: =+L7-K7 -> 57.161 | N7: =+L7/K7 -> 1.2793793 | R7: Ext. MLB | S7: =+UPSTREAM!A41 -> 0.186 | T7: =+HLOOKUP($D$3,UPSTREAM!$A$1:$AK$37,15,0) -> 0.1843634 | U7: =+T7-S7 -> -0.0016365993 | X7: KPO | Y7: =+Y6*Y8 -> 295.2 | Z7: =+HLOOKUP($D$3,UPSTREAM!$A$1:$BD$60,55,0) -> 329.544 | AA7: =+Z7-Y7 -> 34.344 | AB7: =+Z7/Y7 -> 1.1163415
B8: Ext. A&G | C8: =+HLOOKUP($D$3,UPSTREAM!$A$1:$AK$37,26,0)*C4 -> 5450 | D8: =+HLOOKUP($D$3,UPSTREAM!$A$1:$AK$37,27,0) -> 4783.851 | E8: =+D8-C8 -> -666.149 | F8: =+D8/C8 -> 0.87777083 | J8: Ext. A&G | K8: =+HLOOKUP($D$3,UPSTREAM!$A$1:$AK$37,26,0)*UPSTREAM!$A$42*C4 -> 1280.75 | L8: =+HLOOKUP($D$3,UPSTREAM!$A$1:$AK$37,28,0) -> 1121.711 | M8: =+L8-K8 -> -159.039 | N8: =+L8/K8 -> 0.87582354 | R8: Ext. A&G | S8: =+UPSTREAM!A42 -> 0.235 | T8: =+HLOOKUP($D$3,UPSTREAM!$A$1:$AK$37,29,0) -> 0.23447867 | U8: =+T8-S8 -> -0.00052133417 | X8: EXTRACCIÓN | Y8: =+UPSTREAM!AN51 -> 0.41 | Z8: =+Z7/Z6 -> 0.41038388 | AA8: =+Z8-Y8 -> 0.00038387874 | AB8: =+Z8/Y8 -> 1.0009363
B9: Ext. Sinú | C9: =+HLOOKUP($D$3,UPSTREAM!$A$1:$AK$37,19,0)*C4 -> 1300 | D9: =+HLOOKUP($D$3,UPSTREAM!$A$1:$AK$37,20,0) -> 1566 | E9: =+D9-C9 -> 266 | F9: =+IFERROR(D9/C9,0) -> 1.2046154 | J9: Ext. Sinú | K9: =+HLOOKUP($D$3,UPSTREAM!$A$1:$AK$37,19,0)*UPSTREAM!$A$43*C4 -> 286 | L9: =+HLOOKUP($D$3,UPSTREAM!$A$1:$AK$37,21,0) -> 303.24 | M9: =+L9-K9 -> 17.24 | N9: =+L9/K9 -> 1.0602797 | R9: Ext. Sinú | S9: =+UPSTREAM!A43 -> 0.22 | T9: =+HLOOKUP($D$3,UPSTREAM!$A$1:$AK$37,22,0) -> 0.19363985 | U9: =+T9-S9 -> -0.026360153
B11: TOTAL | C11: =+SUM(C6:C9) -> 12200 | D11: =+SUM(D6:D9) -> 12980.52 | E11: =+D11-C11 -> 780.52 | F11: =+D11/C11 -> 1.063977 | J11: TOTAL | K11: =+SUM(K6:K9) -> 2710.95 | L11: =+SUM(L6:L9) -> 2797.092 | M11: =+L11-K11 -> 86.142 | N11: =+L11/K11 -> 1.0317756 | R11: TOTAL | S11: =+K11/C11 -> 0.22220902 | T11: =+L11/D11 -> 0.21548382 | U11: =+T11-S11 -> -0.0067251991
B13: PLANTA | C13: ME | D13: Real | E13: Dif | F13: % | J13: PLANTA | K13: ME | L13: Real | M13: Dif | N13: %
B14: RFF Producción sin Sinú | C14: =+C6+C7+C8 -> 10900 | D14: =+D6+D7+D8 -> 11414.52 | E14: =+D14-C14 -> 514.52 | F14: =+D14/C14 -> 1.0472037 | J14: CPO PROD sin Sinú | K14: =+K6+K7+K8 -> 2424.95 | L14: =+L6+L7+L8 -> 2493.852 | M14: =+L14-K14 -> 68.902 | N14: =+L14/K14 -> 1.0284138
X18: RECUPERACIÓN DE ALMENDRA
C19: Fruta Inventario | J19: INVENTARIO CPO
B20: Ext. Codazzi | C20: 0 | K20: =+TODAY()-1 -> 46002 | X20: PLANTA | Y20: ME PK | Z20: Real PK | AA20: % CUMPL | AB20: DIF TM
B21: Ext. MLB | C21: 0 | J21: PLANTA | K21: TM | X21: Ext. Codazzi | Y21: 0.055 | Z21: 0.0614 | AA21: =+Z21/Y21 -> 1.1163636 | AB21: =+Z21-Y21 -> 0.0064
B22: Ext. A&G | C22: 0 | J22: Ext. Codazzi | K22: =+VLOOKUP(K20,'[4]Base de Datos'!$A$5:$EI$35,40,0)/1000 -> 575.736 | X22: Ext. MLB | Y22: 0.05 | Z22: 0.061 | AA22: =+Z22/Y22 -> 1.22 | AB22: =+Z22-Y22 -> 0.011
B23: Ext. Sinú | C23: 0 | J23: Ext. MLB | K23: =+VLOOKUP(K20,'[4]Base de Datos'!$A$5:$EI$35,11,0)/1000 -> 88.636 | X23: Ext. A&G | Y23: 0.05 | Z23: 0.0438 | AA23: =+Z23/Y23 -> 0.876 | AB23: =+Z23-Y23 -> -0.0062
J24: Ext. A&G | K24: =+VLOOKUP(K20,'[4]Base de Datos'!$A$5:$EI$35,25,0)/1000 -> 174.257
J25: Ext. Sinú | K25: =+VLOOKUP(K20,'[4]BD Sinu'!$A$5:$EI$35,11,0)/1000 -> 121.605
J27: TOTAL | K27: =+SUM(K22:K25) -> 960.234 | X27: INVENTARIO ALMENDRA
J29: Venta CPO | X29: PLANTA | Y29: TM
X30: Ext. Codazzi | Y30: 235
J31: Cliente | K31: Objetivo | L31: Real | M31: Dif | N31: % | X31: Ext. MLB | Y31: 0.5
J32: CI CARIBBEAN | K32: 0 | L32: 0 | M32: =+K32-L32 -> 0 | N32: =+IFERROR(L32/K32,"") | X32: Ext. A&G | Y32: 60
J33: Venta Acepalma | K33: 0 | L33: 0 | M33: =+K33-L33 -> 0 | N33: =+IFERROR(L33/K33,"") | X33: Ext. Sinú* | Y33: 400
J34: Golden Agri 1 | K34: 0 | L34: 0 | M34: =+K34-L34 -> 0 | N34: =+IFERROR(L34/K34,"") | X34: Ext. Codazzi* | Y34: 83
J35: CPO Alto Estearico | K35: 0 | L35: 0 | M35: =+K35-L35 -> 0 | N35: =+IFERROR(L35/K35,"") | X35: Ext. MLB* | Y35: 157
N36: =+IFERROR(L36/K36,"") | X36: *Nuez
J37: TOTAL | K37: =+SUM(K32:K35) -> 0 | L37: =+SUM(L32:L35) -> 0 | M37: =+SUM(M32:M35) -> 0 | N37: =+IFERROR(L37/K37,"")
J42: Prestamo Acepalma CPO
K43: ME | L43: REAL
J44: Ingreso CPO | K44: 0 | L44: 0
J45: Despacho CPO | K45: 700 | L45: 0

Sheet DOWNSTREAM
A1: ZONA | B1: 45992 | C1: =+B1+1 -> 45993 | D1: =+C1+1 -> 45994 | E1: =+D1+1 -> 45995 | F1: =+E1+1 -> 45996 | G1: =+F1+1 -> 45997 | H1: =+G1+1 -> 45998 | I1: =+H1+1 -> 45999 | J1: ACUMULADO S1 | K1: =+I1+1 -> 46000 | L1: =+K1+1 -> 46001 | M1: =+L1+1 -> 46002 | N1: =+M1+1 -> 46003 | O1: =+N1+1 -> 46004 | P1: =+O1+1 -> 46005 | Q1: ACUMULADO S2 | R1: =+P1+1 -> 46006 | S1: =+R1+1 -> 46007 | T1: =+S1+1 -> 46008 | U1: =+T1+1 -> 46009 | V1: =+U1+1 -> 46010 | W1: =+V1+1 -> 46011 | X1: =+W1+1 -> 46012 | Y1: ACUMULADO S3 | Z1: =+X1+1 -> 46013 | AA1: =+Z1+1 -> 46014 | AB1: =+AA1+1 -> 46015 | AC1: =+AB7+1 -> 46016 | AD1: =+AC1+1 -> 46017 | AE1: =+AD1+1 -> 46018 | AF1: =+AE1+1 -> 46019 | AG1: ACUMULADO S4 | AH1: =+AF1+1 -> 46020 | AI1: =+AH1+1 -> 46021 | AJ1: =+AI1+1 -> 46022 | AK1: ACUMULADO DIC 25
A2: Refinería 1 ME | B2: =+HLOOKUP(B$1,'[6]Proyección Diaria'!$C$7:$AH$155,36,0)/1000 -> 355 | C2: =+HLOOKUP(C$1,'[6]Proyección Diaria'!$C$7:$AH$155,36,0)/1000 -> 355 | D2: =+HLOOKUP(D$1,'[6]Proyección Diaria'!$C$7:$AH$155,36,0)/1000 -> 355 | E2: =+HLOOKUP(E$1,'[6]Proyección Diaria'!$C$7:$AH$155,36,0)/1000 -> 355 | F2: =+HLOOKUP(F$1,'[6]Proyección Diaria'!$C$7:$AH$155,36,0)/1000 -> 355 | G2: =+HLOOKUP(G$1,'[6]Proyección Diaria'!$C$7:$AH$155,36,0)/1000 -> 355 | H2: =+HLOOKUP(H$1,'[6]Proyección Diaria'!$C$7:$AH$155,36,0)/1000 -> 280 | I2: =+HLOOKUP(I$1,'[6]Proyección Diaria'!$C$7:$AH$155,36,0)/1000 -> 355 | J2: =+SUM(B2:I2) -> 2765 | K2: =+HLOOKUP(K$1,'[6]Proyección Diaria'!$C$7:$AH$155,36,0)/1000 -> 355 | L2: =+HLOOKUP(L$1,'[6]Proyección Diaria'!$C$7:$AH$155,36,0)/1000 -> 355 | M2: =+HLOOKUP(M$1,'[6]Proyección Diaria'!$C$7:$AH$155,36,0)/1000 -> 355 | N2: =+HLOOKUP(N$1,'[6]Proyección Diaria'!$C$7:$AH$155,36,0)/1000 -> 355 | O2: =+HLOOKUP(O$1,'[6]Proyección Diaria'!$C$7:$AH$155,36,0)/1000 -> 355 | P2: =+HLOOKUP(P$1,'[6]Proyección Diaria'!$C$7:$AH$155,36,0)/1000 -> 280 | Q2: =+SUM(K2:P2)+J2 -> 4820 | R2: =+HLOOKUP(R$1,'[6]Proyección Diaria'!$C$7:$AH$155,36,0)/1000 -> 355 | S2: =+HLOOKUP(S$1,'[6]Proyección Diaria'!$C$7:$AH$155,36,0)/1000 -> 355 | T2: =+HLOOKUP(T$1,'[6]Proyección Diaria'!$C$7:$AH$155,36,0)/1000 -> 355 | U2: =+HLOOKUP(U$1,'[6]Proyección Diaria'!$C$7:$AH$155,36,0)/1000 -> 355 | V2: =+HLOOKUP(V$1,'[6]Proyección Diaria'!$C$7:$AH$155,36,0)/1000 -> 355 | W2: =+HLOOKUP(W$1,'[6]Proyección Diaria'!$C$7:$AH$155,36,0)/1000 -> 355 | X2: =+HLOOKUP(X$1,'[6]Proyección Diaria'!$C$7:$AH$155,36,0)/1000 -> 280 | Y2: =+Q2+SUM(R2:X2) -> 7230 | Z2: =+HLOOKUP(Z$1,'[6]Proyección Diaria'!$C$7:$AH$155,36,0)/1000 -> 355 | AA2: =+HLOOKUP(AA$1,'[6]Proyección Diaria'!$C$7:$AH$155,36,0)/1000 -> 355 | AB2: =+HLOOKUP(AB$1,'[6]Proyección Diaria'!$C$7:$AH$155,36,0)/1000 -> 355 | AC2: =+HLOOKUP(AC$1,'[6]Proyección Diaria'!$C$7:$AH$155,36,0)/1000 -> 355 | AD2: =+HLOOKUP(AD$1,'[6]Proyección Diaria'!$C$7:$AH$155,36,0)/1000 -> 355 | AE2: =+HLOOKUP(AE$1,'[6]Proyección Diaria'!$C$7:$AH$155,36,0)/1000 -> 355 | AF2: =+HLOOKUP(AF$1,'[6]Proyección Diaria'!$C$7:$AH$155,36,0)/1000 -> 280 | AG2: =+Y2+SUM(Z2:AF2) -> 9640 | AH2: =+HLOOKUP(AH$1,'[6]Proyección Diaria'!$C$7:$AH$155,36,0)/1000 -> 355 | AI2: =+HLOOKUP(AI$1,'[6]Proyección Diaria'!$C$7:$AH$155,36,0)/1000 -> 355 | AJ2: =+HLOOKUP(AJ$1,'[6]Proyección Diaria'!$C$7:$AH$155,36,0)/1000 -> 100 | AK2: =+AG2+SUM(AH2:AJ2) -> 10450
A3: Refinería 1 Real | B3: 362.466 | C3: 362.466 | D3: 259.688 | E3: 352.783 | F3: 326.921 | G3: 353.606 | H3: 354 | I3: 341.32 | J3: =+SUM(B3:I3) -> 2713.25 | Q3: =+SUM(K3:P3)+J3 -> 2713.25 | Y3: =+Q3+SUM(R3:X3) -> 2713.25 | AG3: =+Y3+SUM(Z3:AF3) -> 2713.25 | AK3: =+AG3+SUM(AH3:AJ3) -> 2713.25
A4: % Cumplimiento | B4: =IFERROR(B3/B2,0) -> 1.021031 | C4: =IFERROR(C3/C2,0) -> 1.021031 | D4: =IFERROR(D3/D2,0) -> 0.73151549 | E4: =IFERROR(E3/E2,0) -> 0.99375493 | F4: =IFERROR(F3/F2,0) -> 0.92090423 | G4: =IFERROR(G3/G2,0) -> 0.99607324 | H4: =IFERROR(H3/H2,0) -> 1.2642857 | I4: =IFERROR(I3/I2,0) -> 0.96146479 | ... AK4: =IFERROR(AK3/AK2,0) -> 0.25964115
A5: Rendimiento (94,5%)
A6: Acidez Ingreso
A7: Rojo Recepción | AB7: =+AA1+1 -> 46015
A8: Rojo Saponif | AB8: 360
A9: Inventario Inicio
A10: Refinería 2 ME | B10: =+HLOOKUP(B$1,'[6]Proyección Diaria'!$C$7:$AH$155,37,0)/1000+HLOOKUP(B$1,'[6]Proyección Diaria'!$C$7:$AH$155,73,0)/1000 -> 30 | C10: =+HLOOKUP(C$1,'[6]Proyección Diaria'!$C$7:$AH$155,37,0)/1000+HLOOKUP(C$1,'[6]Proyección Diaria'!$C$7:$AH$155,73,0)/1000 -> 0 | D10: =+HLOOKUP(D$1,'[6]Proyección Diaria'!$C$7:$AH$155,37,0)/1000+HLOOKUP(D$1,'[6]Proyección Diaria'!$C$7:$AH$155,73,0)/1000 -> 35 | E10: =+HLOOKUP(E$1,'[6]Proyección Diaria'!$C$7:$AH$155,37,0)/1000+HLOOKUP(E$1,'[6]Proyección Diaria'!$C$7:$AH$155,73,0)/1000 -> 35 | F10: =+HLOOKUP(F$1,'[6]Proyección Diaria'!$C$7:$AH$155,37,0)/1000+HLOOKUP(F$1,'[6]Proyección Diaria'!$C$7:$AH$155,73,0)/1000 -> 35 | G10: =+HLOOKUP(G$1,'[6]Proyección Diaria'!$C$7:$AH$155,37,0)/1000+HLOOKUP(G$1,'[6]Proyección Diaria'!$C$7:$AH$155,73,0)/1000 -> 35 | H10: =+HLOOKUP(H$1,'[6]Proyección Diaria'!$C$7:$AH$155,37,0)/1000+HLOOKUP(H$1,'[6]Proyección Diaria'!$C$7:$AH$155,73,0)/1000 -> 0 | I10: =+HLOOKUP(I$1,'[6]Proyección Diaria'!$C$7:$AH$155,37,0)/1000+HLOOKUP(I$1,'[6]Proyección Diaria'!$C$7:$AH$155,73,0)/1000 -> 35 | J10: =+SUM(B10:I10) -> 205 | K10: =+HLOOKUP(K$1,'[6]Proyección Diaria'!$C$7:$AH$155,37,0)/1000+HLOOKUP(K$1,'[6]Proyección Diaria'!$C$7:$AH$155,73,0)/1000 -> 15 | L10: =+HLOOKUP(L$1,'[6]Proyección Diaria'!$C$7:$AH$155,37,0)/1000+HLOOKUP(L$1,'[6]Proyección Diaria'!$C$7:$AH$155,73,0)/1000 -> 37 | M10: =+HLOOKUP(M$1,'[6]Proyección Diaria'!$C$7:$AH$155,37,0)/1000+HLOOKUP(M$1,'[6]Proyección Diaria'!$C$7:$AH$155,73,0)/1000 -> 37 | N10: =+HLOOKUP(N$1,'[6]Proyección Diaria'!$C$7:$AH$155,37,0)/1000+HLOOKUP(N$1,'[6]Proyección Diaria'!$C$7:$AH$155,73,0)/1000 -> 37 | O10: =+HLOOKUP(O$1,'[6]Proyección Diaria'!$C$7:$AH$155,37,0)/1000+HLOOKUP(O$1,'[6]Proyección Diaria'!$C$7:$AH$155,73,0)/1000 -> 37 | P10: =+HLOOKUP(P$1,'[6]Proyección Diaria'!$C$7:$AH$155,37,0)/1000+HLOOKUP(P$1,'[6]Proyección Diaria'!$C$7:$AH$155,73,0)/1000 -> 37 | Q10: =+SUM(K10:P10)+J10 -> 405 | R10: =+HLOOKUP(R$1,'[6]Proyección Diaria'!$C$7:$AH$155,37,0)/1000+HLOOKUP(R$1,'[6]Proyección Diaria'!$C$7:$AH$155,73,0)/1000 -> 37 | S10: =+HLOOKUP(S$1,'[6]Proyección Diaria'!$C$7:$AH$155,37,0)/1000+HLOOKUP(S$1,'[6]Proyección Diaria'!$C$7:$AH$155,73,0)/1000 -> 37 | T10: =+HLOOKUP(T$1,'[6]Proyección Diaria'!$C$7:$AH$155,37,0)/1000+HLOOKUP(T$1,'[6]Proyección Diaria'!$C$7:$AH$155,73,0)/1000 -> 37 | U10: =+HLOOKUP(U$1,'[6]Proyección Diaria'!$C$7:$AH$155,37,0)/1000+HLOOKUP(U$1,'[6]Proyección Diaria'!$C$7:$AH$155,73,0)/1000 -> 37 | V10: =+HLOOKUP(V$1,'[6]Proyección Diaria'!$C$7:$AH$155,37,0)/1000+HLOOKUP(V$1,'[6]Proyección Diaria'!$C$7:$AH$155,73,0)/1000 -> 25 | W10: =+HLOOKUP(W$1,'[6]Proyección Diaria'!$C$7:$AH$155,37,0)/1000+HLOOKUP(W$1,'[6]Proyección Diaria'!$C$7:$AH$155,73,0)/1000 -> 10 | X10: =+HLOOKUP(X$1,'[6]Proyección Diaria'!$C$7:$AH$155,37,0)/1000+HLOOKUP(X$1,'[6]Proyección Diaria'!$C$7:$AH$155,73,0)/1000 -> 30 | Y10: =+Q10+SUM(R10:X10) -> 618 | Z10: =+HLOOKUP(Z$1,'[6]Proyección Diaria'!$C$7:$AH$155,37,0)/1000+HLOOKUP(Z$1,'[6]Proyección Diaria'!$C$7:$AH$155,73,0)/1000 -> 30 | AA10: =+HLOOKUP(AA$1,'[6]Proyección Diaria'!$C$7:$AH$155,37,0)/1000+HLOOKUP(AA$1,'[6]Proyección Diaria'!$C$7:$AH$155,73,0)/1000 -> 30 | AB10: =+HLOOKUP(AB$1,'[6]Proyección Diaria'!$C$7:$AH$155,37,0)/1000+HLOOKUP(AB$1,'[6]Proyección Diaria'!$C$7:$AH$155,73,0)/1000 -> 30 | AC10: =+HLOOKUP(AC$1,'[6]Proyección Diaria'!$C$7:$AH$155,37,0)/1000+HLOOKUP(AC$1,'[6]Proyección Diaria'!$C$7:$AH$155,73,0)/1000 -> 30 | AD10: =+HLOOKUP(AD$1,'[6]Proyección Diaria'!$C$7:$AH$155,37,0)/1000+HLOOKUP(AD$1,'[6]Proyección Diaria'!$C$7:$AH$155,73,0)/1000 -> 30 | AE10: =+HLOOKUP(AE$1,'[6]Proyección Diaria'!$C$7:$AH$155,37,0)/1000+HLOOKUP(AE$1,'[6]Proyección Diaria'!$C$7:$AH$155,73,0)/1000 -> 30 | AF10: =+HLOOKUP(AF$1,'[6]Proyección Diaria'!$C$7:$AH$155,37,0)/1000+HLOOKUP(AF$1,'[6]Proyección Diaria'!$C$7:$AH$155,73,0)/1000 -> 30 | AG10: =+Y10+SUM(Z10:AF10) -> 828 | AH10: =+HLOOKUP(AH$1,'[6]Proyección Diaria'!$C$7:$AH$155,37,0)/1000+HLOOKUP(AH$1,'[6]Proyección Diaria'!$C$7:$AH$155,73,0)/1000 -> 30 | AI10: =+HLOOKUP(AI$1,'[6]Proyección Diaria'!$C$7:$AH$155,37,0)/1000+HLOOKUP(AI$1,'[6]Proyección Diaria'!$C$7:$AH$155,73,0)/1000 -> 30 | AJ10: =+HLOOKUP(AJ$1,'[6]Proyección Diaria'!$C$7:$AH$155,37,0)/1000+HLOOKUP(AJ$1,'[6]Proyección Diaria'!$C$7:$AH$155,73,0)/1000 -> 10 | AK10: =+AG10+SUM(AH10:AJ10) -> 898
A11: Refineria 2 Real | B11: =+SUM(B12:B13) -> 30.13 | C11: =+SUM(C12:C13) -> 30.13 | D11: =+SUM(D12:D13) -> 31.052 | E11: =+SUM(E12:E13) -> 29.081 | F11: =+SUM(F12:F13) -> 40.847 | G11: =+SUM(G12:G13) -> 23.287 | H11: =+SUM(H12:H13) -> 21 | I11: =+SUM(I12:I13) -> 30.346 | J11: =+SUM(B11:I11) -> 235.873 | K11: =+SUM(K12:K13) -> 0 | L11: =+SUM(L12:L13) -> 0 | M11: =+SUM(M12:M13) -> 0 | N11: =+SUM(N12:N13) -> 0 | O11: =+SUM(O12:O13) -> 0 | P11: =+SUM(P12:P13) -> 0 | Q11: =+SUM(K11:P11)+J11 -> 235.873 | R11: =+SUM(R12:R13) -> 0 | S11: =+SUM(S12:S13) -> 0 | T11: =+SUM(T12:T13) -> 0 | U11: =+SUM(U12:U13) -> 0 | V11: =+SUM(V12:V13) -> 0 | W11: =+SUM(W12:W13) -> 0 | X11: =+SUM(X12:X13) -> 0 | Y11: =+Q11+SUM(R11:X11) -> 235.873 | Z11: =+SUM(Z12:Z13) -> 0 | AA11: =+SUM(AA12:AA13) -> 0 | AB11: =+SUM(AB12:AB13) -> 0 | AC11: =+SUM(AC12:AC13) -> 0 | AD11: =+SUM(AD12:AD13) -> 0 | AE11: =+SUM(AE12:AE13) -> 0 | AF11: =+SUM(AF12:AF13) -> 0 | AG11: =+Y11+SUM(Z11:AF11) -> 235.873 | AH11: =+SUM(AH12:AH13) -> 0 | AI11: =+SUM(AI12:AI13) -> 0 | AJ11: =+SUM(AJ12:AJ13) -> 0 | AK11: =+AG11+SUM(AH11:AJ11) -> 235.873
A12: RBD Palma | B12: 30.13 | C12: 30.13 | H12: 21 | I12: 30.346 | J12: =+SUM(B12:I12) -> 111.606 | Q12: =+SUM(K12:P12)+J12 -> 111.606 | Y12: =+Q12+SUM(R12:X12) -> 111.606 | AG12: =+Y12+SUM(Z12:AF12) -> 111.606 | AK12: =+AG12+SUM(AH12:AJ12) -> 111.606
A13: RBD Palmiste | D13: 31.052 | E13: 29.081 | F13: 40.847 | G13: 23.287 | J13: =+SUM(B13:I13) -> 124.267 | Q13: =+SUM(K13:P13)+J13 -> 124.267 | Y13: =+Q13+SUM(R13:X13) -> 124.267 | AG13: =+Y13+SUM(Z13:AF13) -> 124.267 | AK13: =+AG13+SUM(AH13:AJ13) -> 124.267
A14: % Cumplimiento | B14: =IFERROR(+B11/B10,0) -> 1.0043333 | C14: =IFERROR(+C11/C10,0) -> 0 | D14: =IFERROR(+D11/D10,0) -> 0.8872 | E14: =IFERROR(+E11/E10,0) -> 0.83088571 | F14: =IFERROR(+F11/F10,0) -> 1.1670571 | G14: =IFERROR(+G11/G10,0) -> 0.66534286 | H14: =IFERROR(+H11/H10,0) -> 0 | I14: =IFERROR(+I11/I10,0) -> 0.86702857 | ... AK14: =IFERROR(+AK11/AK10,0) -> 0.26266481
A15: Rendimiento (93,5%)
A16: Rojo Recepción
A17: Rojo Saponif
A18: Inventario Inicio | AB18: 36
A19: Fracc 1 ME | B19: =+HLOOKUP(B$1,'[6]Proyección Diaria'!$C$7:$AH$155,82,0)/1000 -> 92 | C19: =+HLOOKUP(C$1,'[6]Proyección Diaria'!$C$7:$AH$155,82,0)/1000 -> 92 | D19: =+HLOOKUP(D$1,'[6]Proyección Diaria'!$C$7:$AH$155,82,0)/1000 -> 92 | E19: =+HLOOKUP(E$1,'[6]Proyección Diaria'!$C$7:$AH$155,82,0)/1000 -> 92 | F19: =+HLOOKUP(F$1,'[6]Proyección Diaria'!$C$7:$AH$155,82,0)/1000 -> 92 | G19: =+HLOOKUP(G$1,'[6]Proyección Diaria'!$C$7:$AH$155,82,0)/1000 -> 92 | H19: =+HLOOKUP(H$1,'[6]Proyección Diaria'!$C$7:$AH$155,82,0)/1000 -> 92 | I19: =+HLOOKUP(I$1,'[6]Proyección Diaria'!$C$7:$AH$155,82,0)/1000 -> 92 | J19: =+SUM(B19:I19) -> 736 | K19: =+HLOOKUP(K$1,'[6]Proyección Diaria'!$C$7:$AH$155,82,0)/1000 -> 92 | L19: =+HLOOKUP(L$1,'[6]Proyección Diaria'!$C$7:$AH$155,82,0)/1000 -> 92 | M19: =+HLOOKUP(M$1,'[6]Proyección Diaria'!$C$7:$AH$155,82,0)/1000 -> 92 | N19: =+HLOOKUP(N$1,'[6]Proyección Diaria'!$C$7:$AH$155,82,0)/1000 -> 92 | O19: =+HLOOKUP(O$1,'[6]Proyección Diaria'!$C$7:$AH$155,82,0)/1000 -> 92 | P19: =+HLOOKUP(P$1,'[6]Proyección Diaria'!$C$7:$AH$155,82,0)/1000 -> 92 | Q19: =+SUM(K19:P19)+J19 -> 1288 | R19: =+HLOOKUP(R$1,'[6]Proyección Diaria'!$C$7:$AH$155,82,0)/1000 -> 92 | S19: =+HLOOKUP(S$1,'[6]Proyección Diaria'!$C$7:$AH$155,82,0)/1000 -> 92 | T19: =+HLOOKUP(T$1,'[6]Proyección Diaria'!$C$7:$AH$155,82,0)/1000 -> 92 | U19: =+HLOOKUP(U$1,'[6]Proyección Diaria'!$C$7:$AH$155,82,0)/1000 -> 92 | V19: =+HLOOKUP(V$1,'[6]Proyección Diaria'!$C$7:$AH$155,82,0)/1000 -> 92 | W19: =+HLOOKUP(W$1,'[6]Proyección Diaria'!$C$7:$AH$155,82,0)/1000 -> 92 | X19: =+HLOOKUP(X$1,'[6]Proyección Diaria'!$C$7:$AH$155,82,0)/1000 -> 92 | Y19: =+Q19+SUM(R19:X19) -> 1932 | Z19: =+HLOOKUP(Z$1,'[6]Proyección Diaria'!$C$7:$AH$155,82,0)/1000 -> 92 | AA19: =+HLOOKUP(AA$1,'[6]Proyección Diaria'!$C$7:$AH$155,82,0)/1000 -> 92 | AB19: =+HLOOKUP(AB$1,'[6]Proyección Diaria'!$C$7:$AH$155,82,0)/1000 -> 92 | AC19: =+HLOOKUP(AC$1,'[6]Proyección Diaria'!$C$7:$AH$155,82,0)/1000 -> 92 | AD19: =+HLOOKUP(AD$1,'[6]Proyección Diaria'!$C$7:$AH$155,82,0)/1000 -> 92 | AE19: =+HLOOKUP(AE$1,'[6]Proyección Diaria'!$C$7:$AH$155,82,0)/1000 -> 92 | AF19: =+HLOOKUP(AF$1,'[6]Proyección Diaria'!$C$7:$AH$155,82,0)/1000 -> 92 | AG19: =+Y19+SUM(Z19:AF19) -> 2576 | AH19: =+HLOOKUP(AH$1,'[6]Proyección Diaria'!$C$7:$AH$155,82,0)/1000 -> 92 | AI19: =+HLOOKUP(AI$1,'[6]Proyección Diaria'!$C$7:$AH$155,82,0)/1000 -> 92 | AJ19: =+HLOOKUP(AJ$1,'[6]Proyección Diaria'!$C$7:$AH$155,82,0)/1000 -> 50 | AK19: =+AG19+SUM(AH19:AJ19) -> 2810
A20: Fracc 1 Real | B20: 100.85 | C20: 100.85 | D20: 80.01 | E20: 102 | F20: 88.59 | G20: 95.2 | H20: 81 | I20: 94.5 | J20: =+SUM(B20:I20) -> 743 | Q20: =+SUM(K20:P20)+J20 -> 743 | Y20: =+Q20+SUM(R20:X20) -> 743 | AG20: =+Y20+SUM(Z20:AF20) -> 743 | AK20: =+AG20+SUM(AH20:AJ20) -> 743
A21: % Cumplimiento | B21: =IFERROR(+B20/B19,0) -> 1.0961957 | C21: =IFERROR(+C20/C19,0) -> 1.0961957 | D21: =IFERROR(+D20/D19,0) -> 0.86967391 | E21: =IFERROR(+E20/E19,0) -> 1.1086957 | F21: =IFERROR(+F20/F19,0) -> 0.96293478 | G21: =IFERROR(+G20/G19,0) -> 1.0347826 | H21: =IFERROR(+H20/H19,0) -> 0.88043478 | I21: =IFERROR(+I20/I19,0) -> 1.0271739 | ... AK21: =IFERROR(+AK20/AK19,0) -> 0.26441281
A22: Rendimiento (75,2%)
A23: Rojo Recepción
A24: Rojo Saponif
A25: Fracc 2 ME | B25: =+HLOOKUP(B$1,'[6]Proyección Diaria'!$C$7:$AH$155,83,0)/1000 -> 117 | C25: =+HLOOKUP(C$1,'[6]Proyección Diaria'!$C$7:$AH$155,83,0)/1000 -> 117 | D25: =+HLOOKUP(D$1,'[6]Proyección Diaria'!$C$7:$AH$155,83,0)/1000 -> 117 | E25: =+HLOOKUP(E$1,'[6]Proyección Diaria'!$C$7:$AH$155,83,0)/1000 -> 117 | F25: =+HLOOKUP(F$1,'[6]Proyección Diaria'!$C$7:$AH$155,83,0)/1000 -> 117 | G25: =+HLOOKUP(G$1,'[6]Proyección Diaria'!$C$7:$AH$155,83,0)/1000 -> 117 | H25: =+HLOOKUP(H$1,'[6]Proyección Diaria'!$C$7:$AH$155,83,0)/1000 -> 117 | I25: =+HLOOKUP(I$1,'[6]Proyección Diaria'!$C$7:$AH$155,83,0)/1000 -> 117 | J25: =+SUM(B25:I25) -> 936 | K25: =+HLOOKUP(K$1,'[6]Proyección Diaria'!$C$7:$AH$155,83,0)/1000 -> 117 | L25: =+HLOOKUP(L$1,'[6]Proyección Diaria'!$C$7:$AH$155,83,0)/1000 -> 117 | M25: =+HLOOKUP(M$1,'[6]Proyección Diaria'!$C$7:$AH$155,83,0)/1000 -> 117 | N25: =+HLOOKUP(N$1,'[6]Proyección Diaria'!$C$7:$AH$155,83,0)/1000 -> 117 | O25: =+HLOOKUP(O$1,'[6]Proyección Diaria'!$C$7:$AH$155,83,0)/1000 -> 117 | P25: =+HLOOKUP(P$1,'[6]Proyección Diaria'!$C$7:$AH$155,83,0)/1000 -> 117 | Q25: =+SUM(K25:P25)+J25 -> 1638 | R25: =+HLOOKUP(R$1,'[6]Proyección Diaria'!$C$7:$AH$155,83,0)/1000 -> 117 | S25: =+HLOOKUP(S$1,'[6]Proyección Diaria'!$C$7:$AH$155,83,0)/1000 -> 117 | T25: =+HLOOKUP(T$1,'[6]Proyección Diaria'!$C$7:$AH$155,83,0)/1000 -> 117 | U25: =+HLOOKUP(U$1,'[6]Proyección Diaria'!$C$7:$AH$155,83,0)/1000 -> 117 | V25: =+HLOOKUP(V$1,'[6]Proyección Diaria'!$C$7:$AH$155,83,0)/1000 -> 117 | W25: =+HLOOKUP(W$1,'[6]Proyección Diaria'!$C$7:$AH$155,83,0)/1000 -> 117 | X25: =+HLOOKUP(X$1,'[6]Proyección Diaria'!$C$7:$AH$155,83,0)/1000 -> 117 | Y25: =+Q25+SUM(R25:X25) -> 2457 | Z25: =+HLOOKUP(Z$1,'[6]Proyección Diaria'!$C$7:$AH$155,83,0)/1000 -> 117 | AA25: =+HLOOKUP(AA$1,'[6]Proyección Diaria'!$C$7:$AH$155,83,0)/1000 -> 117 | AB25: =+HLOOKUP(AB$1,'[6]Proyección Diaria'!$C$7:$AH$155,83,0)/1000 -> 117 | AC25: =+HLOOKUP(AC$1,'[6]Proyección Diaria'!$C$7:$AH$155,83,0)/1000 -> 117 | AD25: =+HLOOKUP(AD$1,'[6]Proyección Diaria'!$C$7:$AH$155,83,0)/1000 -> 117 | AE25: =+HLOOKUP(AE$1,'[6]Proyección Diaria'!$C$7:$AH$155,83,0)/1000 -> 117 | AF25: =+HLOOKUP(AF$1,'[6]Proyección Diaria'!$C$7:$AH$155,83,0)/1000 -> 117 | AG25: =+Y25+SUM(Z25:AF25) -> 3276 | AH25: =+HLOOKUP(AH$1,'[6]Proyección Diaria'!$C$7:$AH$155,83,0)/1000 -> 117 | AI25: =+HLOOKUP(AI$1,'[6]Proyección Diaria'!$C$7:$AH$155,83,0)/1000 -> 117 | AJ25: =+HLOOKUP(AJ$1,'[6]Proyección Diaria'!$C$7:$AH$155,83,0)/1000 -> 50 | AK25: =+AG25+SUM(AH25:AJ25) -> 3560
A26: Fracc 2 Real | B26: 109.03 | C26: 109.03 | D26: 100.87 | E26: 108.22 | F26: 108.33 | G26: 109.24 | H26: 108.26 | I26: 110.635 | J26: =+SUM(B26:I26) -> 863.615 | Q26: =+SUM(K26:P26)+J26 -> 863.615 | Y26: =+Q26+SUM(R26:X26) -> 863.615 | AG26: =+Y26+SUM(Z26:AF26) -> 863.615 | AK26: =+AG26+SUM(AH26:AJ26) -> 863.615
A27: % Cumplimiento | B27: =IFERROR(+B26/B25,0) -> 0.93188034 | C27: =IFERROR(+C26/C25,0) -> 0.93188034 | D27: =IFERROR(+D26/D25,0) -> 0.86213675 | E27: =IFERROR(+E26/E25,0) -> 0.92495726 | F27: =IFERROR(+F26/F25,0) -> 0.92589744 | G27: =IFERROR(+G26/G25,0) -> 0.93367521 | H27: =IFERROR(+H26/H25,0) -> 0.92529915 | I27: =IFERROR(+I26/I25,0) -> 0.94559829 | ... AK27: =IFERROR(+AK26/AK25,0) -> 0.24258848
A28: Rendimiento (77,3%)
A29: Cold Test
A30: Rojo
A31: Inventario Inicio | AB31: 125
A32: Margarinas ME | B32: =+HLOOKUP(B$1,'[7]Programa Diario CODAZZI'!$F$8:$AL$44,37,0)/1000 -> 63 | C32: =+HLOOKUP(C$1,'[7]Programa Diario CODAZZI'!$F$8:$AL$44,37,0)/1000 -> 63 | D32: =+HLOOKUP(D$1,'[7]Programa Diario CODAZZI'!$F$8:$AL$44,37,0)/1000 -> 63 | E32: =+HLOOKUP(E$1,'[7]Programa Diario CODAZZI'!$F$8:$AL$44,37,0)/1000 -> 63 | F32: =+HLOOKUP(F$1,'[7]Programa Diario CODAZZI'!$F$8:$AL$44,37,0)/1000 -> 63 | G32: =+HLOOKUP(G$1,'[7]Programa Diario CODAZZI'!$F$8:$AL$44,37,0)/1000 -> 63 | H32: =+HLOOKUP(H$1,'[7]Programa Diario CODAZZI'!$F$8:$AL$44,37,0)/1000 -> 63 | I32: =+HLOOKUP(I$1,'[7]Programa Diario CODAZZI'!$F$8:$AL$44,37,0)/1000 -> 59.85 | J32: =+SUM(B32:I32) -> 500.85 | K32: =+HLOOKUP(K$1,'[7]Programa Diario CODAZZI'!$F$8:$AL$44,37,0)/1000 -> 63 | L32: =+HLOOKUP(L$1,'[7]Programa Diario CODAZZI'!$F$8:$AL$44,37,0)/1000 -> 63 | M32: =+HLOOKUP(M$1,'[7]Programa Diario CODAZZI'!$F$8:$AL$44,37,0)/1000 -> 63 | N32: =+HLOOKUP(N$1,'[7]Programa Diario CODAZZI'!$F$8:$AL$44,37,0)/1000 -> 63 | O32: =+HLOOKUP(O$1,'[7]Programa Diario CODAZZI'!$F$8:$AL$44,37,0)/1000 -> 63 | P32: =+HLOOKUP(P$1,'[7]Programa Diario CODAZZI'!$F$8:$AL$44,37,0)/1000 -> 59.85 | Q32: =+SUM(K32:P32)+J32 -> 875.7 | R32: =+HLOOKUP(R$1,'[7]Programa Diario CODAZZI'!$F$8:$AL$44,37,0)/1000 -> 63 | S32: =+HLOOKUP(S$1,'[7]Programa Diario CODAZZI'!$F$8:$AL$44,37,0)/1000 -> 63 | T32: =+HLOOKUP(T$1,'[7]Programa Diario CODAZZI'!$F$8:$AL$44,37,0)/1000 -> 63 | U32: =+HLOOKUP(U$1,'[7]Programa Diario CODAZZI'!$F$8:$AL$44,37,0)/1000 -> 63 | V32: =+HLOOKUP(V$1,'[7]Programa Diario CODAZZI'!$F$8:$AL$44,37,0)/1000 -> 63 | W32: =+HLOOKUP(W$1,'[7]Programa Diario CODAZZI'!$F$8:$AL$44,37,0)/1000 -> 63 | X32: =+HLOOKUP(X$1,'[7]Programa Diario CODAZZI'!$F$8:$AL$44,37,0)/1000 -> 63 | Y32: =+Q32+SUM(R32:X32) -> 1316.7 | Z32: =+HLOOKUP(Z$1,'[7]Programa Diario CODAZZI'!$F$8:$AL$44,37,0)/1000 -> 63 | AA32: =+HLOOKUP(AA$1,'[7]Programa Diario CODAZZI'!$F$8:$AL$44,37,0)/1000 -> 63 | AB32: =+HLOOKUP(AB$1,'[7]Programa Diario CODAZZI'!$F$8:$AL$44,37,0)/1000 -> 63 | AC32: =+HLOOKUP(AC$1,'[7]Programa Diario CODAZZI'!$F$8:$AL$44,37,0)/1000 -> 0 | AD32: =+HLOOKUP(AD$1,'[7]Programa Diario CODAZZI'!$F$8:$AL$44,37,0)/1000 -> 50.4 | AE32: =+HLOOKUP(AE$1,'[7]Programa Diario CODAZZI'!$F$8:$AL$44,37,0)/1000 -> 0 | AF32: =+HLOOKUP(AF$1,'[7]Programa Diario CODAZZI'!$F$8:$AL$44,37,0)/1000 -> 0 | AG32: =+Y32+SUM(Z32:AF32) -> 1556.1 | AH32: =+HLOOKUP(AH$1,'[7]Programa Diario CODAZZI'!$F$8:$AL$44,37,0)/1000 -> 0 | AI32: =+HLOOKUP(AI$1,'[7]Programa Diario CODAZZI'!$F$8:$AL$44,37,0)/1000 -> 0 | AJ32: =+HLOOKUP(AJ$1,'[7]Programa Diario CODAZZI'!$F$8:$AL$44,37,0)/1000 -> 0 | AK32: =+AG32+SUM(AH32:AJ32) -> 1556.1
A33: Margarinas Real | B33: =+IFERROR(VLOOKUP(B1,'[8]Hoja 1'!$A$2:$B$388,2,0)/1000,0) -> 0 | C33: =+IFERROR(VLOOKUP(C1,'[8]Hoja 1'!$A$2:$B$388,2,0)/1000,0) -> 53.55 | D33: 53.55 | E33: 69.3 | F33: 40.95 | G33: 72.45 | H33: 63 | I33: 56.7 | J33: =+SUM(B33:I33) -> 409.5 | K33: =+IFERROR(VLOOKUP(K1,'[8]Hoja 1'!$A$2:$B$388,2,0)/1000,0) -> 0 | L33: =+IFERROR(VLOOKUP(L1,'[8]Hoja 1'!$A$2:$B$388,2,0)/1000,0) -> 0 | M33: =+IFERROR(VLOOKUP(M1,'[8]Hoja 1'!$A$2:$B$388,2,0)/1000,0) -> 40.95 | N33: =+IFERROR(VLOOKUP(N1,'[8]Hoja 1'!$A$2:$B$388,2,0)/1000,0) -> 0 | O33: =+IFERROR(VLOOKUP(O1,'[8]Hoja 1'!$A$2:$B$388,2,0)/1000,0) -> 0 | P33: =+IFERROR(VLOOKUP(P1,'[8]Hoja 1'!$A$2:$B$388,2,0)/1000,0) -> 0 | Q33: =+SUM(K33:P33)+J33 -> 450.45 | R33: =+IFERROR(VLOOKUP(R1,'[8]Hoja 1'!$A$2:$B$388,2,0)/1000,0) -> 0 | S33: =+IFERROR(VLOOKUP(S1,'[8]Hoja 1'!$A$2:$B$388,2,0)/1000,0) -> 0 | T33: =+IFERROR(VLOOKUP(T1,'[8]Hoja 1'!$A$2:$B$388,2,0)/1000,0) -> 0 | U33: =+IFERROR(VLOOKUP(U1,'[8]Hoja 1'!$A$2:$B$388,2,0)/1000,0) -> 0 | V33: =+IFERROR(VLOOKUP(V1,'[8]Hoja 1'!$A$2:$B$388,2,0)/1000,0) -> 0 | W33: =+IFERROR(VLOOKUP(W1,'[8]Hoja 1'!$A$2:$B$388,2,0)/1000,0) -> 0 | X33: =+IFERROR(VLOOKUP(X1,'[8]Hoja 1'!$A$2:$B$388,2,0)/1000,0) -> 0 | Y33: =+Q33+SUM(R33:X33) -> 450.45 | Z33: =+IFERROR(VLOOKUP(Z1,'[8]Hoja 1'!$A$2:$B$388,2,0)/1000,0) -> 0 | AA33: =+IFERROR(VLOOKUP(AA1,'[8]Hoja 1'!$A$2:$B$388,2,0)/1000,0) -> 0 | AB33: =+IFERROR(VLOOKUP(AB1,'[8]Hoja 1'!$A$2:$B$388,2,0)/1000,0) -> 0 | AC33: =+IFERROR(VLOOKUP(AC1,'[8]Hoja 1'!$A$2:$B$388,2,0)/1000,0) -> 0 | AD33: =+IFERROR(VLOOKUP(AD1,'[8]Hoja 1'!$A$2:$B$388,2,0)/1000,0) -> 0 | AE33: =+IFERROR(VLOOKUP(AE1,'[8]Hoja 1'!$A$2:$B$388,2,0)/1000,0) -> 0 | AF33: =+IFERROR(VLOOKUP(AF1,'[8]Hoja 1'!$A$2:$B$388,2,0)/1000,0) -> 0 | AG33: =+Y33+SUM(Z33:AF33) -> 450.45 | AH33: =+IFERROR(VLOOKUP(AH1,'[8]Hoja 1'!$A$2:$B$388,2,0)/1000,0) -> 0 | AI33: =+IFERROR(VLOOKUP(AI1,'[8]Hoja 1'!$A$2:$B$388,2,0)/1000,0) -> 0 | AJ33: =+IFERROR(VLOOKUP(AJ1,'[8]Hoja 1'!$A$2:$B$388,2,0)/1000,0) -> 0 | AK33: =+AG33+SUM(AH33:AJ33) -> 450.45
A34: % Cumplimiento | B34: =IFERROR(B33/B32,0) -> 0 | C34: =IFERROR(C33/C32,0) -> 0.85 | D34: =IFERROR(D33/D32,0) -> 0.85 | E34: =IFERROR(E33/E32,0) -> 1.1 | F34: =IFERROR(F33/F32,0) -> 0.65 | G34: =IFERROR(G33/G32,0) -> 1.15 | H34: =IFERROR(H33/H32,0) -> 1 | I34: =IFERROR(I33/I32,0) -> 0.94736842 | ... AK34: =IFERROR(AK33/AK32,0) -> 0.28947368
A35: TOTAL PALMA RBD ME | B35: =+B2 -> 355 | C35: =+C2 -> 355 | D35: =+D2 -> 355 | E35: =+E2 -> 355 | F35: =+F3 -> 326.921 | G35: =+G2 -> 355 | H35: =+H2 -> 280 | I35: =+I2 -> 355 | J35: =+J2 -> 2765 | K35: =+K2 -> 355 | L35: =+L2 -> 355 | M35: =+M2 -> 355 | N35: =+N2 -> 355 | ... AK35: =+AK2 -> 10450
A36: TOTAL PALMA RBD Real | B36: =+B3 -> 362.466 | C36: =+C3 -> 362.466 | D36: =+D3 -> 259.688 | E36: =+E3 -> 352.783 | F36: =+F3 -> 326.921 | G36: =+G3 -> 353.606 | H36: =+H3 -> 354 | I36: =+I3 -> 341.32 | ... AK36: =+AK3 -> 2713.25
A37: % Cumplimiento | B37: =IFERROR(+B36/B35,0) -> 1.021031 | C37: =IFERROR(+C36/C35,0) -> 1.021031 | D37: =IFERROR(+D36/D35,0) -> 0.73151549 | E37: =IFERROR(+E36/E35,0) -> 0.99375493 | F37: =IFERROR(+F36/F35,0) -> 1 | G37: =IFERROR(+G36/G35,0) -> 0.99607324 | H37: =IFERROR(+H36/H35,0) -> 1.2642857 | I37: =IFERROR(+I36/I35,0) -> 0.96146479 | ... AK37: =IFERROR(+AK36/AK35,0) -> 0.25964115
A38: TOTAL PALMISTE RBD ME | B38: =+B10 -> 30 | C38: =+C10 -> 0 | D38: =+D10 -> 35 | E38: =+E10 -> 35 | F38: =+F10 -> 35 | G38: =+G10 -> 35 | H38: =+H10 -> 0 | I38: =+I10 -> 35 | ... AK38: =+AK10 -> 898
A39: TOTAL PALMISTE RBD Real | B39: =+B11 -> 30.13 | C39: =+C11 -> 30.13 | D39: =+D11 -> 31.052 | E39: =+E11 -> 29.081 | F39: =+F11 -> 40.847 | G39: =+G11 -> 23.287 | H39: =+H11 -> 21 | I39: =+I11 -> 30.346 | ... AK39: =+AK11 -> 235.873
A40: % Cumplimiento | B40: =IFERROR(+B39/B38,0) -> 1.0043333 | C40: =IFERROR(+C39/C38,0) -> 0 | D40: =IFERROR(+D39/D38,0) -> 0.8872 | E40: =IFERROR(+E39/E38,0) -> 0.83088571 | F40: =IFERROR(+F39/F38,0) -> 1.1670571 | G40: =IFERROR(+G39/G38,0) -> 0.66534286 | H40: =IFERROR(+H39/H38,0) -> 0 | I40: =IFERROR(+I39/I38,0) -> 0.86702857 | ... AA40: =IFERROR(+AA39/AA38,0) -> 0 | AB40: =IFERROR(AB39/AB38,0) -> 0 | AC40: =IFERROR(+AC39/AC38,0) -> 0 | AD40: =IFERROR(+AD39/AD38,0) -> 0 | AE40: =IFERROR(+AE39/AE38,0) -> 0 | AF40: =IFERROR(+AF39/AF38,0) -> 0 | AG40: =IFERROR(+AG39/AG38,0) -> 0.28487077 | AH40: =IFERROR(+AH39/AH38,0) -> 0 | AI40: =IFERROR(+AI39/AI38,0) -> 0 | AJ40: =IFERROR(+AJ39/AJ38,0) -> 0 | AK40: =IFERROR(+AK39/AK38,0) -> 0.26266481
A41: TOTAL OLEINA ME | B41: =+B19+B25 -> 209 | C41: =+C19+C25 -> 209 | D41: =+D19+D25 -> 209 | E41: =+E19+E25 -> 209 | F41: =+F19+F25 -> 209 | G41: =+G19+G25 -> 209 | H41: =+H19+H25 -> 209 | I41: =+I19+I25 -> 209 | ... AK41: =+AK19+AK25 -> 6370
A42: TOTAL OLEINA Real | B42: =+B20+B26 -> 209.88 | C42: =+C20+C26 -> 209.88 | D42: =+D20+D26 -> 180.88 | E42: =+E20+E26 -> 210.22 | F42: =+F20+F26 -> 196.92 | G42: =+G20+G26 -> 204.44 | H42: =+H20+H26 -> 189.26 | I42: =+I20+I26 -> 205.135 | ... AK42: =+AK20+AK26 -> 1606.615
A43: % Cumplimiento | B43: =IFERROR(+B42/B41,0) -> 1.0042105 | C43: =IFERROR(+C42/C41,0) -> 1.0042105 | D43: =IFERROR(+D42/D41,0) -> 0.86545455 | E43: =IFERROR(+E42/E41,0) -> 1.0058373 | F43: =IFERROR(+F42/F41,0) -> 0.94220096 | G43: =IFERROR(+G42/G41,0) -> 0.97818182 | H43: =IFERROR(+H42/H41,0) -> 0.90555024 | I43: =IFERROR(+I42/I41,0) -> 0.98150718 | ... AK43: =IFERROR(+AK42/AK41,0) -> 0.25221586
A44: TOTAL MARGARINAS ME | B44: =+B32 -> 63 | C44: =+C32 -> 63 | D44: =+D32 -> 63 | E44: =+E32 -> 63 | F44: =+F32 -> 63 | G44: =+G32 -> 63 | H44: =+H32 -> 63 | I44: =+I32 -> 59.85 | ... AK44: =+AK32 -> 1556.1
A45: TOTAL MARGARINAS Real | B45: =+B33 -> 0 | C45: =+C33 -> 53.55 | D45: =+D33 -> 53.55 | E45: =+E33 -> 69.3 | F45: =+F33 -> 40.95 | G45: =+G33 -> 72.45 | H45: =+H33 -> 63 | I45: =+I33 -> 56.7 | ... AK45: =+AK33 -> 450.45
A46: % Cumplimiento | B46: =IFERROR(+B45/B44,0) -> 0 | C46: =IFERROR(+C45/C44,0) -> 0.85 | D46: =IFERROR(+D45/D44,0) -> 0.85 | E46: =IFERROR(+E45/E44,0) -> 1.1 | F46: =IFERROR(+F45/F44,0) -> 0.65 | G46: =IFERROR(+G45/G44,0) -> 1.15 | H46: =IFERROR(+H45/H44,0) -> 1 | I46: =IFERROR(+I45/I44,0) -> 0.94736842 | ... AK46: =IFERROR(+AK45/AK44,0) -> 0.28947368
H47: PLANTA | I47: ME | J47: REAL | K47: % CUMPL | L47: DIF TM | Q47: PLANTA | R47: ME | S47: REAL | T47: % CUMPL | U47: DIF TM | X47: PLANTA | Y47: ME | Z47: REAL | AA47: % CUMPL | AB47: DIF TM | AF47: PLANTA | AG47: ME | AH47: REAL | AI47: % CUMPL | AJ47: DIF TM | AL47: PLANTA | AM47: ME | AN47: REAL | AO47: % CUMPL | AP47: DIF TM | AS47: PLANTA | AT47: ME | AU47: REAL | AV47: % CUMPL | AW47: DIF TM
H48: REFINERIA 1 | I48: =+J35 -> 2765 | J48: =+J36 -> 2713.25 | K48: =IFERROR(J48/I48,0) -> 0.98128391 | L48: =+J48-I48 -> -51.75 | Q48: REFINERIA 1 | R48: =+Q35 -> 4820 | S48: =+Q36 -> 2713.25 | T48: =IFERROR(S48/R48,0) -> 0.56291494 | U48: =+S48-R48 -> -2106.75 | X48: REFINERIA 1 | Y48: =+Y35 -> 7230 | Z48: =+Y36 -> 2713.25 | AA48: =IFERROR(Z48/Y48,0) -> 0.37527663 | AB48: =+Z48-Y48 -> -4516.75 | AF48: REFINERIA 1 | AG48: =+AG35 -> 9640 | AH48: =+AG36 -> 2713.25 | AI48: =IFERROR(AH48/AG48,0) -> 0.28145747 | AJ48: =+AH48-AG48 -> -6926.75 | AL48: REFINERIA 1 | AM48: =+AK35 -> 10450 | AN48: =+AK36 -> 2713.25 | AO48: =IFERROR(AN48/AM48,0) -> 0.25964115 | AP48: =+AN48-AM48 -> -7736.75 | AS48: REFINERIA 1 | AT48: =+AK35 -> 10450 | AU48: =+AK36 -> 2713.25 | AV48: =IFERROR(AU48/AT48,0) -> 0.25964115 | AW48: =+AU48-AT48 -> -7736.75
H49: REFINERIA 2 | I49: =+J38 -> 205 | J49: =+J39 -> 235.873 | K49: =IFERROR(J49/I49,0) -> 1.1506 | L49: =+J49-I49 -> 30.873 | Q49: REFINERIA 2 | R49: =+Q38 -> 405 | S49: =+Q39 -> 235.873 | T49: =IFERROR(S49/R49,0) -> 0.58240247 | U49: =+S49-R49 -> -169.127 | X49: REFINERIA 2 | Y49: =+Y38 -> 618 | Z49: =+Y39 -> 235.873 | AA49: =IFERROR(Z49/Y49,0) -> 0.38167152 | AB49: =+Z49-Y49 -> -382.127 | AF49: REFINERIA 2 | AG49: =+AG38 -> 828 | AH49: =+AG39 -> 235.873 | AI49: =IFERROR(AH49/AG49,0) -> 0.28487077 | AJ49: =+AH49-AG49 -> -592.127 | AL49: REFINERIA 2 | AM49: =+AK38 -> 898 | AN49: =+AK39 -> 235.873 | AO49: =IFERROR(AN49/AM49,0) -> 0.26266481 | AP49: =+AN49-AM49 -> -662.127 | AS49: REFINERIA 2 | AT49: =+AK38 -> 898 | AU49: =+AK39 -> 235.873 | AV49: =IFERROR(AU49/AT49,0) -> 0.26266481 | AW49: =+AU49-AT49 -> -662.127
H50: OLEINA | I50: =+J41 -> 1672 | J50: =+J42 -> 1606.615 | K50: =IFERROR(J50/I50,0) -> 0.96089414 | L50: =+J50-I50 -> -65.385 | Q50: OLEINA | R50: =+Q41 -> 2926 | S50: =+Q42 -> 1606.615 | T50: =IFERROR(S50/R50,0) -> 0.54908237 | U50: =+S50-R50 -> -1319.385 | X50: OLEINA | Y50: =+Y41 -> 4389 | Z50: =+Y42 -> 1606.615 | AA50: =IFERROR(Z50/Y50,0) -> 0.36605491 | AB50: =+Z50-Y50 -> -2782.385 | AF50: OLEINA | AG50: =+AG41 -> 5852 | AH50: =+AG42 -> 1606.615 | AI50: =IFERROR(AH50/AG50,0) -> 0.27454118 | AJ50: =+AH50-AG50 -> -4245.385 | AL50: OLEINA | AM50: =+AK41 -> 6370 | AN50: =+AK42 -> 1606.615 | AO50: =IFERROR(AN50/AM50,0) -> 0.25221586 | AP50: =+AN50-AM50 -> -4763.385 | AS50: OLEINA | AT50: =+AK41 -> 6370 | AU50: =+AK42 -> 1606.615 | AV50: =IFERROR(AU50/AT50,0) -> 0.25221586 | AW50: =+AU50-AT50 -> -4763.385
H51: MARGARINAS | I51: =+J44 -> 500.85 | J51: =+J45 -> 409.5 | K51: =IFERROR(J51/I51,0) -> 0.81761006 | L51: =+J51-I51 -> -91.35 | Q51: MARGARINAS | R51: =+Q44 -> 875.7 | S51: =+Q45 -> 450.45 | T51: =IFERROR(S51/R51,0) -> 0.51438849 | U51: =+S51-R51 -> -425.25 | X51: MARGARINAS | Y51: =+Y44 -> 1316.7 | Z51: =+Y45 -> 450.45 | AA51: =IFERROR(Z51/Y51,0) -> 0.34210526 | AB51: =+Z51-Y51 -> -866.25 | AF51: MARGARINAS | AG51: =+AG44 -> 1556.1 | AH51: =+AG45 -> 450.45 | AI51: =IFERROR(AH51/AG51,0) -> 0.28947368 | AJ51: =+AH51-AG51 -> -1105.65 | AL51: MARGARINAS | AM51: =+AK44 -> 1556.1 | AN51: =+AK45 -> 450.45 | AO51: =IFERROR(AN51/AM51,0) -> 0.28947368 | AP51: =+AN51-AM51 -> -1105.65 | AS51: MARGARINAS | AT51: =+AK44 -> 1556.1 | AU51: =+AK45 -> 450.45 | AV51: =IFERROR(AU51/AT51,0) -> 0.28947368 | AW51: =+AU51-AT51 -> -1105.65
H52: TOTAL | I52: =SUM(I48:I51) -> 5142.85 | J52: =SUM(J48:J51) -> 4965.238 | K52: =IFERROR(J52/I52,0) -> 0.96546429 | L52: =+J52-I52 -> -177.612 | Q52: TOTAL | R52: =SUM(R48:R51) -> 9026.7 | S52: =SUM(S48:S51) -> 5006.188 | T52: =IFERROR(S52/R52,0) -> 0.5545978 | U52: =+S52-R52 -> -4020.512 | X52: TOTAL | Y52: =SUM(Y48:Y51) -> 13553.7 | Z52: =SUM(Z48:Z51) -> 5006.188 | AA52: =IFERROR(Z52/Y52,0) -> 0.36935951 | AB52: =+Z52-Y52 -> -8547.512 | AF52: TOTAL | AG52: =SUM(AG48:AG51) -> 17876.1 | AH52: =SUM(AH48:AH51) -> 5006.188 | AI52: =IFERROR(AH52/AG52,0) -> 0.28004923 | AJ52: =+AH52-AG52 -> -12869.912 | AL52: TOTAL | AM52: =SUM(AM48:AM51) -> 19274.1 | AN52: =SUM(AN48:AN51) -> 5006.188 | AO52: =IFERROR(AN52/AM52,0) -> 0.25973654 | AP52: =+AN52-AM52 -> -14267.912 | AS52: TOTAL | AT52: =SUM(AT48:AT51) -> 19274.1 | AU52: =SUM(AU48:AU51) -> 5006.188 | AV52: =IFERROR(AU52/AT52,0) -> 0.25973654 | AW52: =+AU52-AT52 -> -14267.912

Sheet DOWNSTREAM (2)
A1: ZONA | B1: 45689 | C1: =+B1+1 -> 45690 | D1: ACUMULADO S1 | E1: =+C1+1 -> 45691 | F1: =+E1+1 -> 45692 | G1: =+F1+1 -> 45693 | H1: =+G1+1 -> 45694 | I1: =+H1+1 -> 45695 | J1: =+I1+1 -> 45696 | K1: =+J1+1 -> 45697 | L1: ACUMULADO S2 | M1: =+K1+1 -> 45698 | N1: =+M1+1 -> 45699 | O1: =+N1+1 -> 45700 | P1: =+O1+1 -> 45701 | Q1: =+P1+1 -> 45702 | R1: =+Q1+1 -> 45703 | S1: =+R1+1 -> 45704 | T1: ACUMULADO S3 | U1: =+S1+1 -> 45705 | V1: =+U1+1 -> 45706 | W1: =+V1+1 -> 45707 | X1: =+W1+1 -> 45708 | Y1: =+X1+1 -> 45709 | Z1: =+Y1+1 -> 45710 | AA1: =+Z1+1 -> 45711 | AB1: ACUMULADO S4 | AC1: =+AA1+1 -> 45712 | AD1: =+AC1+1 -> 45713 | AE1: =+AD1+1 -> 45714 | AF1: =+AE1+1 -> 45715 | AG1: =+AF1+1 -> 45716 | AH1: Acumulado FEB 25 | BE1: TOTAL
A2: Refinería 1 ME | B2: =+B3 -> 340.249 | C2: =+C3 -> 265.73 | D2: =+SUM(B2:C2) -> 605.979 | E2: =+E3 -> 371.199 | F2: =+F3 -> 311.248 | G2: =+G3 -> 345.552 | H2: =+H3 -> 347.101 | I2: =+I3 -> 331.205 | J2: =+J3 -> 374.989 | K2: =+K3 -> 371.824 | L2: =+D2+SUM(E2:K2) -> 3059.097 | M2: =+M3 -> 356.436 | N2: =+N3 -> 379.614 | O2: =+O3 -> 373.846 | P2: =+P3 -> 358.372 | Q2: =+Q3 -> 368.394 | R2: =+R3 -> 368.394 | S2: =+S3 -> 371.182 | T2: =+L2+SUM(M2:S2) -> 5635.335 | U2: =+U3 -> 340.927 | V2: =+V3 -> 366.377 | W2: 250 | X2: 365 | Y2: 365 | Z2: 365 | AA2: 350 | AB2: =+T2+SUM(U2:AA2) -> 8037.639 | AC2: 365 | AD2: 365 | AE2: 365 | AF2: 365 | AG2: 365 | AH2: =+AB2+SUM(AC2:AG2) -> 9862.639 | BE2: 9790
A3: Refinería 1 Real | B3: 340.249 | C3: 265.73 | D3: =+SUM(B3:C3) -> 605.979 | E3: 371.199 | F3: 311.248 | G3: 345.552 | H3: 347.101 | I3: 331.205 | J3: 374.989 | K3: 371.824 | L3: =+D3+SUM(E3:K3) -> 3059.097 | M3: 356.436 | N3: 379.614 | O3: 373.846 | P3: 358.372 | Q3: 368.394 | R3: 368.394 | S3: 371.182 | T3: =+L3+SUM(M3:S3) -> 5635.335 | U3: 340.927 | V3: 366.377 | W3: 275.672 | X3: =+DOWNSTREAM!W3 -> 0 | Y3: =+DOWNSTREAM!X3 -> 0 | Z3: =+DOWNSTREAM!Z3 -> 0 | AA3: =+DOWNSTREAM!AA3 -> 0 | AB3: =+T3+SUM(U3:AA3) -> 6618.311 | AC3: =+AC2 -> 365 | AD3: =+AD2 -> 365 | AE3: =+AE2 -> 365 | AF3: =+AF2 -> 365 | AG3: =+AG2 -> 365 | AH3: =+AB3+SUM(AC3:AG3) -> 8443.311
A4: % Cumplimiento | B4: =IFERROR(B3/B2,0) -> 1 | C4: =IFERROR(C3/C2,0) -> 1 | D4: =IFERROR(D3/D2,0) -> 1 | E4: =IFERROR(E3/E2,0) -> 1 | F4: =IFERROR(F3/F2,0) -> 1 | G4: =IFERROR(G3/G2,0) -> 1 | H4: =IFERROR(H3/H2,0) -> 1 | I4: =IFERROR(I3/I2,0) -> 1 | ... AH4: =IFERROR(AH3/AH2,0) -> 0.85609044
A5: Rendimiento (94,5%)
A6: Acidez Ingreso
A7: Rojo Recepción
A8: Rojo Saponif
A9: Inventario Inicio
A10: Refinería 2 ME | B10: =+B11 -> 32.222 | C10: =+C11 -> 24.335 | D10: =+SUM(B10:C10) -> 56.557 | E10: =+E11 -> 33.44 | F10: =+F11 -> 33.214 | G10: =+G11 -> 33.459 | H10: =+H11 -> 43.639 | I10: =+I11 -> 21.359 | J10: =+J11 -> 33.855 | K10: =+K11 -> 14.175 | L10: =+D10+SUM(E10:K10) -> 269.698 | M10: =+M11 -> 32.997 | N10: =+N11 -> 21.72 | O10: =+O11 -> 40.732 | P10: =+P11 -> 39.725 | Q10: =+Q11 -> 36.232 | R10: =+R11 -> 36.232 | S10: =+S11 -> 44.209 | T10: =+L10+SUM(M10:S10) -> 521.545 | U10: =+U11 -> 36.284 | V10: =+V11 -> 33.594 | W10: 41 | X10: 41 | Y10: 41 | Z10: 41 | AA10: 41 | AB10: =+T10+SUM(U10:AA10) -> 796.423 | AC10: 41 | AD10: 41 | AE10: 41 | AF10: 41 | AG10: 41 | AH10: =+AB10+SUM(AC10:AG10) -> 1001.423 | BE10: 370
A11: Refineria 2 Real | B11: 32.222 | C11: 24.335 | D11: =+SUM(B11:C11) -> 56.557 | E11: 33.44 | F11: 33.214 | G11: 33.459 | H11: 43.639 | I11: 21.359 | J11: 33.855 | K11: 14.175 | L11: =+D11+SUM(E11:K11) -> 269.698 | M11: 32.997 | N11: 21.72 | O11: 40.732 | P11: 39.725 | Q11: 36.232 | R11: 36.232 | S11: 44.209 | T11: =+L11+SUM(M11:S11) -> 521.545 | U11: 36.284 | V11: 33.594 | W11: 24.873 | X11: =+DOWNSTREAM!W11 -> 0 | Y11: =+DOWNSTREAM!X11 -> 0 | Z11: =+DOWNSTREAM!Z11 -> 0 | AA11: =+DOWNSTREAM!AA11 -> 0 | AB11: =+T11+SUM(U11:AA11) -> 616.296 | AC11: =+AC10 -> 41 | AD11: =+AD10 -> 41 | AE11: =+AE10 -> 41 | AF11: =+AF10 -> 41 | AG11: =+AG10 -> 41 | AH11: =+AB11+SUM(AC11:AG11) -> 821.296
A12: % Cumplimiento | B12: =IFERROR(+B11/B10,0) -> 1 | C12: =IFERROR(+C11/C10,0) -> 1 | D12: =IFERROR(+D11/D10,0) -> 1 | E12: =IFERROR(+E11/E10,0) -> 1 | F12: =IFERROR(+F11/F10,0) -> 1 | G12: =IFERROR(+G11/G10,0) -> 1 | H12: =IFERROR(+H11/H10,0) -> 1 | I12: =IFERROR(+I11/I10,0) -> 1 | ... AH12: =IFERROR(+AH11/AH10,0) -> 0.82012896
A13: Rendimiento (93,5%)
A14: Rojo Recepción
A15: Rojo Saponif
A16: Inventario Inicio
A17: Fracc 1 ME | B17: =+B18 -> 97.9 | C17: =+C18 -> 90 | D17: =+SUM(B17:C17) -> 187.9 | E17: =+E18 -> 96.17 | F17: =+F18 -> 88.5 | G17: =+G18 -> 88.365 | H17: =+H18 -> 96.44 | I17: =+I18 -> 75.83 | J17: =+J18 -> 100.66 | K17: =+K18 -> 90.39 | L17: =+D17+SUM(E17:K17) -> 824.255 | M17: =+M18 -> 91.11 | N17: =+N18 -> 96.25 | O17: =+O18 -> 35.8 | P17: =+P18 -> 57 | Q17: =+Q18 -> 49.9 | R17: =+R18 -> 49.9 | S17: =+S18 -> 63.46 | T17: =+L17+SUM(M17:S17) -> 1267.675 | U17: =+U18 -> 94.67 | V17: =+V18 -> 28.63 | W17: 90 | X17: 90 | Y17: 90 | Z17: 90 | AA17: - | AB17: =+T17+SUM(U17:AA17) -> 1750.975 | AC17: 90 | AD17: 90 | AE17: 90 | AF17: 90 | AG17: 90 | AH17: =+AB17+SUM(AC17:AG17) -> 2200.975 | BE17: 3578.9474
A18: Fracc 1 Real | B18: 97.9 | C18: 90 | D18: =+SUM(B18:C18) -> 187.9 | E18: 96.17 | F18: 88.5 | G18: 88.365 | H18: 96.44 | I18: 75.83 | J18: 100.66 | K18: 90.39 | L18: =+D18+SUM(E18:K18) -> 824.255 | M18: 91.11 | N18: 96.25 | O18: 35.8 | P18: 57 | Q18: 49.9 | R18: 49.9 | S18: 63.46 | T18: =+L18+SUM(M18:S18) -> 1267.675 | U18: 94.67 | V18: 28.63 | W18: 87.7 | X18: =+DOWNSTREAM!W20 -> 0 | Y18: =+DOWNSTREAM!X20 -> 0 | Z18: =+DOWNSTREAM!Z20 -> 0 | AA18: =+DOWNSTREAM!AA20 -> 0 | AB18: =+T18+SUM(U18:AA18) -> 1478.675 | AC18: =+AC17 -> 90 | AD18: =+AD17 -> 90 | AE18: =+AE17 -> 90 | AF18: =+AF17 -> 90 | AG18: =+AG17 -> 90 | AH18: =+AB18+SUM(AC18:AG18) -> 1928.675
A19: % Cumplimiento | B19: =IFERROR(+B18/B17,0) -> 1 | C19: =IFERROR(+C18/C17,0) -> 1 | D19: =IFERROR(+D18/D17,0) -> 1 | E19: =IFERROR(+E18/E17,0) -> 1 | F19: =IFERROR(+F18/F17,0) -> 1 | G19: =IFERROR(+G18/G17,0) -> 1 | H19: =IFERROR(+H18/H17,0) -> 1 | I19: =IFERROR(+I18/I17,0) -> 1 | ... AH19: =IFERROR(+AH18/AH17,0) -> 0.8762821
A20: Rendimiento (75,2%)
A21: Rojo Recepción
A22: Rojo Saponif
A23: Fracc 2 ME | B23: =+B24 -> 131.07 | C23: =+C24 -> 130.51 | D23: =+SUM(B23:C23) -> 261.58 | E23: =+E24 -> 134.739 | F23: =+F24 -> 130.27 | G23: =+G24 -> 130.35 | H23: =+H24 -> 130.77 | I23: =+I24 -> 130.6 | J23: =+J24 -> 139.86 | K23: =+K24 -> 130.05 | L23: =+D23+SUM(E23:K23) -> 1188.219 | M23: =+M24 -> 129.34 | N23: =+N24 -> 132.6 | O23: =+O24 -> 85.62 | P23: =+P24 -> 100.524 | Q23: =+Q24 -> 90.287 | R23: =+R24 -> 90.287 | S23: =+S24 -> 102.544 | T23: =+L23+SUM(M23:S23) -> 1919.421 | U23: =+U24 -> 135.43 | V23: =+V24 -> 87.23 | W23: 120 | X23: 120 | Y23: 120 | Z23: 120 | AA23: 100 | AB23: =+T23+SUM(U23:AA23) -> 2722.081 | AC23: 120 | AD23: 120 | AE23: 120 | AF23: 120 | AG23: 120 | AH23: =+AB23+SUM(AC23:AG23) -> 3322.081 | BE23: 4636.3636
A24: Fracc 2 Real | B24: 131.07 | C24: 130.51 | D24: =+SUM(B24:C24) -> 261.58 | E24: 134.739 | F24: 130.27 | G24: 130.35 | H24: 130.77 | I24: 130.6 | J24: 139.86 | K24: 130.05 | L24: =+D24+SUM(E24:K24) -> 1188.219 | M24: 129.34 | N24: 132.6 | O24: 85.62 | P24: 100.524 | Q24: 90.287 | R24: 90.287 | S24: 102.544 | T24: =+L24+SUM(M24:S24) -> 1919.421 | U24: 135.43 | V24: 87.23 | W24: 112.59 | X24: =+DOWNSTREAM!W26 -> 0 | Y24: =+DOWNSTREAM!X26 -> 0 | Z24: =+DOWNSTREAM!Z26 -> 0 | AA24: =+DOWNSTREAM!AA26 -> 0 | AB24: =+T24+SUM(U24:AA24) -> 2254.671 | AC24: =+AC23 -> 120 | AD24: =+AD23 -> 120 | AE24: =+AE23 -> 120 | AF24: =+AF23 -> 120 | AG24: =+AG23 -> 120 | AH24: =+AB24+SUM(AC24:AG24) -> 2854.671
A25: % Cumplimiento | B25: =IFERROR(+B24/B23,0) -> 1 | C25: =IFERROR(+C24/C23,0) -> 1 | D25: =IFERROR(+D24/D23,0) -> 1 | E25: =IFERROR(+E24/E23,0) -> 1 | F25: =IFERROR(+F24/F23,0) -> 1 | G25: =IFERROR(+G24/G23,0) -> 1 | H25: =IFERROR(+H24/H23,0) -> 1 | I25: =IFERROR(+I24/I23,0) -> 1 | ... AH25: =IFERROR(+AH24/AH23,0) -> 0.85930205
A26: Rendimiento (77,3%)
A27: Cold Test
A28: Rojo
A29: Inventario Inicio
A30: Margarinas ME | B30: =+HLOOKUP(B$1,'[7]Programa Diario CODAZZI'!$F$8:$AL$44,37,0)/1000 -> #N/A | C30: =+HLOOKUP(C$1,'[7]Programa Diario CODAZZI'!$F$8:$AL$44,37,0)/1000 -> #N/A | D30: =+SUM(B30:C30) -> #N/A | E30: =+HLOOKUP(E$1,'[7]Programa Diario CODAZZI'!$F$8:$AL$44,37,0)/1000 -> #N/A | F30: =+HLOOKUP(F$1,'[7]Programa Diario CODAZZI'!$F$8:$AL$44,37,0)/1000 -> #N/A | G30: =+HLOOKUP(G$1,'[7]Programa Diario CODAZZI'!$F$8:$AL$44,37,0)/1000 -> #N/A | H30: =+HLOOKUP(H$1,'[7]Programa Diario CODAZZI'!$F$8:$AL$44,37,0)/1000 -> #N/A | I30: =+HLOOKUP(I$1,'[7]Programa Diario CODAZZI'!$F$8:$AL$44,37,0)/1000 -> #N/A | J30: =+HLOOKUP(J$1,'[7]Programa Diario CODAZZI'!$F$8:$AL$44,37,0)/1000 -> #N/A | K30: =+HLOOKUP(K$1,'[7]Programa Diario CODAZZI'!$F$8:$AL$44,37,0)/1000 -> #N/A | L30: =+D30+SUM(E30:K30) -> #N/A | M30: =+HLOOKUP(M$1,'[7]Programa Diario CODAZZI'!$F$8:$AL$44,37,0)/1000 -> #N/A | N30: =+HLOOKUP(N$1,'[7]Programa Diario CODAZZI'!$F$8:$AL$44,37,0)/1000 -> #N/A | O30: =+HLOOKUP(O$1,'[7]Programa Diario CODAZZI'!$F$8:$AL$44,37,0)/1000 -> #N/A | P30: =+HLOOKUP(P$1,'[7]Programa Diario CODAZZI'!$F$8:$AL$44,37,0)/1000 -> #N/A | Q30: =+HLOOKUP(Q$1,'[7]Programa Diario CODAZZI'!$F$8:$AL$44,37,0)/1000 -> #N/A | R30: =+HLOOKUP(R$1,'[7]Programa Diario CODAZZI'!$F$8:$AL$44,37,0)/1000 -> #N/A | S30: =+HLOOKUP(S$1,'[7]Programa Diario CODAZZI'!$F$8:$AL$44,37,0)/1000 -> #N/A | T30: =+L30+SUM(M30:S30) -> #N/A | U30: =+HLOOKUP(U$1,'[7]Programa Diario CODAZZI'!$F$8:$AL$44,37,0)/1000 -> #N/A | V30: 63 | W30: 63 | X30: 63 | Y30: 63 | Z30: 63 | AA30: 59.85 | AB30: =+T30+SUM(U30:AA30) -> #N/A | AC30: 59.85 | AD30: 63 | AE30: 63 | AF30: 56.7 | AG30: 0 | AH30: =+AB30+SUM(AC30:AG30) -> #N/A | BE30: 645
A31: Margarinas Real | B31: 22.05 | C31: 72.45 | D31: =+SUM(B31:C31) -> 94.5 | E31: 72.45 | F31: 44.1 | G31: 63 | H31: 12.48 | I31: 50.52 | J31: 53.52 | K31: 0 | L31: =+D31+SUM(E31:K31) -> 390.57 | M31: 28.35 | N31: 66.15 | O31: 66.15 | P31: 66.15 | Q31: 69.3 | R31: 50.4 | S31: 15.75 | T31: =+L31+SUM(M31:S31) -> 752.82 | U31: 47.25 | V31: 63 | W31: 63 | X31: =+DOWNSTREAM!W33 -> 0 | Y31: =+DOWNSTREAM!X33 -> 0 | Z31: =+DOWNSTREAM!Z33 -> 0 | AA31: =+DOWNSTREAM!AA33 -> 0 | AB31: =+T31+SUM(U31:AA31) -> 926.07 | AC31: 59.85 | AD31: 63 | AE31: 63 | AF31: 56.7 | AG31: 0 | AH31: =+AB31+SUM(AC31:AG31) -> 1168.62
A32: % Cumplimiento | B32: =IFERROR(B31/B30,0) -> 0 | C32: =IFERROR(C31/C30,0) -> 0 | D32: =IFERROR(D31/D30,0) -> 0 | E32: =IFERROR(E31/E30,0) -> 0 | F32: =IFERROR(F31/F30,0) -> 0 | G32: =IFERROR(G31/G30,0) -> 0 | H32: =IFERROR(H31/H30,0) -> 0 | I32: =IFERROR(I31/I30,0) -> 0 | ... AH32: =IFERROR(AH31/AH30,0) -> 0
A33: TOTAL PALMA RBD ME | B33: =+B2 -> 340.249 | C33: =+C2 -> 265.73 | D33: =+D2 -> 605.979 | E33: =+E2 -> 371.199 | F33: =+F2 -> 311.248 | G33: =+G3 -> 345.552 | H33: =+H2 -> 347.101 | I33: =+I2 -> 331.205 | J33: =+J2 -> 374.989 | K33: =+K2 -> 371.824 | L33: =+L2 -> 3059.097 | M33: =+M2 -> 356.436 | N33: =+N2 -> 379.614 | O33: =+O2 -> 373.846 | ... AH33: =+AH2 -> 9862.639
A34: TOTAL PALMA RBD Real | B34: =+B3 -> 340.249 | C34: =+C3 -> 265.73 | D34: =+D3 -> 605.979 | E34: =+E3 -> 371.199 | F34: =+F3 -> 311.248 | G34: =+G3 -> 345.552 | H34: =+H3 -> 347.101 | I34: =+I3 -> 331.205 | ... AH34: =+AH3 -> 8443.311
A35: % Cumplimiento | B35: =IFERROR(+B34/B33,0) -> 1 | C35: =IFERROR(+C34/C33,0) -> 1 | D35: =IFERROR(+D34/D33,0) -> 1 | E35: =IFERROR(+E34/E33,0) -> 1 | F35: =IFERROR(+F34/F33,0) -> 1 | G35: =IFERROR(+G34/G33,0) -> 1 | H35: =IFERROR(+H34/H33,0) -> 1 | I35: =IFERROR(+I34/I33,0) -> 1 | ... AH35: =IFERROR(+AH34/AH33,0) -> 0.85609044
A36: TOTAL PALMISTE RBD ME | B36: =+B10 -> 32.222 | C36: =+C10 -> 24.335 | D36: =+D10 -> 56.557 | E36: =+E10 -> 33.44 | F36: =+F10 -> 33.214 | G36: =+G10 -> 33.459 | H36: =+H10 -> 43.639 | I36: =+I10 -> 21.359 | ... AH36: =+AH10 -> 1001.423
A37: TOTAL PALMISTE RBD Real | B37: =+B11 -> 32.222 | C37: =+C11 -> 24.335 | D37: =+D11 -> 56.557 | E37: =+E11 -> 33.44 | F37: =+F11 -> 33.214 | G37: =+G11 -> 33.459 | H37: =+H11 -> 43.639 | I37: =+I11 -> 21.359 | ... AH37: =+AH11 -> 821.296
A38: % Cumplimiento | B38: =IFERROR(+B37/B36,0) -> 1 | C38: =IFERROR(+C37/C36,0) -> 1 | D38: =IFERROR(+D37/D36,0) -> 1 | E38: =IFERROR(+E37/E36,0) -> 1 | F38: =IFERROR(+F37/F36,0) -> 1 | G38: =IFERROR(+G37/G36,0) -> 1 | H38: =IFERROR(+H37/H36,0) -> 1 | I38: =IFERROR(+I37/I36,0) -> 1 | ... AH38: =IFERROR(+AH37/AH36,0) -> 0.82012896
A39: TOTAL OLEINA ME | B39: =+B17+B23 -> 228.97 | C39: =+C17+C23 -> 220.51 | D39: =+D17+D23 -> 449.48 | E39: =+E17+E23 -> 230.909 | F39: =+F17+F23 -> 218.77 | G39: =+G17+G23 -> 218.715 | H39: =+H17+H23 -> 227.21 | I39: =+I17+I23 -> 206.43 | ... AH39: =+AH17+AH23 -> 5523.056
A40: TOTAL OLEINA Real | B40: =+B18+B24 -> 228.97 | C40: =+C18+C24 -> 220.51 | D40: =+D18+D24 -> 449.48 | E40: =+E18+E24 -> 230.909 | F40: =+F18+F24 -> 218.77 | G40: =+G18+G24 -> 218.715 | H40: =+H18+H24 -> 227.21 | I40: =+I18+I24 -> 206.43 | ... AH40: =+AH18+AH24 -> 4783.346
A41: % Cumplimiento | B41: =IFERROR(+B40/B39,0) -> 1 | C41: =IFERROR(+C40/C39,0) -> 1 | D41: =IFERROR(+D40/D39,0) -> 1 | E41: =IFERROR(+E40/E39,0) -> 1 | F41: =IFERROR(+F40/F39,0) -> 1 | G41: =IFERROR(+G40/G39,0) -> 1 | H41: =IFERROR(+H40/H39,0) -> 1 | I41: =IFERROR(+I40/I39,0) -> 1 | ... AH41: =IFERROR(+AH40/AH39,0) -> 0.86606871
A42: TOTAL MARGARINAS ME | B42: =+B30 -> #N/A | C42: =+C30 -> #N/A | D42: =+D30 -> #N/A | E42: =+E30 -> #N/A | F42: =+F30 -> #N/A | G42: =+G30 -> #N/A | H42: =+H30 -> #N/A | I42: =+I30 -> #N/A | ... AH42: =+AH30 -> #N/A
A43: TOTAL MARGARINAS Real | B43: =+B31 -> 22.05 | C43: =+C31 -> 72.45 | D43: =+D31 -> 94.5 | E43: =+E31 -> 72.45 | F43: =+F31 -> 44.1 | G43: =+G31 -> 63 | H43: =+H31 -> 12.48 | I43: =+I31 -> 50.52 | ... AH43: =+AH31 -> 1168.62
A44: % Cumplimiento | B44: =IFERROR(+B43/B42,0) -> 0 | C44: =IFERROR(+C43/C42,0) -> 0 | D44: =IFERROR(+D43/D42,0) -> 0 | E44: =IFERROR(+E43/E42,0) -> 0 | F44: =IFERROR(+F43/F42,0) -> 0 | G44: =IFERROR(+G43/G42,0) -> 0 | H44: =IFERROR(+H43/H42,0) -> 0 | I44: =IFERROR(+I43/I42,0) -> 0 | ... AH44: =IFERROR(+AH43/AH42,0) -> 0
B45: PLANTA | C45: ME | D45: REAL | E45: % CUMPL | F45: DIF TM | J45: PLANTA | K45: ME | L45: REAL | M45: % CUMPL | N45: DIF TM | R45: PLANTA | S45: ME | T45: REAL | U45: % CUMPL | V45: DIF TM | Z45: PLANTA | AA45: ME | AB45: REAL | AC45: % CUMPL | AD45: DIF TM | AF45: PLANTA | AG45: ME | AH45: REAL | AI45: % CUMPL | AJ45: DIF TM | BJ45: PLANTA | BK45: ME | BL45: REAL | BM45: % CUMPL | BN45: DIF TM
B46: REFINERIA 1 | C46: =+D33 -> 605.979 | D46: =+D34 -> 605.979 | E46: =IFERROR(D46/C46,0) -> 1 | F46: =+D46-C46 -> 0 | J46: REFINERIA 1 | K46: =+L33 -> 3059.097 | L46: =+L34 -> 3059.097 | M46: =IFERROR(L46/K46,0) -> 1 | N46: =+L46-K46 -> 0 | R46: REFINERIA 1 | S46: =+T33 -> 5635.335 | T46: =+T34 -> 5635.335 | U46: =IFERROR(T46/S46,0) -> 1 | V46: =+T46-S46 -> 0 | Z46: REFINERIA 1 | AA46: =+AB33 -> 8037.639 | AB46: =+AB34 -> 6618.311 | AC46: =IFERROR(AB46/AA46,0) -> 0.82341481 | AD46: =+AB46-AA46 -> -1419.328 | AF46: REFINERIA 1 | AG46: =+AH33 -> 9862.639 | AH46: =+AH34 -> 8443.311 | AI46: =IFERROR(AH46/AG46,0) -> 0.85609044 | AJ46: =+AH46-AG46 -> -1419.328 | BJ46: REFINERIA 1 | BK46: =+AH33 -> 9862.639 | BL46: =+AH34 -> 8443.311 | BM46: =IFERROR(BL46/BK46,0) -> 0.85609044 | BN46: =+BL46-BK46 -> -1419.328
B47: REFINERIA 2 | C47: =+D36 -> 56.557 | D47: =+D37 -> 56.557 | E47: =IFERROR(D47/C47,0) -> 1 | F47: =+D47-C47 -> 0 | J47: REFINERIA 2 | K47: =+L36 -> 269.698 | L47: =+L37 -> 269.698 | M47: =IFERROR(L47/K47,0) -> 1 | N47: =+L47-K47 -> 0 | R47: REFINERIA 2 | S47: =+T36 -> 521.545 | T47: =+T37 -> 521.545 | U47: =IFERROR(T47/S47,0) -> 1 | V47: =+T47-S47 -> 0 | Z47: REFINERIA 2 | AA47: =+AB36 -> 796.423 | AB47: =+AB37 -> 616.296 | AC47: =IFERROR(AB47/AA47,0) -> 0.77382999 | AD47: =+AB47-AA47 -> -180.127 | AF47: REFINERIA 2 | AG47: =+AH36 -> 1001.423 | AH47: =+AH37 -> 821.296 | AI47: =IFERROR(AH47/AG47,0) -> 0.82012896 | AJ47: =+AH47-AG47 -> -180.127 | BJ47: REFINERIA 2 | BK47: =+AH36 -> 1001.423 | BL47: =+AH37 -> 821.296 | BM47: =IFERROR(BL47/BK47,0) -> 0.82012896 | BN47: =+BL47-BK47 -> -180.127
B48: OLEINA | C48: =+D39 -> 449.48 | D48: =+D40 -> 449.48 | E48: =IFERROR(D48/C48,0) -> 1 | F48: =+D48-C48 -> 0 | J48: OLEINA | K48: =+L39 -> 2012.474 | L48: =+L40 -> 2012.474 | M48: =IFERROR(L48/K48,0) -> 1 | N48: =+L48-K48 -> 0 | R48: OLEINA | S48: =+T39 -> 3187.096 | T48: =+T40 -> 3187.096 | U48: =IFERROR(T48/S48,0) -> 1 | V48: =+T48-S48 -> 0 | Z48: OLEINA | AA48: =+AB39 -> 4473.056 | AB48: =+AB40 -> 3733.346 | AC48: =IFERROR(AB48/AA48,0) -> 0.83462984 | AD48: =+AB48-AA48 -> -739.71 | AF48: OLEINA | AG48: =+AH39 -> 5523.056 | AH48: =+AH40 -> 4783.346 | AI48: =IFERROR(AH48/AG48,0) -> 0.86606871 | AJ48: =+AH48-AG48 -> -739.71 | BJ48: OLEINA | BK48: =+AH39 -> 5523.056 | BL48: =+AH40 -> 4783.346 | BM48: =IFERROR(BL48/BK48,0) -> 0.86606871 | BN48: =+BL48-BK48 -> -739.71
B49: MARGARINAS | C49: =+D42 -> #N/A | D49: =+D43 -> 94.5 | E49: =IFERROR(D49/C49,0) -> 0 | F49: =+D49-C49 -> #N/A | J49: MARGARINAS | K49: =+L42 -> #N/A | L49: =+L43 -> 390.57 | M49: =IFERROR(L49/K49,0) -> 0 | N49: =+L49-K49 -> #N/A | R49: MARGARINAS | S49: =+T42 -> #N/A | T49: =+T43 -> 752.82 | U49: =IFERROR(T49/S49,0) -> 0 | V49: =+T49-S49 -> #N/A | Z49: MARGARINAS | AA49: =+AB42 -> #N/A | AB49: =+AB43 -> 926.07 | AC49: =IFERROR(AB49/AA49,0) -> 0 | AD49: =+AB49-AA49 -> #N/A | AF49: MARGARINAS | AG49: =+AH42 -> #N/A | AH49: =+AH43 -> 1168.62 | AI49: =IFERROR(AH49/AG49,0) -> 0 | AJ49: =+AH49-AG49 -> #N/A | BJ49: MARGARINAS | BK49: =+AH42 -> #N/A | BL49: =+AH43 -> 1168.62 | BM49: =IFERROR(BL49/BK49,0) -> 0 | BN49: =+BL49-BK49 -> #N/A
B50: TOTAL | C50: =SUM(C46:C49) -> #N/A | D50: =SUM(D46:D49) -> 1206.516 | E50: =IFERROR(D50/C50,0) -> 0 | F50: =+D50-C50 -> #N/A | J50: TOTAL | K50: =SUM(K46:K49) -> #N/A | L50: =SUM(L46:L49) -> 5731.839 | M50: =IFERROR(L50/K50,0) -> 0 | N50: =+L50-K50 -> #N/A | R50: TOTAL | S50: =SUM(S46:S49) -> #N/A | T50: =SUM(T46:T49) -> 10096.796 | U50: =IFERROR(T50/S50,0) -> 0 | V50: =+T50-S50 -> #N/A | Z50: TOTAL | AA50: =SUM(AA46:AA49) -> #N/A | AB50: =SUM(AB46:AB49) -> 11894.023 | AC50: =IFERROR(AB50/AA50,0) -> 0 | AD50: =+AB50-AA50 -> #N/A | AF50: TOTAL | AG50: =SUM(AG46:AG49) -> #N/A | AH50: =SUM(AH46:AH49) -> 15216.573 | AI50: =IFERROR(AH50/AG50,0) -> 0 | AJ50: =+AH50-AG50 -> #N/A | BJ50: TOTAL | BK50: =SUM(BK46:BK49) -> #N/A | BL50: =SUM(BL46:BL49) -> 15216.573 | BM50: =IFERROR(BL50/BK50,0) -> 0 | BN50: =+BL50-BK50 -> #N/A
V51: =+R51-Q51 -> 0
V52: =+R52-Q52 -> 0
V53: =+R53-Q53 -> 0
V54: =+R54-Q54 -> 0
V55: =+R55-Q55 -> 0
V56: =+R56-Q56 -> 0
V57: =+R57-Q57 -> 0
V58: =+R58-Q58 -> 0
V59: =+R59-Q59 -> 0
V60: =+R60-Q60 -> 0
Q61: =+SUM(Q52:Q58) -> 0 | R61: =+SUM(R52:R58) -> 0 | V61: =+R61-Q61 -> 0

Sheet DOWNSTREAM mod
A1: ZONA | B1: 45717 | C1: =+B1+1 -> 45718 | D1: ACUMULADO S1 | E1: =+C1+1 -> 45719 | F1: =+E1+1 -> 45720 | G1: =+F1+1 -> 45721 | H1: =+G1+1 -> 45722 | I1: =+H1+1 -> 45723 | J1: =+I1+1 -> 45724 | K1: =+J1+1 -> 45725 | L1: ACUMULADO S2 | M1: =+K1+1 -> 45726 | N1: =+M1+1 -> 45727 | O1: =+N1+1 -> 45728 | P1: =+O1+1 -> 45729 | Q1: =+P1+1 -> 45730 | R1: =+Q1+1 -> 45731 | S1: =+R1+1 -> 45732 | T1: ACUMULADO S3 | U1: =+S1+1 -> 45733 | V1: =+U1+1 -> 45734 | W1: =+V1+1 -> 45735 | X1: =+W1+1 -> 45736 | Y1: =+X1+1 -> 45737 | Z1: =+Y1+1 -> 45738 | AA1: =+Z1+1 -> 45739 | AB1: =+AA1+1 -> 45740 | AC1: ACUMULADO S4 | AD1: =+AB1+1 -> 45741 | AE1: =+AD1+1 -> 45742 | AF1: =+AE1+1 -> 45743 | AG1: =+AF1+1 -> 45744 | AH1: =+AG1+1 -> 45745 | AI1: =+AH1+1 -> 45746 | AJ1: Acumulado ABR 25 | BG1: TOTAL
A2: Refinería 1 ME | B2: 346.75809 | C2: 346.75809 | D2: =+SUM(B2:C2) -> 693.51618 | E2: 346.75809 | F2: 346.75809 | G2: 346.75809 | H2: 346.75809 | I2: 346.75809 | J2: 346.75809 | K2: 346.75809 | L2: =+D2+SUM(E2:K2) -> 3120.8228 | M2: 346.75809 | N2: 346.75809 | O2: 360 | P2: 360 | Q2: 360 | R2: 360 | S2: 360 | T2: =+L2+SUM(M2:S2) -> 5614.339 | U2: 360 | V2: 360 | W2: 360 | X2: 360 | Y2: 360 | Z2: 360 | AA2: 360 | AB2: 360 | AC2: =+T2+SUM(U2:AB2) -> 8494.339 | AD2: 360 | AE2: 360 | AF2: 360 | AG2: 360 | AH2: 360 | AI2: 360 | AJ2: =+AC2+SUM(AD2:AI2) -> 10654.339 | BG2: 9790
A3: Refinería 1 Real | B3: 355.951 | C3: 359.386 | D3: =+SUM(B3:C3) -> 715.337 | E3: 353.159 | F3: 355.097 | G3: 337.639 | H3: 358.699 | I3: 334.065 | J3: 363.063 | K3: 357.838 | L3: =+D3+SUM(E3:K3) -> 3174.897 | M3: 317.698 | N3: 321.804 | O3: 343.592 | P3: 323.922 | Q3: 311.948 | R3: 331.465 | S3: 337.165 | T3: =+L3+SUM(M3:S3) -> 5462.491 | U3: =+DOWNSTREAM!T3 -> 0 | V3: =+DOWNSTREAM!U3 -> 0 | W3: =+DOWNSTREAM!V3 -> 0 | X3: =+DOWNSTREAM!W3 -> 0 | Y3: =+DOWNSTREAM!X3 -> 0 | Z3: =+DOWNSTREAM!Z3 -> 0 | AA3: =+DOWNSTREAM!AA3 -> 0 | AB3: =+DOWNSTREAM!AB3 -> 0 | AC3: =+T3+SUM(U3:AB3) -> 5462.491 | AD3: =+DOWNSTREAM!AC3 -> 0 | AE3: =+DOWNSTREAM!AD3 -> 0 | AF3: =+DOWNSTREAM!AE3 -> 0 | AG3: =+DOWNSTREAM!AF3 -> 0 | AH3: =+DOWNSTREAM!AH3 -> 0 | AI3: =+DOWNSTREAM!AI3 -> 0 | AJ3: =+AC3+SUM(AD3:AI3) -> 5462.491
A4: % Cumplimiento | B4: =IFERROR(B3/B2,0) -> 1.026511 | C4: =IFERROR(C3/C2,0) -> 1.0364171 | D4: =IFERROR(D3/D2,0) -> 1.031464 | E4: =IFERROR(E3/E2,0) -> 1.0184593 | F4: =IFERROR(F3/F2,0) -> 1.0240482 | G4: =IFERROR(G3/G2,0) -> 0.97370187 | H4: =IFERROR(H3/H2,0) -> 1.0344358 | I4: =IFERROR(I3/I2,0) -> 0.96339497 | ... AJ4: =IFERROR(AJ3/AJ2,0) -> 0.51270107
A5: Rendimiento (94,5%)
A6: Acidez Ingreso
A7: Rojo Recepción
A8: Rojo Saponif
A9: Inventario Inicio
A10: Refinería 2 ME | B10: 22.32 | C10: 22.32 | D10: =+SUM(B10:C10) -> 44.64 | E10: 22.32 | F10: 22.32 | G10: 22.32 | H10: 22.32 | I10: 22.32 | J10: 22.32 | K10: 22.32 | L10: =+D10+SUM(E10:K10) -> 200.88 | M10: 22.32 | N10: 22.32 | O10: 37 | P10: 37 | Q10: 37 | R10: 37 | S10: 37 | T10: =+L10+SUM(M10:S10) -> 430.52 | U10: 10 | V10: 30 | W10: 30 | X10: 30 | Y10: 30 | Z10: 10 | AA10: 10 | AB10: 36 | AC10: =+T10+SUM(U10:AB10) -> 616.52 | AD10: 36 | AE10: 36 | AF10: 36 | AG10: 20 | AH10: 10 | AI10: 30 | AJ10: =+AC10+SUM(AD10:AI10) -> 784.52 | BG10: 370
A11: Refineria 2 Real | B11: 29.77 | C11: 31.6 | D11: =+SUM(B11:C11) -> 61.37 | E11: 27.8 | F11: 0 | G11: 0 | H11: 19.4 | I11: 23.33 | J11: 31.666 | K11: 32 | L11: =+D11+SUM(E11:K11) -> 195.566 | M11: 18.966 | N11: 30.988 | O11: 33.431 | P11: 36.492 | Q11: 37.35 | R11: 38.421 | S11: 37.914 | T11: =+L11+SUM(M11:S11) -> 429.128 | U11: =+DOWNSTREAM!T11 -> 0 | V11: =+DOWNSTREAM!U11 -> 0 | W11: =+DOWNSTREAM!V11 -> 0 | X11: =+DOWNSTREAM!W11 -> 0 | Y11: =+DOWNSTREAM!X11 -> 0 | Z11: =+DOWNSTREAM!Z11 -> 0 | AA11: =+DOWNSTREAM!AA11 -> 0 | AB11: =+DOWNSTREAM!AB11 -> 0 | AC11: =+T11+SUM(U11:AB11) -> 429.128 | AD11: =+DOWNSTREAM!AC11 -> 0 | AE11: =+DOWNSTREAM!AD11 -> 0 | AF11: =+DOWNSTREAM!AE11 -> 0 | AG11: =+DOWNSTREAM!AF11 -> 0 | AH11: =+DOWNSTREAM!AH11 -> 0 | AI11: =+DOWNSTREAM!AI11 -> 0 | AJ11: =+AC11+SUM(AD11:AI11) -> 429.128
A12: % Cumplimiento | B12: =IFERROR(+B11/B10,0) -> 1.3337814 | C12: =IFERROR(+C11/C10,0) -> 1.4157706 | D12: =IFERROR(+D11/D10,0) -> 1.374776 | E12: =IFERROR(+E11/E10,0) -> 1.2455197 | F12: =IFERROR(+F11/F10,0) -> 0 | G12: =IFERROR(+G11/G10,0) -> 0 | H12: =IFERROR(+H11/H10,0) -> 0.86917563 | I12: =IFERROR(+I11/I10,0) -> 1.0452509 | ... AJ12: =IFERROR(+AJ11/AJ10,0) -> 0.54699434
A13: Rendimiento (93,5%)
A14: Rojo Recepción
A15: Rojo Saponif
A16: Inventario Inicio
A17: Fracc 1 ME | B17: 70.678273 | C17: 70.678273 | D17: =+SUM(B17:C17) -> 141.35655 | E17: 70.678273 | F17: 70.678273 | G17: 70.678273 | H17: 70.678273 | I17: 70.678273 | J17: 70.678273 | K17: 70.678273 | L17: =+D17+SUM(E17:K17) -> 636.10445 | M17: 70.678273 | N17: 70.678273 | O17: 95 | P17: 95 | Q17: 95 | R17: 95 | S17: 95 | T17: =+L17+SUM(M17:S17) -> 1252.461 | U17: 95 | V17: 95 | W17: 95 | X17: 95 | Y17: 95 | Z17: 95 | AA17: 95 | AB17: 95 | AC17: =+T17+SUM(U17:AB17) -> 2012.461 | AD17: 95 | AE17: 95 | AF17: 95 | AG17: 95 | AH17: 95 | AI17: 95 | AJ17: =+AC17+SUM(AD17:AI17) -> 2582.461 | BG17: 3578.9474
A18: Fracc 1 Real | B18: 64.57 | C18: 93.8 | D18: =+SUM(B18:C18) -> 158.37 | E18: 83.1 | F18: 93.23 | G18: 86.911 | H18: 0 | I18: 53.7 | J18: 47.37 | K18: 78.2 | L18: =+D18+SUM(E18:K18) -> 600.881 | M18: 90.65 | N18: 85.93 | O18: 85.9 | P18: 80.5 | Q18: 93.3 | R18: 91.6 | S18: 85.5 | T18: =+L18+SUM(M18:S18) -> 1214.261 | U18: =+DOWNSTREAM!T20 -> 0 | V18: =+DOWNSTREAM!U20 -> 0 | W18: =+DOWNSTREAM!V20 -> 0 | X18: =+DOWNSTREAM!W20 -> 0 | Y18: =+DOWNSTREAM!X20 -> 0 | Z18: =+DOWNSTREAM!Z20 -> 0 | AA18: =+DOWNSTREAM!AA20 -> 0 | AB18: =+DOWNSTREAM!AB20 -> 0 | AC18: =+T18+SUM(U18:AB18) -> 1214.261 | AD18: =+DOWNSTREAM!AC20 -> 0 | AE18: =+DOWNSTREAM!AD20 -> 0 | AF18: =+DOWNSTREAM!AE20 -> 0 | AG18: =+DOWNSTREAM!AF20 -> 0 | AH18: =+DOWNSTREAM!AH20 -> 0 | AI18: =+DOWNSTREAM!AI20 -> 0 | AJ18: =+AC18+SUM(AD18:AI18) -> 1214.261
A19: % Cumplimiento | B19: =IFERROR(+B18/B17,0) -> 0.91357637 | C19: =IFERROR(+C18/C17,0) -> 1.3271405 | D19: =IFERROR(+D18/D17,0) -> 1.1203584 | E19: =IFERROR(+E18/E17,0) -> 1.1757503 | F19: =IFERROR(+F18/F17,0) -> 1.3190758 | G19: =IFERROR(+G18/G17,0) -> 1.2296707 | H19: =IFERROR(+H18/H17,0) -> 0 | I19: =IFERROR(+I18/I17,0) -> 0.75978088 | ... AJ19: =IFERROR(+AJ18/AJ17,0) -> 0.47019529
A20: Rendimiento (75,2%)
A21: Rojo Recepción
A22: Rojo Saponif
A23: Fracc 2 ME | B23: 117.71364 | C23: 117.71364 | D23: =+SUM(B23:C23) -> 235.42727 | E23: 117.71364 | F23: 117.71364 | G23: 117.71364 | H23: 117.71364 | I23: 117.71364 | J23: 117.71364 | K23: 117.71364 | L23: =+D23+SUM(E23:K23) -> 1059.4227 | M23: 117.71364 | N23: 117.71364 | O23: 125 | P23: 125 | Q23: 125 | R23: 125 | S23: 125 | T23: =+L23+SUM(M23:S23) -> 1919.85 | U23: 125 | V23: 125 | W23: 125 | X23: 125 | Y23: 125 | Z23: 125 | AA23: 125 | AB23: 125 | AC23: =+T23+SUM(U23:AB23) -> 2919.85 | AD23: 125 | AE23: 125 | AF23: 125 | AG23: 125 | AH23: 125 | AI23: 125 | AJ23: =+AC23+SUM(AD23:AI23) -> 3669.85 | BG23: 4636.3636
A24: Fracc 2 Real | B24: 127.94 | C24: 131.12 | D24: =+SUM(B24:C24) -> 259.06 | E24: 118.33 | F24: 130.69 | G24: 131.57 | H24: 61.66 | I24: 86.78 | J24: 130.19 | K24: 115.4 | L24: =+D24+SUM(E24:K24) -> 1033.68 | M24: 130.96 | N24: 130.21 | O24: 130.06 | P24: 131.24 | Q24: 131.44 | R24: 130.85 | S24: 130.45 | T24: =+L24+SUM(M24:S24) -> 1948.89 | U24: =+DOWNSTREAM!T26 -> 0 | V24: =+DOWNSTREAM!U26 -> 0 | W24: =+DOWNSTREAM!V26 -> 0 | X24: =+DOWNSTREAM!W26 -> 0 | Y24: =+DOWNSTREAM!X26 -> 0 | Z24: =+DOWNSTREAM!Z26 -> 0 | AA24: =+DOWNSTREAM!AA26 -> 0 | AB24: =+DOWNSTREAM!AB26 -> 0 | AC24: =+T24+SUM(U24:AB24) -> 1948.89 | AD24: =+DOWNSTREAM!AC26 -> 0 | AE24: =+DOWNSTREAM!AD26 -> 0 | AF24: =+DOWNSTREAM!AE26 -> 0 | AG24: =+DOWNSTREAM!AF26 -> 0 | AH24: =+DOWNSTREAM!AH26 -> 0 | AI24: =+DOWNSTREAM!AI26 -> 0 | AJ24: =+AC24+SUM(AD24:AI24) -> 1948.89
A25: % Cumplimiento | B25: =IFERROR(+B24/B23,0) -> 1.0868749 | C25: =IFERROR(+C24/C23,0) -> 1.1138896 | D25: =IFERROR(+D24/D23,0) -> 1.1003823 | E25: =IFERROR(+E24/E23,0) -> 1.0052361 | F25: =IFERROR(+F24/F23,0) -> 1.1102367 | G25: =IFERROR(+G24/G23,0) -> 1.1177125 | H25: =IFERROR(+H24/H23,0) -> 0.52381357 | I25: =IFERROR(+I24/I23,0) -> 0.7372128 | ... AJ25: =IFERROR(+AJ24/AJ23,0) -> 0.5310544
A26: Rendimiento (77,3%)
A27: Cold Test
A28: Rojo
A29: Inventario Inicio
A30: Margarinas ME | B30: =+HLOOKUP(B$1,'[7]Programa Diario CODAZZI'!$F$8:$AL$44,37,0)/1000 -> #N/A | C30: =+HLOOKUP(C$1,'[7]Programa Diario CODAZZI'!$F$8:$AL$44,37,0)/1000 -> #N/A | D30: =+SUM(B30:C30) -> #N/A | E30: =+HLOOKUP(E$1,'[7]Programa Diario CODAZZI'!$F$8:$AL$44,37,0)/1000 -> #N/A | F30: =+HLOOKUP(F$1,'[7]Programa Diario CODAZZI'!$F$8:$AL$44,37,0)/1000 -> #N/A | G30: =+HLOOKUP(G$1,'[7]Programa Diario CODAZZI'!$F$8:$AL$44,37,0)/1000 -> #N/A | H30: =+HLOOKUP(H$1,'[7]Programa Diario CODAZZI'!$F$8:$AL$44,37,0)/1000 -> #N/A | I30: =+HLOOKUP(I$1,'[7]Programa Diario CODAZZI'!$F$8:$AL$44,37,0)/1000 -> #N/A | J30: =+HLOOKUP(J$1,'[7]Programa Diario CODAZZI'!$F$8:$AL$44,37,0)/1000 -> #N/A | K30: =+HLOOKUP(K$1,'[7]Programa Diario CODAZZI'!$F$8:$AL$44,37,0)/1000 -> #N/A | L30: =+D30+SUM(E30:K30) -> #N/A | M30: =+HLOOKUP(M$1,'[7]Programa Diario CODAZZI'!$F$8:$AL$44,37,0)/1000 -> #N/A | N30: =+HLOOKUP(N$1,'[7]Programa Diario CODAZZI'!$F$8:$AL$44,37,0)/1000 -> #N/A | O30: =+HLOOKUP(O$1,'[7]Programa Diario CODAZZI'!$F$8:$AL$44,37,0)/1000 -> #N/A | P30: =+HLOOKUP(P$1,'[7]Programa Diario CODAZZI'!$F$8:$AL$44,37,0)/1000 -> #N/A | Q30: =+HLOOKUP(Q$1,'[7]Programa Diario CODAZZI'!$F$8:$AL$44,37,0)/1000 -> #N/A | R30: =+HLOOKUP(R$1,'[7]Programa Diario CODAZZI'!$F$8:$AL$44,37,0)/1000 -> #N/A | S30: =+HLOOKUP(S$1,'[7]Programa Diario CODAZZI'!$F$8:$AL$44,37,0)/1000 -> #N/A | T30: =+L30+SUM(M30:S30) -> #N/A | U30: =+HLOOKUP(U$1,'[7]Programa Diario CODAZZI'!$F$8:$AL$44,37,0)/1000 -> #N/A | V30: =+HLOOKUP(V$1,'[7]Programa Diario CODAZZI'!$F$8:$AL$44,37,0)/1000 -> #N/A | W30: =+HLOOKUP(W$1,'[7]Programa Diario CODAZZI'!$F$8:$AL$44,37,0)/1000 -> #N/A | X30: =+HLOOKUP(X$1,'[7]Programa Diario CODAZZI'!$F$8:$AL$44,37,0)/1000 -> #N/A | Y30: =+HLOOKUP(Y$1,'[7]Programa Diario CODAZZI'!$F$8:$AL$44,37,0)/1000 -> #N/A | Z30: =+HLOOKUP(Z$1,'[7]Programa Diario CODAZZI'!$F$8:$AL$44,37,0)/1000 -> #N/A | AA30: =+HLOOKUP(AA$1,'[7]Programa Diario CODAZZI'!$F$8:$AL$44,37,0)/1000 -> #N/A | AB30: =+HLOOKUP(AB$1,'[7]Programa Diario CODAZZI'!$F$8:$AL$44,37,0)/1000 -> #N/A | AC30: =+T30+SUM(U30:AB30) -> #N/A | AD30: =+HLOOKUP(AD$1,'[7]Programa Diario CODAZZI'!$F$8:$AL$44,37,0)/1000 -> #N/A | AE30: =+HLOOKUP(AE$1,'[7]Programa Diario CODAZZI'!$F$8:$AL$44,37,0)/1000 -> #N/A | AF30: =+HLOOKUP(AF$1,'[7]Programa Diario CODAZZI'!$F$8:$AL$44,37,0)/1000 -> #N/A | AG30: =+HLOOKUP(AG$1,'[7]Programa Diario CODAZZI'!$F$8:$AL$44,37,0)/1000 -> #N/A | AH30: =+HLOOKUP(AH$1,'[7]Programa Diario CODAZZI'!$F$8:$AL$44,37,0)/1000 -> #N/A | AI30: =+HLOOKUP(AI$1,'[7]Programa Diario CODAZZI'!$F$8:$AL$44,37,0)/1000 -> #N/A | AJ30: =+AC30+SUM(AD30:AI30) -> #N/A | BG30: 645
A31: Margarinas Real | B31: 63 | C31: 56.7 | D31: =+SUM(B31:C31) -> 119.7 | E31: 53.55 | F31: 40.95 | G31: 63 | H31: 66.15 | I31: 63 | J31: 44.1 | K31: 9.45 | L31: =+D31+SUM(E31:K31) -> 459.9 | M31: 40.95 | N31: 63 | O31: 63 | P31: 56.7 | Q31: 69.3 | R31: 59.565 | S31: 53.55 | T31: =+L31+SUM(M31:S31) -> 865.965 | U31: =+DOWNSTREAM!T33 -> 0 | V31: =+DOWNSTREAM!U33 -> 0 | W31: =+DOWNSTREAM!V33 -> 0 | X31: =+DOWNSTREAM!W33 -> 0 | Y31: =+DOWNSTREAM!X33 -> 0 | Z31: =+DOWNSTREAM!Z33 -> 0 | AA31: =+DOWNSTREAM!AA33 -> 0 | AB31: =+DOWNSTREAM!AB33 -> 0 | AC31: =+T31+SUM(U31:AB31) -> 865.965 | AD31: =+DOWNSTREAM!AC33 -> 0 | AE31: =+DOWNSTREAM!AD33 -> 0 | AF31: =+DOWNSTREAM!AE33 -> 0 | AG31: =+DOWNSTREAM!AF33 -> 0 | AH31: =+DOWNSTREAM!AH33 -> 0 | AI31: =+DOWNSTREAM!AI33 -> 0 | AJ31: =+AC31+SUM(AD31:AI31) -> 865.965
A32: % Cumplimiento | B32: =IFERROR(B31/B30,0) -> 0 | C32: =IFERROR(C31/C30,0) -> 0 | D32: =IFERROR(D31/D30,0) -> 0 | E32: =IFERROR(E31/E30,0) -> 0 | F32: =IFERROR(F31/F30,0) -> 0 | G32: =IFERROR(G31/G30,0) -> 0 | H32: =IFERROR(H31/H30,0) -> 0 | I32: =IFERROR(I31/I30,0) -> 0 | ... AJ32: =IFERROR(AJ31/AJ30,0) -> 0
A33: TOTAL PALMA RBD ME | B33: =+B2 -> 346.75809 | C33: =+C2 -> 346.75809 | D33: =+D2 -> 693.51618 | E33: =+E2 -> 346.75809 | F33: =+F2 -> 346.75809 | G33: =+G3 -> 337.639 | H33: =+H2 -> 346.75809 | I33: =+I2 -> 346.75809 | J33: =+J2 -> 346.75809 | K33: =+K2 -> 346.75809 | L33: =+L2 -> 3120.8228 | M33: =+M2 -> 346.75809 | N33: =+N2 -> 346.75809 | O33: =+O2 -> 360 | ... AJ33: =+AJ2 -> 10654.339
A34: TOTAL PALMA RBD Real | B34: =+B3 -> 355.951 | C34: =+C3 -> 359.386 | D34: =+D3 -> 715.337 | E34: =+E3 -> 353.159 | F34: =+F3 -> 355.097 | G34: =+G3 -> 337.639 | H34: =+H3 -> 358.699 | I34: =+I3 -> 334.065 | ... AJ34: =+AJ3 -> 5462.491
A35: % Cumplimiento | B35: =IFERROR(+B34/B33,0) -> 1.026511 | C35: =IFERROR(+C34/C33,0) -> 1.0364171 | D35: =IFERROR(+D34/D33,0) -> 1.031464 | E35: =IFERROR(+E34/E33,0) -> 1.0184593 | F35: =IFERROR(+F34/F33,0) -> 1.0240482 | G35: =IFERROR(+G34/G33,0) -> 1 | H35: =IFERROR(+H34/H33,0) -> 1.0344358 | I35: =IFERROR(+I34/I33,0) -> 0.96339497 | ... AJ35: =IFERROR(+AJ34/AJ33,0) -> 0.51270107
A36: TOTAL PALMISTE RBD ME | B36: =+B10 -> 22.32 | C36: =+C10 -> 22.32 | D36: =+D10 -> 44.64 | E36: =+E10 -> 22.32 | F36: =+F10 -> 22.32 | G36: =+G10 -> 22.32 | H36: =+H10 -> 22.32 | I36: =+I10 -> 22.32 | ... AJ36: =+AJ10 -> 784.52
A37: TOTAL PALMISTE RBD Real | B37: =+B11 -> 29.77 | C37: =+C11 -> 31.6 | D37: =+D11 -> 61.37 | E37: =+E11 -> 27.8 | F37: =+F11 -> 0 | G37: =+G11 -> 0 | H37: =+H11 -> 19.4 | I37: =+I11 -> 23.33 | ... AJ37: =+AJ11 -> 429.128
A38: % Cumplimiento | B38: =IFERROR(+B37/B36,0) -> 1.3337814 | C38: =IFERROR(+C37/C36,0) -> 1.4157706 | D38: =IFERROR(+D37/D36,0) -> 1.374776 | E38: =IFERROR(+E37/E36,0) -> 1.2455197 | F38: =IFERROR(+F37/F36,0) -> 0 | G38: =IFERROR(+G37/G36,0) -> 0 | H38: =IFERROR(+H37/H36,0) -> 0.86917563 | I38: =IFERROR(+I37/I36,0) -> 1.0452509 | ... AJ38: =IFERROR(+AJ37/AJ36,0) -> 0.54699434
A39: TOTAL OLEINA ME | B39: =+B17+B23 -> 188.39191 | C39: =+C17+C23 -> 188.39191 | D39: =+D17+D23 -> 376.78382 | E39: =+E17+E23 -> 188.39191 | F39: =+F17+F23 -> 188.39191 | G39: =+G17+G23 -> 188.39191 | H39: =+H17+H23 -> 188.39191 | I39: =+I17+I23 -> 188.39191 | ... AJ39: =+AJ17+AJ23 -> 6252.311
A40: TOTAL OLEINA Real | B40: =+B18+B24 -> 192.51 | C40: =+C18+C24 -> 224.92 | D40: =+D18+D24 -> 417.43 | E40: =+E18+E24 -> 201.43 | F40: =+F18+F24 -> 223.92 | G40: =+G18+G24 -> 218.481 | H40: =+H18+H24 -> 61.66 | I40: =+I18+I24 -> 140.48 | ... AJ40: =+AJ18+AJ24 -> 3163.151
A41: % Cumplimiento | B41: =IFERROR(+B40/B39,0) -> 1.0218592 | C41: =IFERROR(+C40/C39,0) -> 1.1938942 | D41: =IFERROR(+D40/D39,0) -> 1.1078767 | E41: =IFERROR(+E40/E39,0) -> 1.0692073 | F41: =IFERROR(+F40/F39,0) -> 1.1885861 | G41: =IFERROR(+G40/G39,0) -> 1.1597154 | H41: =IFERROR(+H40/H39,0) -> 0.32729643 | I41: =IFERROR(+I40/I39,0) -> 0.74567958 | ... AJ41: =IFERROR(+AJ40/AJ39,0) -> 0.50591709
A42: TOTAL MARGARINAS ME | B42: =+B30 -> #N/A | C42: =+C30 -> #N/A | D42: =+D30 -> #N/A | E42: =+E30 -> #N/A | F42: =+F30 -> #N/A | G42: =+G30 -> #N/A | H42: =+H30 -> #N/A | I42: =+I30 -> #N/A | ... AJ42: =+AJ30 -> #N/A
A43: TOTAL MARGARINAS Real | B43: =+B31 -> 63 | C43: =+C31 -> 56.7 | D43: =+D31 -> 119.7 | E43: =+E31 -> 53.55 | F43: =+F31 -> 40.95 | G43: =+G31 -> 63 | H43: =+H31 -> 66.15 | I43: =+I31 -> 63 | ... AJ43: =+AJ31 -> 865.965
A44: % Cumplimiento | B44: =IFERROR(+B43/B42,0) -> 0 | C44: =IFERROR(+C43/C42,0) -> 0 | D44: =IFERROR(+D43/D42,0) -> 0 | E44: =IFERROR(+E43/E42,0) -> 0 | F44: =IFERROR(+F43/F42,0) -> 0 | G44: =IFERROR(+G43/G42,0) -> 0 | H44: =IFERROR(+H43/H42,0) -> 0 | I44: =IFERROR(+I43/I42,0) -> 0 | ... AJ44: =IFERROR(+AJ43/AJ42,0) -> 0
B45: PLANTA | C45: ME | D45: REAL | E45: % CUMPL | F45: DIF TM | J45: PLANTA | K45: ME | L45: REAL | M45: % CUMPL | N45: DIF TM | R45: PLANTA | S45: ME | T45: REAL | U45: % CUMPL | V45: DIF TM | Z45: PLANTA | AA45: ME | AB45: REAL | AC45: % CUMPL | AD45: DIF TM | AF45: PLANTA | AG45: ME | AJ45: REAL | AK45: % CUMPL | AL45: DIF TM | BL45: PLANTA | BM45: ME | BN45: REAL | BO45: % CUMPL | BP45: DIF TM
B46: REFINERIA 1 | C46: =+D33 -> 693.51618 | D46: =+D34 -> 715.337 | E46: =IFERROR(D46/C46,0) -> 1.031464 | F46: =+D46-C46 -> 21.820818 | J46: REFINERIA 1 | K46: =+L33 -> 3120.8228 | L46: =+L34 -> 3174.897 | M46: =IFERROR(L46/K46,0) -> 1.0173269 | N46: =+L46-K46 -> 54.074182 | R46: REFINERIA 1 | S46: =+T33 -> 5614.339 | T46: =+T34 -> 5462.491 | U46: =IFERROR(T46/S46,0) -> 0.97295354 | V46: =+T46-S46 -> -151.848 | Z46: REFINERIA 1 | AA46: =+AC33 -> 8494.339 | AB46: =+AC34 -> 5462.491 | AC46: =IFERROR(AB46/AA46,0) -> 0.64307429 | AD46: =+AB46-AA46 -> -3031.848 | AE46: =1303935/1000 -> 1303.935 | AF46: REFINERIA 1 | AG46: =+AJ33 -> 10654.339 | AJ46: =+AJ34 -> 5462.491 | AK46: =IFERROR(AJ46/AG46,0) -> 0.51270107 | AL46: =+AJ46-AG46 -> -5191.848 | BL46: REFINERIA 1 | BM46: =+AJ33 -> 10654.339 | BN46: =+AJ34 -> 5462.491 | BO46: =IFERROR(BN46/BM46,0) -> 0.51270107 | BP46: =+BN46-BM46 -> -5191.848
B47: REFINERIA 2 | C47: =+D36 -> 44.64 | D47: =+D37 -> 61.37 | E47: =IFERROR(D47/C47,0) -> 1.374776 | F47: =+D47-C47 -> 16.73 | J47: REFINERIA 2 | K47: =+L36 -> 200.88 | L47: =+L37 -> 195.566 | M47: =IFERROR(L47/K47,0) -> 0.9735464 | N47: =+L47-K47 -> -5.314 | R47: REFINERIA 2 | S47: =+T36 -> 430.52 | T47: =+T37 -> 429.128 | U47: =IFERROR(T47/S47,0) -> 0.9967667 | V47: =+T47-S47 -> -1.392 | Z47: REFINERIA 2 | AA47: =+AC36 -> 616.52 | AB47: =+AC37 -> 429.128 | AC47: =IFERROR(AB47/AA47,0) -> 0.69604879 | AD47: =+AB47-AA47 -> -187.392 | AE47: =+AC31+AE31 -> 865.965 | AF47: REFINERIA 2 | AG47: =+AJ36 -> 784.52 | AJ47: =+AJ37 -> 429.128 | AK47: =IFERROR(AJ47/AG47,0) -> 0.54699434 | AL47: =+AJ47-AG47 -> -355.392 | BL47: REFINERIA 2 | BM47: =+AJ36 -> 784.52 | BN47: =+AJ37 -> 429.128 | BO47: =IFERROR(BN47/BM47,0) -> 0.54699434 | BP47: =+BN47-BM47 -> -355.392
B48: OLEINA | C48: =+D39 -> 376.78382 | D48: =+D40 -> 417.43 | E48: =IFERROR(D48/C48,0) -> 1.1078767 | F48: =+D48-C48 -> 40.646182 | J48: OLEINA | K48: =+L39 -> 1695.5272 | L48: =+L40 -> 1634.561 | M48: =IFERROR(L48/K48,0) -> 0.96404293 | N48: =+L48-K48 -> -60.966182 | R48: OLEINA | S48: =+T39 -> 3172.311 | T48: =+T40 -> 3163.151 | U48: =IFERROR(T48/S48,0) -> 0.99711252 | V48: =+T48-S48 -> -9.16 | Z48: OLEINA | AA48: =+AC39 -> 4932.311 | AB48: =+AC40 -> 3163.151 | AC48: =IFERROR(AB48/AA48,0) -> 0.64131216 | AD48: =+AB48-AA48 -> -1769.16 | AE48: =+AE46-AE47 -> 437.97 | AF48: OLEINA | AG48: =+AJ39 -> 6252.311 | AJ48: =+AJ40 -> 3163.151 | AK48: =IFERROR(AJ48/AG48,0) -> 0.50591709 | AL48: =+AJ48-AG48 -> -3089.16 | BL48: OLEINA | BM48: =+AJ39 -> 6252.311 | BN48: =+AJ40 -> 3163.151 | BO48: =IFERROR(BN48/BM48,0) -> 0.50591709 | BP48: =+BN48-BM48 -> -3089.16
B49: MARGARINAS | C49: =+D42 -> #N/A | D49: =+D43 -> 119.7 | E49: =IFERROR(D49/C49,0) -> 0 | F49: =+D49-C49 -> #N/A | J49: MARGARINAS | K49: =+L42 -> #N/A | L49: =+L43 -> 459.9 | M49: =IFERROR(L49/K49,0) -> 0 | N49: =+L49-K49 -> #N/A | R49: MARGARINAS | S49: =+T42 -> #N/A | T49: =+T43 -> 865.965 | U49: =IFERROR(T49/S49,0) -> 0 | V49: =+T49-S49 -> #N/A | Z49: MARGARINAS | AA49: =+AC42 -> #N/A | AB49: =+AC43 -> 865.965 | AC49: =IFERROR(AB49/AA49,0) -> 0 | AD49: =+AB49-AA49 -> #N/A | AF49: MARGARINAS | AG49: =+AJ42 -> #N/A | AJ49: =+AJ43 -> 865.965 | AK49: =IFERROR(AJ49/AG49,0) -> 0 | AL49: =+AJ49-AG49 -> #N/A | BL49: MARGARINAS | BM49: =+AJ42 -> #N/A | BN49: =+AJ43 -> 865.965 | BO49: =IFERROR(BN49/BM49,0) -> 0 | BP49: =+BN49-BM49 -> #N/A
B50: TOTAL | C50: =SUM(C46:C49) -> #N/A | D50: =SUM(D46:D49) -> 1313.837 | E50: =IFERROR(D50/C50,0) -> 0 | F50: =+D50-C50 -> #N/A | J50: TOTAL | K50: =SUM(K46:K49) -> #N/A | L50: =SUM(L46:L49) -> 5464.924 | M50: =IFERROR(L50/K50,0) -> 0 | N50: =+L50-K50 -> #N/A | R50: TOTAL | S50: =SUM(S46:S49) -> #N/A | T50: =SUM(T46:T49) -> 9920.735 | U50: =IFERROR(T50/S50,0) -> 0 | V50: =+T50-S50 -> #N/A | Z50: TOTAL | AA50: =SUM(AA46:AA49) -> #N/A | AB50: =SUM(AB46:AB49) -> 9920.735 | AC50: =IFERROR(AB50/AA50,0) -> 0 | AD50: =+AB50-AA50 -> #N/A | AF50: TOTAL | AG50: =SUM(AG46:AG49) -> #N/A | AJ50: =SUM(AJ46:AJ49) -> 9920.735 | AK50: =IFERROR(AJ50/AG50,0) -> 0 | AL50: =+AJ50-AG50 -> #N/A | BL50: TOTAL | BM50: =SUM(BM46:BM49) -> #N/A | BN50: =SUM(BN46:BN49) -> 9920.735 | BO50: =IFERROR(BN50/BM50,0) -> 0 | BP50: =+BN50-BM50 -> #N/A
V51: =+R51-Q51 -> 0
V52: =+R52-Q52 -> 0
V53: =+R53-Q53 -> 0
V54: =+R54-Q54 -> 0
V55: =+R55-Q55 -> 0
V56: =+R56-Q56 -> 0
V57: =+R57-Q57 -> 0
V58: =+R58-Q58 -> 0
V59: =+R59-Q59 -> 0
V60: =+R60-Q60 -> 0
Q61: =+SUM(Q52:Q58) -> 0 | R61: =+SUM(R52:R58) -> 0 | V61: =+R61-Q61 -> 0

Sheet Resumen DOWNSTREAM
B3: DOWNSTREAM | E3: ACUMULADO S1
B5: PLANTA | C5: ME 1 | D5: ME 2 | E5: Real | F5: Dif 1 | G5: RBD Rep | H5: Real T | I5: Dif 2 | J5: % | K5: % | M5: Inventario
B6: REFINERIA 1 | C6: =+HLOOKUP($E3,DOWNSTREAM!$A$1:$AO$46,35,0) -> 2765 | D6: =+HLOOKUP($E3,'DOWNSTREAM mod'!$A$1:$AJ$44,33,0) -> 693.51618 | E6: =+HLOOKUP($E$3,DOWNSTREAM!$A$1:$AO$46,36,0) -> 2713.25 | F6: =+E6-C6 -> -51.75 | G6: 949.11 | H6: =+G6+E6 -> 3662.36 | I6: =+H6-D6 -> 2968.8438 | J6: =+E6/C6 -> 0.98128391 | K6: =+H6/D6 -> 5.2808573 | M6: =+[9]Inf_Diario_RBD!$D$12/1000 -> 345.8293 | N6: RBD
B7: REFINERIA 2 | C7: =+HLOOKUP($E$3,DOWNSTREAM!$A$1:$AO$46,38,0) -> 205 | D7: =+HLOOKUP($E$3,'DOWNSTREAM mod'!$A$1:$AJ$44,36,0) -> 44.64 | E7: =+HLOOKUP($E$3,DOWNSTREAM!$A$1:$AO$46,39,0) -> 235.873 | F7: =+E7-C7 -> 30.873 | H7: =+G7+E7 -> 235.873 | I7: =+H7-D7 -> 191.233 | J7: =+E7/C7 -> 1.1506 | K7: =+H7/D7 -> 5.2838934
B8: OLEINA | C8: =+HLOOKUP($E$3,DOWNSTREAM!$A$1:$AO$46,41,0) -> 1672 | D8: =+HLOOKUP($E$3,'DOWNSTREAM mod'!$A$1:$AJ$44,39,0) -> 376.78382 | E8: =+HLOOKUP($E$3,DOWNSTREAM!$A$1:$AO$46,42,0) -> 1606.615 | F8: =+E8-C8 -> -65.385 | H8: =+G8+E8 -> 1606.615 | I8: =+H8-D8 -> 1229.8312 | J8: =+E8/C8 -> 0.96089414 | K8: =+H8/D8 -> 4.2640234 | M8: =+[9]Inf_Diario_Oleina!$D$12/1000 -> 159.44696 | N8: Oleina
B9: MARGARINAS | C9: =+HLOOKUP($E$3,DOWNSTREAM!$A$1:$AO$46,44,0) -> 500.85 | D9: =+HLOOKUP($E$3,'DOWNSTREAM mod'!$A$1:$AJ$44,42,0) -> #N/A | E9: =+HLOOKUP($E$3,DOWNSTREAM!$A$1:$AO$46,45,0) -> 409.5 | F9: =+E9-C9 -> -91.35 | H9: =+G9+E9 -> 409.5 | I9: =+H9-D9 -> #N/A | J9: =+E9/C9 -> 0.81761006 | K9: =+H9/D9 -> #N/A | M9: 528.202 | N9: Margarinas
B11: TOTAL | C11: =+SUM(C6:C9) -> 5142.85 | D11: =+SUM(D6:D9) -> #N/A | E11: =+SUM(E6:E9) -> 4965.238 | F11: =+SUM(F6:F9) -> -177.612 | G11: =+SUM(G6:G9) -> 949.11 | H11: =+SUM(H6:H9) -> 5914.348 | I11: =+H11-D11 -> #N/A | J11: =+E11/C11 -> 0.96546429 | K11: =+H11/D11 -> #N/A
B17: Efeciencia
B19: RBD | C19: 0.9484
B20: Oleina | C20: 0.744 | E20: Incremento 3%

Sheet Lista
C5: ACUMULADO S1
C6: ACUMULADO S2
C7: ACUMULADO S3
C8: ACUMULADO S4
C9: ACUMULADO DIC 25
C13: ACUMULADO S1
C14: ACUMULADO S2
C15: ACUMULADO S3
C16: ACUMULADO S4
C17: ACUMULADO DIC 25

Sheet PLANEACIÓN DICIEMBRE
B1: PROCESO ABRIL 2025 | H1: Costos Abril 07 | I1: %
C2: TM | D2: EXT | E2: CPO | F2: PK | G2: KPO
B3: CODAZZI | C3: 23000 | D3: 0.204 | E3: =+D3*C3 -> 4692 | F3: =+C3*0.055 -> 1265 | H3: 923 | I3: 19,81%
B4: MLB | C4: 9000 | D4: 0.18 | E4: =+D4*C4 -> 1620 | F4: =+C4*0.05 -> 450 | H4: 823,81 | I4: 17,67%
B5: CATATUMBO | C5: 20000 | D5: 0.227 | E5: =+D5*C5 -> 4540 | F5: =+C5*0.05 -> 1000 | H5: 904,26 | I5: 19,40%
B6: SINÚ | C6: 8000 | D6: 0.205 | E6: =+D6*C6 -> 1640 | F6: =+C6*0.045 -> 360 | H6: 859,88 | I6: 18,45%
B7: TOTAL | C7: =+SUM(C3:C6) -> 60000 | D7: =+E7/C7 -> 0.2082 | E7: =+SUM(E3:E6) -> 12492 | F7: =+SUM(F3:F6)-1-400 -> 2674 | G7: =+F7*0.405-1 -> 1081.97
B13: PROCESO JUNIO 2025
C14: TM | D14: EXT | E14: CPO | F14: PK | G14: KPO
B15: CODAZZI | C15: 19900 | D15: 0.214 | E15: =+D15*C15 -> 4258.6 | F15: =+C15*0.055 -> 1094.5
B16: MLB | C16: 8800 | D16: 0.195 | E16: =+D16*C16 -> 1716 | F16: =+C16*0.05 -> 440
B17: CATATUMBO | C17: 18300 | D17: 0.234 | E17: =+D17*C17 -> 4282.2 | F17: =+C17*0.05 -> 915
B18: SINÚ | C18: 6250 | D18: 0.23 | E18: =+D18*C18 -> 1437.5 | F18: =+C18*0.045 -> 281.25
B19: TOTAL | C19: =+SUM(C15:C18) -> 53250 | D19: =+E19/C19 -> 0.21961127 | E19: =+SUM(E15:E18) -> 11694.3 | F19: =+SUM(F15:F18)-1 -> 2729.75 | G19: =+F19*0.41-1 -> 1118.1975
B22: PROCESO JULIO 2025 | H22: CENSO | I22: Precio
C23: TM | D23: EXT | E23: CPO | F23: PK | G23: KPO
B24: CODAZZI | C24: 17500 | D24: 0.227 | E24: =+D24*C24 -> 3972.5 | F24: =+C24*0.055 -> 962.5 | H24: =17700+1450 -> 19150 | I24: 0.192
B25: MLB | C25: 6300 | D25: 0.2 | E25: =+D25*C25 -> 1260 | F25: =+C25*0.05 -> 315 | H25: 8900 | I25: 0.175
B26: CATATUMBO | C26: 16100 | D26: 0.235 | E26: =+D26*C26 -> 3783.5 | F26: =+C26*0.05 -> 805 | H26: 17581 | I26: 0.196
B27: SINÚ | C27: 6200 | D27: 0.235 | E27: =+D27*C27 -> 1457 | F27: =+C27*0.045 -> 279 | H27: 7700 | I27: 0.182
B28: TOTAL | C28: =+SUM(C24:C27) -> 46100 | D28: =+E28/C28 -> 0.22718004 | E28: =+SUM(E24:E27) -> 10473 | F28: =+SUM(F24:F27)+200 -> 2561.5 | G28: =+F28*0.41-1 -> 1049.215 | H28: =+SUM(H24:H27) -> 53331 | I28: =+(D24*I24+D25*I25+D26*I26+D27*I27)/SUM(D24:D27) -> 0.18663768
B33: PROCESO SEPTIEMBRE 2025 | H33: Censo | I33: Precio
C34: TM | D34: EXT | E34: CPO | F34: PK | G34: KPO
B35: CODAZZI | C35: 20500 | D35: 0.22 | E35: =+C35*D35 -> 4510 | F35: =+C35*0.055 -> 1127.5 | H35: =19370 -> 19370 | I35: 809.84 | J35: 0.195
B36: MLB | C36: 6700 | D36: 0.198 | E36: =+C36*D36 -> 1326.6 | F36: =+C36*0.05 -> 335 | H36: =6517.72 -> 6517.72 | I36: 712 | J36: 0.173
B37: CATATUMBO | C37: 22500 | D37: 0.235 | E37: =+C37*D37 -> 5287.5 | F37: =+C37*0.05 -> 1125 | H37: 22296 | I37: 816.537 | J37: 0.196
B38: SINÚ | C38: 5950 | D38: 0.22 | E38: =+C38*D38 -> 1309 | F38: =+C38*0.045 -> 267.75 | H38: 7317 | I38: 777.1 | J38: 0.187
B39: TOTAL | C39: =+SUM(C35:C38) -> 55650 | D39: =+E39/C39 -> 0.22341599 | E39: =+SUM(E35:E38) -> 12433.1 | F39: =+SUM(F35:F38) -> 2855.25 | G39: =+F39*41% -> 1170.6525 | H39: =+SUM(H35:H38) -> 55500.72
B43: PROCESO SEPTIEMBRE V2 2025 | H43: Censo | I43: Precio
C44: TM | D44: EXT | E44: CPO | F44: PK | G44: KPO
B45: CODAZZI | C45: 21000 | D45: 0.22 | E45: =+C45*D45 -> 4620 | F45: =+C45*0.055 -> 1155 | H45: =19370 -> 19370 | I45: 809.84 | J45: 0.195
B46: MLB | C46: 7000 | D46: 0.198 | E46: =+C46*D46 -> 1386 | F46: =+C46*0.05 -> 350 | H46: =6517.72 -> 6517.72 | I46: 712 | J46: 0.173
B47: CATATUMBO | C47: 23400 | D47: 0.235 | E47: =+C47*D47 -> 5499 | F47: =+C47*0.05 -> 1170 | H47: 22296 | I47: 816.537 | J47: 0.196
B48: SINÚ | C48: 6200 | D48: 0.22 | E48: =+C48*D48 -> 1364 | F48: =+C48*0.045 -> 279 | H48: 7317 | I48: 777.1 | J48: 0.187
B49: TOTAL | C49: =+SUM(C45:C48) -> 57600 | D49: =+E49/C49 -> 0.22342014 | E49: =+SUM(E45:E48) -> 12869 | F49: =+SUM(F45:F48) -> 2954 | G49: =+F49*41% -> 1211.14 | H49: =+SUM(H45:H48) -> 55500.72
B52: PROCESO OCTUBRE V2 2025 | H52: Censo | I52: Precio
C53: TM | D53: EXT | E53: CPO | F53: PK | G53: KPO
B54: CODAZZI | C54: 20500 | D54: 0.22 | E54: =+C54*D54 -> 4510 | F54: =+C54*0.055 -> 1127.5 | H54: 19640 | I54: 809.84 | J54: 0.195
B55: MLB | C55: 6732.22 | D55: 0.198 | E55: =+C55*D55 -> 1332.9796 | F55: =+C55*0.05 -> 336.611 | H55: 2050000 | I55: 712 | J55: 0.173
B56: CATATUMBO | C56: 21000 | D56: 0.235 | E56: =+C56*D56 -> 4935 | F56: =+C56*0.05 -> 1050 | H56: 20491 | I56: 816.537 | J56: 0.196
B57: SINÚ | C57: 6000 | D57: 0.22 | E57: =+C57*D57 -> 1320 | F57: =+C57*0.045 -> 270 | H57: 5500 | I57: 777.1 | J57: 0.187
B58: TOTAL | C58: =+SUM(C54:C57) -> 54232.22 | D58: =+E58/C58 -> 0.22307734 | E58: =+SUM(E54:E57) -> 12097.98 | F58: =+SUM(F54:F57) -> 2784.111 | G58: =+F58*41% -> 1141.4855 | H58: =+SUM(H54:H57) -> 2095631
B62: PROCESO OCTUBRE 2025
C63: TM | D63: EXT | E63: CPO | F63: PK | G63: KPO
B64: CODAZZI | C64: 17000 | D64: 0.216 | E64: =+D64*C64 -> 3672 | F64: 935
B65: MLB | C65: 8300 | D65: 0.198 | E65: =+D65*C65 -> 1643.4 | F65: 415
B66: CATATUMBO | C66: 23150 | D66: 0.235 | E66: =+D66*C66 -> 5440.25 | F66: 1157.5
B67: SINÚ | C67: 6630 | D67: 0.22 | E67: =+D67*C67 -> 1458.6 | F67: 298.35
B68: TOTAL | C68: =+SUM(C64:C67) -> 55080 | D68: =+E68/C68 -> 0.22175472 | E68: 12214.25 | F68: 2905.85 | G68: =+F68*41% -> 1191.3985
B71: PROCESO OCTUBRE V2 2025
C72: TM | D72: EXT | E72: CPO | F72: PK | G72: KPO
B73: CODAZZI | C73: =+C64*H73 -> 17617.284 | D73: 0.216 | E73: =+D73*C73 -> 3805.3333 | F73: 935 | H73: 1.0363108
B74: MLB | C74: =+C65*H74 -> 8601.3798 | D74: 0.198 | E74: =+D74*C74 -> 1703.0732 | F74: 415 | H74: 1.0363108
B75: CATATUMBO | C75: =+C66*H75 -> 23990.595 | D75: 0.235 | E75: =+D75*C75 -> 5637.7899 | F75: 1157.5 | H75: 1.0363108
B76: SINÚ | C76: =+C67*H76 -> 6870.7407 | D76: 0.22 | E76: =+D76*C76 -> 1511.563 | F76: 298.35 | H76: 1.0363108
B77: TOTAL | C77: =+SUM(C73:C76) -> 57080 | D77: =+E77/C77 -> 0.22175472 | E77: =+SUM(E73:E76) -> 12657.759 | F77: 2905.85 | G77: =+F77*41% -> 1191.3985
B81: PROCESO NOVIEMBRE 2025
C82: TM | D82: EXT | E82: CPO | F82: PK | G82: KPO
B83: CODAZZI | C83: =19770+500 -> 20270 | D83: 0.216 | E83: =+D83*C83 -> 4378.32 | F83: 935
B84: MLB | C84: 5500 | D84: 0.186 | E84: =+D84*C84 -> 1023 | F84: 415
B85: CATATUMBO | C85: 18500 | D85: 0.235 | E85: =+D85*C85 -> 4347.5 | F85: 1157.5
B86: SINÚ | C86: 6800 | D86: 0.224 | E86: =+D86*C86 -> 1523.2 | F86: 298.35
B87: TOTAL | C87: =+SUM(C83:C86) -> 51070 | D87: =+E87/C87 -> 0.22071706 | E87: =+SUM(E83:E86) -> 11272.02 | F87: =+SUM(F83:F86) -> 2805.85 | G87: =+F87*41% -> 1150.3985
B90: PROCESO NOVIEMBRE 2025
C91: TM | D91: EXT | E91: CPO | F91: PK | G91: KPO
B92: CODAZZI | C92: 21000 | D92: 0.216 | E92: =+D92*C92 -> 4536 | F92: 1155
B93: MLB | C93: 4900 | D93: 0.186 | E93: =+D93*C93 -> 911.4 | F93: 255
B94: CATATUMBO | C94: 20700 | D94: 0.235 | E94: =+D94*C94 -> 4864.5 | F94: 1025
B95: SINÚ | C95: 6540 | D95: 0.224 | E95: =+D95*C95 -> 1464.96 | F95: 289.8
B96: TOTAL | C96: =+SUM(C92:C95) -> 53140 | D96: =+E96/C96 -> 0.2216195 | E96: =+SUM(E92:E95) -> 11776.86 | F96: 2850 | G96: =+F96*41% -> 1168.5
B100: PROCESO DICIEMBRE 2025
C101: TM | D101: EXT | E101: CPO | F101: PK | G101: KPO | H101: CENSO | I101: NOV
B102: CODAZZI | C102: 18300 | D102: 0.216 | E102: =+D102*C102 -> 3952.8 | F102: 1155 | H102: 20610 | I102: 19036.5
B103: MLB | C103: 7000 | D103: 0.186 | E103: =+D103*C103 -> 1302 | F103: 255 | H103: 8609.99 | I103: 4811.2
B104: CATATUMBO | C104: 22000 | D104: 0.235 | E104: =+D104*C104 -> 5170 | F104: 1025 | H104: 18121 | I104: 22123.422
B105: SINÚ | C105: 5130 | D105: 0.22 | E105: =+D105*C105 -> 1128.6 | F105: 289.8 | H105: 5300 | I105: 6542.5
B106: TOTAL | C106: =+SUM(C102:C105) -> 52430 | D106: =+E106/C106 -> 0.22035857 | E106: =+SUM(E102:E105) -> 11553.4 | F106: 3000 | G106: =+F106*41% -> 1230 | H106: =+SUM(H102:H105) -> 52640.99 | I106: =+SUM(I102:I105) -> 52513.622
C113: CATATUMBO | D113: CODAZZI | E113: SINU
C114: 25 DOMINGO | D114: 25 DOMINGO
C115: 31 DOMINGO | D115: 31 DOMINGO

Sheet CENSO Y COSTOS
B2: COSTOS | CL2: CENSO ABRIL - JULIO
C4: Costos 27 Marzo | E4: Costos 31 Marzo | G4: Costos 31 Marzo | I4: Costos 7 Abril | K4: DIF | L4: VAR | M4: Costos 17 Abril | O4: Costos 24 Abril | Q4: DIF | R4: VAR | S4: Costos 11 Mayo | U4: DIF | V4: VAR | W4: Costos 17 Mayo | Y4: DIF | Z4: VAR | AA4: Costos 22 Mayo | AC4: DIF | AD4: VAR | AE4: Costos 31Mayo | AG4: DIF | AH4: VAR | AI4: Costos JUNIO | AK4: DIF | AL4: VAR | AM4: Costos 07 Junio | AO4: DIF | AP4: VAR | AQ4: Costos 07 Junio | AS4: DIF | AT4: VAR | AU4: Costos 19 Junio | AW4: DIF | AX4: VAR | AY4: Costos 26 Junio | BA4: DIF | BB4: VAR | BC4: Costos 30 Junio | BE4: DIF | BF4: VAR | BG4: Costos 17 Julio | BI4: DIF | BJ4: VAR | BK4: Costos 14 Agosto | BM4: DIF | BN4: VAR | BO4: Costos 31 Agosto | BQ4: DIF | BR4: VAR | BS4: Costos 18 Sept | BU4: DIF | BV4: VAR | BW4: Costos 3 Oct | BY4: DIF | BZ4: VAR | CA4: Costos 16 Nov | CC4: DIF | CD4: VAR | CE4: Costos 16 Nov | CG4: DIF | CH4: VAR | CL4: EXTRACTORA | CM4: ABRIL | CN4: MAYO | CO4: JUNIO | CP4: JULIO | CQ4: AGOSTO | CR4: SEPTIEMBRE
B5: EXTRACTORA | C5: $ | D5: % | E5: $ | F5: % | G5: $ | H5: % | I5: $ | J5: % | K5: $ | L5: % | M5: $ | N5: % | O5: $ | P5: % | Q5: $ | R5: % | S5: $ | T5: % | U5: $ | V5: % | W5: $ | X5: % | Y5: $ | Z5: % | AA5: $ | AB5: % | AC5: $ | AD5: % | AE5: $ | AF5: % | AG5: $ | AH5: % | AI5: $ | AJ5: % | AK5: $ | AL5: % | AM5: $ | AN5: % | AO5: $ | AP5: % | AQ5: $ | AR5: % | AS5: $ | AT5: % | AU5: $ | AV5: % | AW5: $ | AX5: % | AY5: $ | AZ5: % | BA5: $ | BB5: % | BC5: $ | BD5: % | BE5: $ | BF5: % | BG5: $ | BH5: % | BI5: $ | BJ5: % | BK5: $ | BL5: % | BM5: $ | BN5: % | BO5: $ | BP5: % | BQ5: $ | BR5: % | BS5: $ | BT5: % | BU5: $ | BV5: % | BW5: $ | BX5: % | BY5: $ | BZ5: % | CA5: $ | CB5: % | CC5: $ | CD5: % | CE5: $ | CF5: % | CG5: $ | CH5: % | CL5: CODAZZI | CM5: =21000+1300 -> 22300 | CN5: =18900+1300 -> 20200 | CO5: =17500+1280 -> 18780 | CP5: =17700+1450 -> 19150 | CQ5: =16500+1500 -> 18000 | CR5: =15500+1570 -> 17070
B6: CODAZZI | C6: 918 | D6: 0.197 | E6: 923 | F6: 0.1981 | G6: 923 | H6: 0.1981 | I6: 898 | J6: 0.1977 | K6: =+I6-E6 -> -25 | L6: =(+I6/E6)-1 -> -0.02708559 | M6: 901 | N6: 0.1984 | O6: 860.26 | P6: 0.198 | Q6: =+O6-M6 -> -40.74 | R6: =(+M6/I6)-1 -> 0.0033407572 | S6: 850.75 | T6: 0.194 | U6: =+S6-K15 -> 850.75 | V6: =(+S6/K15)-1 -> #DIV/0! | W6: 834 | X6: 0.1903 | Y6: =+W6-S6 -> -16.75 | Z6: =(+W6/S6)-1 -> -0.01968851 | AA6: 831.14 | AB6: 0.1895 | AC6: =+AA6-W6 -> -2.86 | AD6: =(+AA6/W6)-1 -> -0.0034292566 | AE6: 831.14 | AF6: 0.1895 | AG6: =+AE6-AA6 -> 0 | AH6: =(+AE6/AA6)-1 -> 0 | AJ6: 0.192 | AK6: =+AI6-AA6 -> -831.14 | AL6: =(+AJ6/AB6)-1 -> 0.013192612 | AM6: 823.38 | AN6: 0.1884 | AO6: =+AM6-AE6 -> -7.76 | AP6: =(+AM6/AE6)-1 -> -0.0093365739 | AQ6: 788.78 | AR6: 0.1884 | AS6: =+AQ6-AI6 -> 788.78 | AT6: =(+AQ6/AM6)-1 -> -0.04202191 | AU6: 802 | AV6: 0.1917 | AW6: =+AU6-AQ6 -> 13.22 | AX6: =(+AU6/AQ6)-1 -> 0.01676006 | AY6: 812.64 | AZ6: 0.1941 | BA6: =+AY6-AU6 -> 10.64 | BB6: =(+AY6/AU6)-1 -> 0.013266833 | BC6: 822.01 | BD6: 0.1964 | BE6: =+BC6-AY6 -> 9.37 | BF6: =(+BC6/AY6)-1 -> 0.011530321 | BG6: 811.7 | BH6: 0.1953 | BI6: =+BG6-BC6 -> -10.31 | BJ6: =(+BG6/BC6)-1 -> -0.012542426 | BK6: 834.1 | BL6: 0.1948 | BM6: =+BK6-BG6 -> 22.4 | BN6: =(+BK6/BG6)-1 -> 0.027596403 | BO6: 847.79 | BP6: 0.198 | BQ6: =+BO6-BK6 -> 13.69 | BR6: =(+BO6/BK6)-1 -> 0.0164129 | BS6: 858.21 | BT6: 0.1926 | BU6: =+BS6-BO6 -> 10.42 | BV6: =(+BS6/BO6)-1 -> 0.01229078 | BW6: 853.17 | BX6: 0.1915 | BY6: =+BW6-BS6 -> -5.04 | BZ6: =(+BW6/BS6)-1 -> -0.0058726885 | CA6: 847.47 | CB6: 0.1959 | CC6: =+CA6-BW6 -> -5.7 | CD6: =(+CA6/BW6)-1 -> -0.0066809663 | CE6: 883 | CF6: 20,41% | CG6: =+CE6-CA6 -> 35.53 | CH6: =(+CE6/CA6)-1 -> 0.041924788 | CL6: MLB | CM6: 9400 | CN6: 8300 | CO6: 8900 | CP6: 8700
B7: MLB | C7: 828.67 | D7: 0.1778 | E7: 823.81 | F7: 0.1767 | G7: 823.81 | H7: 0.1767 | I7: 768.32 | J7: 0.1692 | K7: =+I7-E7 -> -55.49 | L7: =(+I7/E7)-1 -> -0.067357765 | M7: 777.21 | N7: 0.1712 | O7: 762.93 | P7: 0.1702 | Q7: =+O7-M7 -> -14.28 | R7: =(+M7/I7)-1 -> 0.0115707 | S7: 719.27 | T7: 0.164 | U7: =+S7-K16 -> 719.27 | V7: =(+S7/K16)-1 -> #DIV/0! | W7: 726.78 | X7: 0.1657 | Y7: =+W7-S7 -> 7.51 | Z7: =(+W7/S7)-1 -> 0.010441142 | AA7: 747.23 | AB7: 0.1704 | AC7: =+AA7-W7 -> 20.45 | AD7: =(+AA7/W7)-1 -> 0.028137813 | AE7: 747.23 | AF7: 0.1704 | AG7: =+AE7-AA7 -> 0 | AH7: =(+AE7/AA7)-1 -> 0 | AJ7: 0.17 | AK7: =+AI7-AA7 -> -747.23 | AL7: =(+AJ7/AB7)-1 -> -0.0023474178 | AM7: 715.42 | AN7: 0.1631 | AO7: =+AM7-AE7 -> -31.81 | AP7: =(+AM7/AE7)-1 -> -0.042570561 | AQ7: 693.2 | AR7: 0.1656 | AS7: =+AQ7-AI7 -> 693.2 | AT7: =(+AQ7/AM7)-1 -> -0.031058679 | AU7: 699.3 | AV7: 0.167 | AW7: =+AU7-AQ7 -> 6.1 | AX7: =(+AU7/AQ7)-1 -> 0.0087997692 | AY7: 700.4 | AZ7: 0.1673 | BA7: =+AY7-AU7 -> 1.1 | BB7: =(+AY7/AU7)-1 -> 0.0015730016 | BC7: 714.9 | BD7: 0.1708 | BE7: =+BC7-AY7 -> 14.5 | BF7: =(+BC7/AY7)-1 -> 0.020702456 | BG7: 712.6 | BH7: 0.1714 | BI7: =+BG7-BC7 -> -2.3 | BJ7: =(+BG7/BC7)-1 -> -0.0032172332 | BK7: 724.9 | BL7: 0.1693 | BM7: =+BK7-BG7 -> 12.3 | BN7: =(+BK7/BG7)-1 -> 0.017260735 | BO7: 743.2 | BP7: 0.1736 | BQ7: =+BO7-BK7 -> 18.3 | BR7: =(+BO7/BK7)-1 -> 0.025244861 | BS7: 756.8 | BT7: 0.1699 | BU7: =+BS7-BO7 -> 13.6 | BV7: =(+BS7/BO7)-1 -> 0.018299247 | BW7: 794.1 | BX7: 0.1782 | BY7: =+BW7-BS7 -> 37.3 | BZ7: =(+BW7/BS7)-1 -> 0.049286469 | CA7: 748.5 | CB7: 0.173 | CC7: =+CA7-BW7 -> -45.6 | CD7: =(+CA7/BW7)-1 -> -0.057423498 | CE7: 740 | CF7: 17,11% | CG7: =+CE7-CA7 -> -8.5 | CH7: =(+CE7/CA7)-1 -> -0.011356045 | CL7: CATATUMBO | CM7: 21824 | CN7: 19372 | CO7: 18298 | CP7: 17581 | CQ7: 17872 | CR7: 20519
B8: CATATUMBO | C8: 913.31 | D8: 0.1959 | E8: 904.26 | F8: 0.194 | G8: 904.26 | H8: 0.194 | I8: 866.44 | J8: 0.1908 | K8: =+I8-E8 -> -37.82 | L8: =(+I8/E8)-1 -> -0.041824254 | M8: 864.31 | N8: 0.1903 | O8: 762.86 | P8: 0.1898 | Q8: =+O8-M8 -> -101.45 | R8: =(+M8/I8)-1 -> -0.0024583353 | S8: 796.3 | T8: 0.1816 | U8: =+S8-K17 -> 796.3 | V8: =(+S8/K17)-1 -> #DIV/0! | W8: 817.68 | X8: 0.1865 | Y8: =+W8-S8 -> 21.38 | Z8: =(+W8/S8)-1 -> 0.026849177 | AA8: 828.76 | AB8: 0.189 | AC8: =+AA8-W8 -> 11.08 | AD8: =(+AA8/W8)-1 -> 0.013550533 | AE8: 828.76 | AF8: 0.189 | AG8: =+AE8-AA8 -> 0 | AH8: =(+AE8/AA8)-1 -> 0 | AJ8: 0.192 | AK8: =+AI8-AA8 -> -828.76 | AL8: =(+AJ8/AB8)-1 -> 0.015873016 | AM8: 794.63 | AN8: 0.1812 | AO8: =+AM8-AE8 -> -34.13 | AP8: =(+AM8/AE8)-1 -> -0.041182007 | AQ8: 796.19 | AR8: 0.1816 | AS8: =+AQ8-AI8 -> 796.19 | AT8: =(+AQ8/AM8)-1 -> 0.0019631778 | AU8: 809.798 | AV8: 0.1934 | AW8: =+AU8-AQ8 -> 13.608 | AX8: =(+AU8/AQ8)-1 -> 0.017091398 | AY8: 810.222 | AZ8: 0.1935 | BA8: =+AY8-AU8 -> 0.424 | BB8: =(+AY8/AU8)-1 -> 0.00052358736 | BC8: 810.439 | BD8: 0.1936 | BE8: =+BC8-AY8 -> 0.217 | BF8: =(+BC8/AY8)-1 -> 0.00026782783 | BG8: 817.456 | BH8: 0.1967 | BI8: =+BG8-BC8 -> 7.017 | BJ8: =(+BG8/BC8)-1 -> 0.0086582704 | BK8: 824.367 | BL8: 0.1926 | BM8: =+BK8-BG8 -> 6.911 | BN8: =(+BK8/BG8)-1 -> 0.0084542777 | BO8: 830.931 | BP8: 0.1941 | BQ8: =+BO8-BK8 -> 6.564 | BR8: =(+BO8/BK8)-1 -> 0.007962473 | BS8: 861.851 | BT8: 0.1934 | BU8: =+BS8-BO8 -> 30.92 | BV8: =(+BS8/BO8)-1 -> 0.037211273 | BW8: 868.818 | BX8: 0.195 | BY8: =+BW8-BS8 -> 6.967 | BZ8: =(+BW8/BS8)-1 -> 0.0080837639 | CA8: 847.967 | CB8: 0.196 | CC8: =+CA8-BW8 -> -20.851 | CD8: =(+CA8/BW8)-1 -> -0.023999273 | CE8: 822 | CF8: 19,00% | CG8: =+CE8-CA8 -> -25.967 | CH8: =(+CE8/CA8)-1 -> -0.030622654 | CL8: SINÚ | CM8: 9500 | CN8: 7700 | CO8: 7500 | CP8: 7700
B9: SINÚ | C9: 858.92 | D9: 0.1842 | E9: 859.88 | F9: 0.1845 | G9: 859.88 | H9: 0.1845 | I9: 825.77 | J9: 0.1818 | K9: =+I9-E9 -> -34.11 | L9: =(+I9/E9)-1 -> -0.039668326 | M9: 828.09 | N9: 0.1824 | O9: 836.83 | P9: 0.1843 | Q9: =+O9-M9 -> 8.74 | R9: =(+M9/I9)-1 -> 0.002809499 | S9: 806.02 | T9: 0.1838 | U9: =+S9-K18 -> 806.02 | V9: =(+S9/K18)-1 -> #DIV/0! | W9: 803.71 | X9: 0.1833 | Y9: =+W9-S9 -> -2.31 | Z9: =(+W9/S9)-1 -> -0.0028659338 | AA9: 807 | AB9: 0.184 | AC9: =+AA9-W9 -> 3.29 | AD9: =(+AA9/W9)-1 -> 0.0040935163 | AE9: 807 | AF9: 0.184 | AG9: =+AE9-AA9 -> 0 | AH9: =(+AE9/AA9)-1 -> 0 | AJ9: 0.184 | AK9: =+AI9-AA9 -> -807 | AL9: =(+AJ9/AB9)-1 -> 0 | AM9: 798.79 | AN9: 0.1821 | AO9: =+AM9-AE9 -> -8.21 | AP9: =(+AM9/AE9)-1 -> -0.010173482 | AQ9: 774.6 | AR9: 0.185 | AS9: =+AQ9-AI9 -> 774.6 | AT9: =(+AQ9/AM9)-1 -> -0.030283303 | AU9: 780.7 | AV9: 0.1865 | AW9: =+AU9-AQ9 -> 6.1 | AX9: =(+AU9/AQ9)-1 -> 0.0078750323 | AY9: 779.2 | AZ9: 0.1861 | BA9: =+AY9-AU9 -> -1.5 | BB9: =(+AY9/AU9)-1 -> -0.0019213526 | BC9: 781.7 | BD9: 0.1867 | BE9: =+BC9-AY9 -> 2.5 | BF9: =(+BC9/AY9)-1 -> 0.0032084189 | BG9: 775.8 | BH9: 0.1866 | BI9: =+BG9-BC9 -> -5.9 | BJ9: =(+BG9/BC9)-1 -> -0.0075476526 | BK9: 800 | BL9: 0.1869 | BM9: =+BK9-BG9 -> 24.2 | BN9: =(+BK9/BG9)-1 -> 0.031193607 | BO9: 802 | BP9: 0.1873 | BQ9: =+BO9-BK9 -> 2 | BR9: =(+BO9/BK9)-1 -> 0.0025 | BS9: 829.4 | BT9: 0.1862 | BU9: =+BS9-BO9 -> 27.4 | BV9: =(+BS9/BO9)-1 -> 0.034164589 | BW9: 841.7 | BX9: 0.1889 | BY9: =+BW9-BS9 -> 12.3 | BZ9: =(+BW9/BS9)-1 -> 0.014829998 | CA9: 811 | CB9: 0.1875 | CC9: =+CA9-BW9 -> -30.7 | CD9: =(+CA9/BW9)-1 -> -0.036473803 | CE9: 811 | CF9: 0.1875 | CG9: =+CE9-CA9 -> 0 | CH9: =(+CE9/CA9)-1 -> 0 | CL9: REPELON | CM9: 91.9 | CN9: 137.8 | CO9: 137.8 | CP9: 202.1 | CQ9: 220.4 | CR9: 119.4
CL11: TOTAL | CM11: =+SUM(CM5:CM9) -> 63115.9 | CN11: =+SUM(CN5:CN9) -> 55709.8 | CO11: =+SUM(CO5:CO9) -> 53615.8 | CP11: =+SUM(CP5:CP9) -> 53333.1 | CQ11: =+SUM(CQ5:CQ9) -> 36092.4 | CR11: =+SUM(CR5:CR9) -> 37708.4

Sheet ACUMULADO 2025
B2: ACUMULADO 2025
C4: Enero | D4: Febrero | E4: Marzo | F4: Abril | G4: Mayo | H4: Junio | I4: Julio | J4: Agosto | K4: Septiembre | L4: Octubre | M4: Noviembre | N4: Diciembre | O4: TOTAL
A5: Codazzi | B5: RFF Procesada 2025 | C5: 23942 | D5: 20911 | E5: 23306 | F5: 22844 | G5: 19765 | H5: 16856.57 | I5: 20885.8 | J5: 22286 | K5: 21258.25 | L5: 17000 | M5: 18870.5 | O5: =+SUM(C5:H5) -> 127624.57
A6: MLB | B6: RFF Procesada 2025 | C6: 11997 | D6: 10793 | E6: 12894.88 | F6: 10543 | G6: 9879 | H6: 6822.47 | I6: 7206.91 | J6: 7738.57 | K6: 7317.06 | L6: 8300 | M6: 4692 | O6: =+SUM(C6:H6) -> 62929.35
A7: A&G | B7: RFF Procesada 2025 | C7: 16844.237 | D7: 18554 | E7: 18827.581 | F7: 17972 | G7: 18658.109 | H7: 16956.319 | I7: 21020.219 | J7: 19236.605 | K7: 22461.803 | L7: 23150 | M7: 21618.532 | O7: =+SUM(C7:H7) -> 107812.25
A8: Sinu | B8: RFF Procesada 2025 | C8: 6035 | D8: 7270 | E8: 8455 | F8: 7257 | G8: 7471 | H8: 6237.4 | I8: 6035.2 | J8: 6085.8 | K8: 6505.8 | L8: 6630 | M8: 6520.5 | O8: =+SUM(C8:H8) -> 42725.4
A9: TOTAL | C9: =+SUM(C5:C8) -> 58818.237 | D9: =+SUM(D5:D8) -> 57528 | E9: =+SUM(E5:E8) -> 63483.461 | F9: =+SUM(F5:F8) -> 58616 | G9: =+SUM(G5:G8) -> 55773.109 | H9: =+SUM(H5:H8) -> 46872.759 | I9: =+SUM(I5:I8) -> 55148.129 | J9: =+SUM(J5:J8) -> 55346.975 | ... O9: =+SUM(O5:O8) -> 341091.57
C11: Enero | D11: Febrero | E11: Marzo | F11: Abril | G11: Mayo | H11: Junio | I11: Julio | J11: Agosto | K11: Septiembre | L11: Octubre | M11: Noviembre | N11: Diciembre | O11: TOTAL
A12: Codazzi | B12: Producción CPO 2025 | C12: 4796 | D12: 4277.697 | E12: 4811.63 | F12: 4777 | G12: 4282 | H12: 3870.886 | I12: 4752.241 | J12: 4913.524 | K12: 4676.276 | L12: 3672 | M12: 4194.884 | O12: =+SUM(C12:H12) -> 26815.213
A13: MLB | B13: Producción CPO 2025 | C13: 2121 | D13: 1908 | E13: 2394 | F13: 1993 | G13: 1960 | H13: 1385.587 | I13: 1471.187 | J13: 1548.524 | K13: 1445.8646 | L13: 1643.4 | M13: 872.131 | O13: =+SUM(C13:H13) -> 11761.587
A14: A&G | B14: Producción CPO 2025 | C14: 3878.765 | D14: 4216 | E14: 4283 | F14: 4119 | G14: 4405 | H14: 4021.311 | I14: 5086.516 | J14: 4552.976 | K14: 5339.6564 | L14: 5440.25 | M14: 5057.615 | O14: =+SUM(C14:H14) -> 24923.076
A15: Sinu | B15: Producción CPO 2025 | C15: 1265 | D15: 1462 | E15: 1758 | F15: 1581 | G15: 1724 | H15: 1465.531 | I15: 1390.212 | J15: 1331.045 | K15: 1455.4228 | L15: 1458.6 | M15: 1436.495 | O15: =+SUM(C15:H15) -> 9255.531
A16: TOTAL | C16: =+SUM(C12:C15) -> 12060.765 | D16: =+SUM(D12:D15) -> 11863.697 | E16: =+SUM(E12:E15) -> 13246.63 | F16: =+SUM(F12:F15) -> 12470 | G16: =+SUM(G12:G15) -> 12371 | H16: =+SUM(H12:H15) -> 10743.315 | I16: =+SUM(I12:I15) -> 12700.156 | J16: =+SUM(J12:J15) -> 12346.069 | ... O16: =+SUM(O12:O15) -> 72755.407
C18: Enero | D18: Febrero | E18: Marzo | F18: Abril | G18: Mayo | H18: Junio | I18: Julio | J18: Agosto | K18: Septiembre | L18: Octubre | M18: Noviembre | N18: Diciembre | O18: TOTAL
A19: Codazzi | B19: Extracción 2025 | C19: =+C12/C5 -> 0.20031743 | D19: =+D12/D5 -> 0.20456683 | E19: =+E12/E5 -> 0.20645456 | F19: =+F12/F5 -> 0.20911399 | G19: =+G12/G5 -> 0.21664559 | H19: =+H12/H5 -> 0.22963663 | I19: =+I12/I5 -> 0.22753455 | J19: =+J12/J5 -> 0.22047581 | ... M19: =+M12/M5 -> 0.22229851 | O19: =+O12/O5 -> 0.21011011
A20: MLB | B20: Extracción 2025 | C20: =+C13/C6 -> 0.1767942 | D20: =+D13/D6 -> 0.17678125 | E20: =+E13/E6 -> 0.18565508 | F20: =+F13/F6 -> 0.18903538 | G20: =+G13/G6 -> 0.19840065 | H20: =+H13/H6 -> 0.2030917 | I20: =+I13/I6 -> 0.20413561 | J20: =+J13/J6 -> 0.20010467 | ... M20: =+M13/M6 -> 0.18587617 | O20: =+O13/O6 -> 0.18690145
A21: A&G | B21: Extracción 2025 | C21: =+C14/C7 -> 0.23027253 | D21: =+D14/D7 -> 0.22722863 | E21: =+E14/E7 -> 0.22748541 | F21: =+F14/F7 -> 0.22918985 | G21: =+G14/G7 -> 0.23609038 | H21: =+H14/H7 -> 0.23715707 | I21: =+I14/I7 -> 0.24198206 | J21: =+J14/J7 -> 0.23668293 | ... M21: =+M14/M7 -> 0.23394812 | O21: =+O14/O7 -> 0.2311711
A22: Sinu | B22: Extracción 2025 | C22: =+C15/C8 -> 0.2096106 | D22: =+D15/D8 -> 0.20110041 | E22: =+E15/E8 -> 0.20792431 | F22: =+F15/F8 -> 0.21785862 | G22: =+G15/G8 -> 0.23075893 | H22: =+H15/H8 -> 0.23495864 | I22: =+I15/I8 -> 0.23035061 | J22: =+J15/J8 -> 0.21871323 | ... M22: =+M15/M8 -> 0.22030442 | O22: =+O15/O8 -> 0.21662831
A23: TOTAL | C23: =IFERROR(+C16/C9,"") -> 0.20505145 | D23: =IFERROR(+D16/D9,"") -> 0.20622474 | E23: =IFERROR(+E16/E9,"") -> 0.20866269 | F23: =IFERROR(+F16/F9,"") -> 0.21274055 | G23: =IFERROR(+G16/G9,"") -> 0.2218094 | H23: =IFERROR(+H16/H9,"") -> 0.22920168 | I23: =IFERROR(+I16/I9,"") -> 0.23029169 | J23: =IFERROR(+J16/J9,"") -> 0.22306673 | ... O23: =IFERROR(+O16/O9,"") -> 0.21330169
